Workbook

Sheet README
A1: Public lab reports meet quick-commerce demand: MVP product list
A2: Built 2 Oct 2026 for the Food Quality Rater MVP. Everything here was read from public web pages on that date. I did not open lab PDFs, buy products or run any test.
A4: What this is
A5: Purpose | B5: A starting list for the MVP: Indian packaged-food and nutrition products whose lab test reports (or lab-backed ratings) are publicly listed, checked against Blinkit, Zepto, Instamart and BigBasket so you can start with products people actually buy.
A6: Where to look first | B6: Shortlist: one row per quick-commerce (QC) product line I checked, ranked by QC score. All reports: every report row from four public sources, filterable. QC listings: the listing links and ratings counts behind every platform flag. QC signals: published data on what sells on QC. Report hubs: where each source keeps its reports and what the terms look like. Scoring: every weight and threshold. Blue cells are editable and everything recalculates.
A7: What the data shows | B7: Trustified is not only supplements. Its list includes mainstream staples and snacks that sell heavily on QC: Amul, Mother Dairy and Country Delight milk, Aashirvaad atta, Tata Salt, MDH and Everest masalas, Kellogg's, Cadbury, Lindt and Amul chocolate, Haldiram's. Many of those carry a Failed verdict, which is where a Trust Report matters most and where the PRD's publication gate applies.
A9: Key numbers (live formulas)
A10: Report rows | B10: =COUNTA('All reports'!$A$5:$A$249) -> 245
A11: from Trustified Pass/Fail | B11: =COUNTIF('All reports'!$J$5:$J$249,"Trustified Pass/Fail") -> 179
A12: from Trustified NMR (honey) | B12: =COUNTIF('All reports'!$J$5:$J$249,"Trustified NMR") -> 6
A13: from The Whole Truth's hub | B13: =COUNTIF('All reports'!$J$5:$J$249,"The Whole Truth hub") -> 6
A14: from Unbox Health | B14: =COUNTIF('All reports'!$J$5:$J$249,"Unbox Health") -> 54
A15: Rows marked Passed | B15: =COUNTIF('All reports'!$F$5:$F$249,"Passed") -> 100
A16: Rows marked Failed | B16: =COUNTIF('All reports'!$F$5:$F$249,"Failed") -> 56
A17: Rows marked Expired (incl. Unbox) | B17: =COUNTIF('All reports'!$F$5:$F$249,"Expired") -> 34
A18: Rows on a QC product line I checked | B18: =SUMPRODUCT(--('All reports'!$M$5:$M$249<>"")) -> 50
A19: QC product lines checked | B19: =COUNTIF('All reports'!$Z$5:$Z$249,1) -> 39
A20: of which listed on 3 or more platforms | B20: =COUNTIFS('All reports'!$Z$5:$Z$249,1,'All reports'!$S$5:$S$249,">=3") -> 21
A21: of which the latest report is a Fail | B21: =COUNTIFS('All reports'!$Z$5:$Z$249,1,'All reports'!$F$5:$F$249,"Failed") -> 12
A22: Highest ratings count seen on a listing | B22: =MAX('All reports'!$T$5:$T$249) -> 1581833
A23: Maximum possible QC score at current weights | B23: =Scoring!B19 -> 14
A25: How the QC score works
A26: Formula | B26: QC score = (confirmed platforms x 1 + demand tier x 2) x match factor + 2 if the category is a QC top-seller category + freshness points. Freshness: 2 if the report is under 12 months old, 1 if 12-24 months, 0 if older, 1 if undated, 0 if Expired. Maximum 14 at the default weights. The verdict does not change the score, so a failing product on a best-selling line ranks high on purpose.
A27: Platform flags (Blinkit to BigBasket) | B27: Y = a listing page or brand page seen on 2 Oct 2026. ? = only a third-party or cached page; not scored. - = not seen in my checks (not proof it is not sold). Blank = line not checked.
A28: QC match | B28: Exact = same product as the tested sample, pack size aside. Same line = same brand line, tested SKU not confirmed on the listing. Variant differs = the brand line is listed but it is a different variant from the one tested. Factors are 1, 0.75 and 0.5.
A29: Top ratings count | B29: The highest ratings count on any listing of that line. Cumulative and pooled across packs and pincodes. It is a popularity proxy, not a sales rank; QC apps publish no rank. n/c = no ratings count captured on any listing of that line.
A30: Primary for line | B30: 1 marks the row that stands for its QC line on the Shortlist: the most recently dated report, first row on a tie. Other rows for the line stay in All reports.
A31: Verdict | B31: Trustified's own label (Passed, Failed, Expired, Not recommended; 'No status shown' where the tile has none). 'Report published' means a lab report is public but carries no verdict (Trustified NMR honey tests, The Whole Truth's hub). Unbox rows: Rated = current grade, Expired = shown as Previously Rated, Listed, rating not captured = on Unbox but the grade was not captured.
A33: Method
A34: 1. Reports | B34: Read Trustified's public Pass/Fail list, category pages and NMR page, The Whole Truth's batch hub, and Unbox Health's explore pages (grades are visible without login, full reports are not).
A35: 2. QC check | B35: For lab-tested products that looked like likely sellers, I searched Blinkit, Zepto, Instamart and BigBasket listing pages and recorded the listing, pack, price, ratings count and URL on QC listings. The check covers only the lines in the Shortlist.
A36: 3. Best-seller proxy | B36: QC platforms publish no sales ranks. I used ratings counts on product pages as a popularity proxy and published category rankings (QC signals) to flag top categories.
A37: 4. Not done | B37: No lab report was re-verified. Pack size or SKU code, lab accreditation, parameters tested and the reason for any Fail are not captured: they sit inside each report. Trustified and Whole Truth rows are batch-level lab evidence; Unbox rows are a competitor's grade for a bought sample.
A39: Caveats
A40: 1. Coverage | B40: QC columns are filled only for the lines checked; blank means not checked. Not yet checked (search rate limit): Daawat Brown Rice, Everest Garam Masala, Epigamia Turbo, Patanjali Cow Ghee and Amul Cheese Cubes.
A41: 2. Older Trustified entries | B41: Trustified's list continues with about 85 older entries (the ones I sampled are 2023-24 and mostly Expired). I left them out on purpose, so this is not the full Trustified archive.
A42: 3. Snapshot | B42: Listings, prices and ratings were read on 2 Oct 2026 without a delivery pincode. Availability varies by pincode and changes daily. Zepto and Blinkit pages sometimes show a different pack or variant; QC match and the notes say where.
A43: 4. Reuse terms | B43: Trustified shows no API or reuse terms. Showing its report content inside the product needs written permission; linking out is the safe default (PRD critical path). Unbox is a direct competitor and gates reports behind a login. Whole Truth reports are the brand's own PDFs; ask before reusing.
A44: 5. Reports are per batch | B44: A report covers one batch of one SKU. A Pass on one batch is not a verdict on the line. Failed and Not recommended rows need the PRD publication gate (legal check, brand notice, 7-day reply) before anything is shown.
A45: 6. Data quirks | B45: Three Trustified rows (Farmley Makhana, Noto, Minus 30) carry Jan 2025 publish dates that look earlier than their batch codes imply. MuscleBlaze Iso Zero, MuscleBlaze Performance Whey, Nutrabay Concentrate Whey and As It Is Atom Creatine show no batch or date on the list page. Gritzo age bands read '13 years' on Trustified. A '6.6 lac' ratings card on Blinkit (Amul Masti pouch curd) is read as 660,000.
A47: Sources
A48: Trustified Pass/Fail | B48: https://www.trustified.in/passandfail
A49: Trustified NMR reports | B49: https://www.trustified.in/nmr-reports
A50: Trustified nut butters | B50: https://www.trustified.in/nut-butters
A51: Trustified protein bar | B51: https://www.trustified.in/proteinbar
A52: Trustified dark chocolate | B52: https://www.trustified.in/dark-chocolate
A53: Trustified breakfast cereals | B53: https://www.trustified.in/items/breakfastcereals
A54: The Whole Truth lab-report hub | B54: https://twtprotein.notion.site/Protein-Lab-Test-Reports-1d0fae391f3f4c8f9f398306890cedff
A55: Unbox Health explore | B55: https://www.unboxhealth.in/explore
A56: NewsBytes: Blinkit and Instamart 2024 orders | B56: https://www.newsbytesapp.com/news/business/chips-colas-condoms-rule-shopping-carts-on-quick-commerce-platforms/story
A57: afaqs: Zepto 2025 data | B57: https://www.afaqs.com/news/mktg/zeptos-2025-data-maps-changing-shopping-habits-across-indian-cities-10954599
A58: BestMediaInfo: Instamart 2025 | B58: https://bestmediainfo.com/insights/gold-iphones-666-roses-a-minute-what-indians-ordered-on-instamart-in-2025-might-surprise-you-10930811
A59: Media4Growth: Blinkit billboards | B59: https://www.media4growth.com/showcase/campaigns/blinkit-turns-indias-shopping-data-into-year-end-ooh-humour-81597
... A63: Listing pages | B63: See the QC listings sheet: one URL per row.
A65: Suggested next steps
A66: 1 | B66: Settle the Trustified licence question first; it is the critical path in the PRD. Until then, link out only.
A67: 2 | B67: Run the unchecked lines and the biggest-selling untested-on-QC rows through the same listing check.
A68: 3 | B68: Re-check the top Shortlist lines in each app with a real delivery pincode before relying on any flag.

Sheet Shortlist
A1: Shortlist: quick-commerce product lines with a public lab report, ranked by QC score
A2: One row per product line I checked on Blinkit, Zepto, Instamart and BigBasket. Each line is represented by its most recent dated report. Weights and thresholds: Scoring sheet. Verdicts do not change the rank.
A4: QC rank | B4: Brand | C4: Product (as listed by the report source) | D4: Category | E4: Verdict | F4: Report date | G4: Lab | H4: Batch tested | I4: Source | J4: Platforms with a listing | K4: Top ratings count | L4: Demand tier (0-3) | M4: QC score | N4: QC match | O4: Other report rows for this line | P4: Report | Q4: QC listing | R4: Publish route | S4: Helper: row in All reports
A5: 1 | B5: =IF($S5="","",INDEX('All reports'!$B$5:$B$249,$S5)) -> Mother Dairy | C5: =IF($S5="","",INDEX('All reports'!$C$5:$C$249,$S5)) -> Cow Milk | D5: =IF($S5="","",INDEX('All reports'!$E$5:$E$249,$S5)) -> Milk | E5: =IF($S5="","",INDEX('All reports'!$F$5:$F$249,$S5)) -> Failed | F5: =IF($S5="","",IF(INDEX('All reports'!$G$5:$G$249,$S5)="","",INDEX('All reports'!$G$5:$G$249,$S5))) -> 46061 | G5: =IF($S5="","",INDEX('All reports'!$I$5:$I$249,$S5)) -> Eurofins | H5: =IF($S5="","",IF(INDEX('All reports'!$H$5:$H$249,$S5)="","",INDEX('All reports'!$H$5:$H$249,$S5))) -> (05)05NOV25SZ5M | I5: =IF($S5="","",INDEX('All reports'!$J$5:$J$249,$S5)) -> Trustified Pass/Fail | J5: =IF($S5="","",SUBSTITUTE(TRIM(IF(INDEX('All reports'!$O$5:$O$249,$S5)="Y","Blinkit",IF(INDEX('All reports'!$O$5:$O$249,$S5)="?","Blinkit?",""))&" "&IF(INDEX('All reports'!$P$5:$P$249,$S5)="Y","Zepto",IF(INDEX('All reports'!$P$5:$P$249,$S5)="?","Zepto?",""))&" "&IF(INDEX('All reports'!$Q$5:$Q$249,$S5)="Y","Instamart",IF(INDEX('All reports'!$Q$5:$Q$249,$S5)="?","Instamart?",""))&" "&IF(INDEX('All reports'!$R$5:$R$249,$S5)="Y","BigBasket",IF(INDEX('All reports'!$R$5:$R$249,$S5)="?","BigBasket?","")))," "," · ")) -> Blinkit · Zepto · Instamart · BigBasket | K5: =IF($S5="","",INDEX('All reports'!$T$5:$T$249,$S5)) -> 302321 | L5: =IF($S5="","",INDEX('All reports'!$U$5:$U$249,$S5)) -> 3 | M5: =IF($S5="","",INDEX('All reports'!$Y$5:$Y$249,$S5)) -> 14 | N5: =IF($S5="","",IF(INDEX('All reports'!$N$5:$N$249,$S5)="","",INDEX('All reports'!$N$5:$N$249,$S5))) -> Exact | O5: =IF($S5="","",COUNTIF('All reports'!$M$5:$M$249,INDEX('All reports'!$M$5:$M$249,$S5))-1) -> 0 | P5: =IFERROR(HYPERLINK(INDEX('All reports'!$L$5:$L$249,$S5),"Open report"),"") -> Open report | Q5: =IFERROR(HYPERLINK(INDEX('QC listings'!$H$5:$H$200,MATCH(INDEX('All reports'!$M$5:$M$249,$S5),'QC listings'!$A$5:$A$200,0)),"Open listing"),"") -> Open listing | R5: =IF($S5="","",INDEX('All reports'!$AC$5:$AC$249,$S5)) -> Link out; licence needed to display; run the PRD publication gate first (negative verdict) | S5: =IFERROR(MATCH($A5,'All reports'!$AA$5:$AA$249,0),"") -> 5
A6: 2 | B6: =IF($S6="","",INDEX('All reports'!$B$5:$B$249,$S6)) -> Amul | C6: =IF($S6="","",INDEX('All reports'!$C$5:$C$249,$S6)) -> Gold Milk | D6: =IF($S6="","",INDEX('All reports'!$E$5:$E$249,$S6)) -> Milk | E6: =IF($S6="","",INDEX('All reports'!$F$5:$F$249,$S6)) -> Failed | F6: =IF($S6="","",IF(INDEX('All reports'!$G$5:$G$249,$S6)="","",INDEX('All reports'!$G$5:$G$249,$S6))) -> 46061 | G6: =IF($S6="","",INDEX('All reports'!$I$5:$I$249,$S6)) -> Eurofins | H6: =IF($S6="","",IF(INDEX('All reports'!$H$5:$H$249,$S6)="","",INDEX('All reports'!$H$5:$H$249,$S6))) -> SR26DM | I6: =IF($S6="","",INDEX('All reports'!$J$5:$J$249,$S6)) -> Trustified Pass/Fail | J6: =IF($S6="","",SUBSTITUTE(TRIM(IF(INDEX('All reports'!$O$5:$O$249,$S6)="Y","Blinkit",IF(INDEX('All reports'!$O$5:$O$249,$S6)="?","Blinkit?",""))&" "&IF(INDEX('All reports'!$P$5:$P$249,$S6)="Y","Zepto",IF(INDEX('All reports'!$P$5:$P$249,$S6)="?","Zepto?",""))&" "&IF(INDEX('All reports'!$Q$5:$Q$249,$S6)="Y","Instamart",IF(INDEX('All reports'!$Q$5:$Q$249,$S6)="?","Instamart?",""))&" "&IF(INDEX('All reports'!$R$5:$R$249,$S6)="Y","BigBasket",IF(INDEX('All reports'!$R$5:$R$249,$S6)="?","BigBasket?","")))," "," · ")) -> Blinkit · Zepto · BigBasket | K6: =IF($S6="","",INDEX('All reports'!$T$5:$T$249,$S6)) -> 1581833 | L6: =IF($S6="","",INDEX('All reports'!$U$5:$U$249,$S6)) -> 3 | M6: =IF($S6="","",INDEX('All reports'!$Y$5:$Y$249,$S6)) -> 13 | N6: =IF($S6="","",IF(INDEX('All reports'!$N$5:$N$249,$S6)="","",INDEX('All reports'!$N$5:$N$249,$S6))) -> Exact | O6: =IF($S6="","",COUNTIF('All reports'!$M$5:$M$249,INDEX('All reports'!$M$5:$M$249,$S6))-1) -> 0 | P6: =IFERROR(HYPERLINK(INDEX('All reports'!$L$5:$L$249,$S6),"Open report"),"") -> Open report | Q6: =IFERROR(HYPERLINK(INDEX('QC listings'!$H$5:$H$200,MATCH(INDEX('All reports'!$M$5:$M$249,$S6),'QC listings'!$A$5:$A$200,0)),"Open listing"),"") -> Open listing | R6: =IF($S6="","",INDEX('All reports'!$AC$5:$AC$249,$S6)) -> Link out; licence needed to display; run the PRD publication gate first (negative verdict) | S6: =IFERROR(MATCH($A6,'All reports'!$AA$5:$AA$249,0),"") -> 1
A7: 3 | B7: =IF($S7="","",INDEX('All reports'!$B$5:$B$249,$S7)) -> Amul | C7: =IF($S7="","",INDEX('All reports'!$C$5:$C$249,$S7)) -> Taaza Homogenised Toned Milk | D7: =IF($S7="","",INDEX('All reports'!$E$5:$E$249,$S7)) -> Milk | E7: =IF($S7="","",INDEX('All reports'!$F$5:$F$249,$S7)) -> Passed | F7: =IF($S7="","",IF(INDEX('All reports'!$G$5:$G$249,$S7)="","",INDEX('All reports'!$G$5:$G$249,$S7))) -> 46061 | G7: =IF($S7="","",INDEX('All reports'!$I$5:$I$249,$S7)) -> Eurofins | H7: =IF($S7="","",IF(INDEX('All reports'!$H$5:$H$249,$S7)="","",INDEX('All reports'!$H$5:$H$249,$S7))) -> MAC2691 | I7: =IF($S7="","",INDEX('All reports'!$J$5:$J$249,$S7)) -> Trustified Pass/Fail | J7: =IF($S7="","",SUBSTITUTE(TRIM(IF(INDEX('All reports'!$O$5:$O$249,$S7)="Y","Blinkit",IF(INDEX('All reports'!$O$5:$O$249,$S7)="?","Blinkit?",""))&" "&IF(INDEX('All reports'!$P$5:$P$249,$S7)="Y","Zepto",IF(INDEX('All reports'!$P$5:$P$249,$S7)="?","Zepto?",""))&" "&IF(INDEX('All reports'!$Q$5:$Q$249,$S7)="Y","Instamart",IF(INDEX('All reports'!$Q$5:$Q$249,$S7)="?","Instamart?",""))&" "&IF(INDEX('All reports'!$R$5:$R$249,$S7)="Y","BigBasket",IF(INDEX('All reports'!$R$5:$R$249,$S7)="?","BigBasket?","")))," "," · ")) -> Blinkit · Zepto · BigBasket | K7: =IF($S7="","",INDEX('All reports'!$T$5:$T$249,$S7)) -> 1214721 | L7: =IF($S7="","",INDEX('All reports'!$U$5:$U$249,$S7)) -> 3 | M7: =IF($S7="","",INDEX('All reports'!$Y$5:$Y$249,$S7)) -> 13 | N7: =IF($S7="","",IF(INDEX('All reports'!$N$5:$N$249,$S7)="","",INDEX('All reports'!$N$5:$N$249,$S7))) -> Exact | O7: =IF($S7="","",COUNTIF('All reports'!$M$5:$M$249,INDEX('All reports'!$M$5:$M$249,$S7))-1) -> 0 | P7: =IFERROR(HYPERLINK(INDEX('All reports'!$L$5:$L$249,$S7),"Open report"),"") -> Open report | Q7: =IFERROR(HYPERLINK(INDEX('QC listings'!$H$5:$H$200,MATCH(INDEX('All reports'!$M$5:$M$249,$S7),'QC listings'!$A$5:$A$200,0)),"Open listing"),"") -> Open listing | R7: =IF($S7="","",INDEX('All reports'!$AC$5:$AC$249,$S7)) -> Link out; Trustified's written licence needed to display the report | S7: =IFERROR(MATCH($A7,'All reports'!$AA$5:$AA$249,0),"") -> 2
A8: 4 | B8: =IF($S8="","",INDEX('All reports'!$B$5:$B$249,$S8)) -> Amul | C8: =IF($S8="","",INDEX('All reports'!$C$5:$C$249,$S8)) -> Masti Dahi Cup | D8: =IF($S8="","",INDEX('All reports'!$E$5:$E$249,$S8)) -> Curd & yoghurt | E8: =IF($S8="","",INDEX('All reports'!$F$5:$F$249,$S8)) -> Passed | F8: =IF($S8="","",IF(INDEX('All reports'!$G$5:$G$249,$S8)="","",INDEX('All reports'!$G$5:$G$249,$S8))) -> 46026 | G8: =IF($S8="","",INDEX('All reports'!$I$5:$I$249,$S8)) -> Eurofins | H8: =IF($S8="","",IF(INDEX('All reports'!$H$5:$H$249,$S8)="","",INDEX('All reports'!$H$5:$H$249,$S8))) -> MPC 338/01 | I8: =IF($S8="","",INDEX('All reports'!$J$5:$J$249,$S8)) -> Trustified Pass/Fail | J8: =IF($S8="","",SUBSTITUTE(TRIM(IF(INDEX('All reports'!$O$5:$O$249,$S8)="Y","Blinkit",IF(INDEX('All reports'!$O$5:$O$249,$S8)="?","Blinkit?",""))&" "&IF(INDEX('All reports'!$P$5:$P$249,$S8)="Y","Zepto",IF(INDEX('All reports'!$P$5:$P$249,$S8)="?","Zepto?",""))&" "&IF(INDEX('All reports'!$Q$5:$Q$249,$S8)="Y","Instamart",IF(INDEX('All reports'!$Q$5:$Q$249,$S8)="?","Instamart?",""))&" "&IF(INDEX('All reports'!$R$5:$R$249,$S8)="Y","BigBasket",IF(INDEX('All reports'!$R$5:$R$249,$S8)="?","BigBasket?","")))," "," · ")) -> Zepto · BigBasket | K8: =IF($S8="","",INDEX('All reports'!$T$5:$T$249,$S8)) -> 103152 | L8: =IF($S8="","",INDEX('All reports'!$U$5:$U$249,$S8)) -> 3 | M8: =IF($S8="","",INDEX('All reports'!$Y$5:$Y$249,$S8)) -> 12 | N8: =IF($S8="","",IF(INDEX('All reports'!$N$5:$N$249,$S8)="","",INDEX('All reports'!$N$5:$N$249,$S8))) -> Exact | O8: =IF($S8="","",COUNTIF('All reports'!$M$5:$M$249,INDEX('All reports'!$M$5:$M$249,$S8))-1) -> 0 | P8: =IFERROR(HYPERLINK(INDEX('All reports'!$L$5:$L$249,$S8),"Open report"),"") -> Open report | Q8: =IFERROR(HYPERLINK(INDEX('QC listings'!$H$5:$H$200,MATCH(INDEX('All reports'!$M$5:$M$249,$S8),'QC listings'!$A$5:$A$200,0)),"Open listing"),"") -> Open listing | R8: =IF($S8="","",INDEX('All reports'!$AC$5:$AC$249,$S8)) -> Link out; Trustified's written licence needed to display the report | S8: =IFERROR(MATCH($A8,'All reports'!$AA$5:$AA$249,0),"") -> 7
A9: 5 | B9: =IF($S9="","",INDEX('All reports'!$B$5:$B$249,$S9)) -> Amul | C9: =IF($S9="","",INDEX('All reports'!$C$5:$C$249,$S9)) -> Masti Dahi | D9: =IF($S9="","",INDEX('All reports'!$E$5:$E$249,$S9)) -> Curd & yoghurt | E9: =IF($S9="","",INDEX('All reports'!$F$5:$F$249,$S9)) -> Failed | F9: =IF($S9="","",IF(INDEX('All reports'!$G$5:$G$249,$S9)="","",INDEX('All reports'!$G$5:$G$249,$S9))) -> 46026 | G9: =IF($S9="","",INDEX('All reports'!$I$5:$I$249,$S9)) -> Eurofins | H9: =IF($S9="","",IF(INDEX('All reports'!$H$5:$H$249,$S9)="","",INDEX('All reports'!$H$5:$H$249,$S9))) -> SR04CM | I9: =IF($S9="","",INDEX('All reports'!$J$5:$J$249,$S9)) -> Trustified Pass/Fail | J9: =IF($S9="","",SUBSTITUTE(TRIM(IF(INDEX('All reports'!$O$5:$O$249,$S9)="Y","Blinkit",IF(INDEX('All reports'!$O$5:$O$249,$S9)="?","Blinkit?",""))&" "&IF(INDEX('All reports'!$P$5:$P$249,$S9)="Y","Zepto",IF(INDEX('All reports'!$P$5:$P$249,$S9)="?","Zepto?",""))&" "&IF(INDEX('All reports'!$Q$5:$Q$249,$S9)="Y","Instamart",IF(INDEX('All reports'!$Q$5:$Q$249,$S9)="?","Instamart?",""))&" "&IF(INDEX('All reports'!$R$5:$R$249,$S9)="Y","BigBasket",IF(INDEX('All reports'!$R$5:$R$249,$S9)="?","BigBasket?","")))," "," · ")) -> Blinkit | K9: =IF($S9="","",INDEX('All reports'!$T$5:$T$249,$S9)) -> 660000 | L9: =IF($S9="","",INDEX('All reports'!$U$5:$U$249,$S9)) -> 3 | M9: =IF($S9="","",INDEX('All reports'!$Y$5:$Y$249,$S9)) -> 11 | N9: =IF($S9="","",IF(INDEX('All reports'!$N$5:$N$249,$S9)="","",INDEX('All reports'!$N$5:$N$249,$S9))) -> Exact | O9: =IF($S9="","",COUNTIF('All reports'!$M$5:$M$249,INDEX('All reports'!$M$5:$M$249,$S9))-1) -> 0 | P9: =IFERROR(HYPERLINK(INDEX('All reports'!$L$5:$L$249,$S9),"Open report"),"") -> Open report | Q9: =IFERROR(HYPERLINK(INDEX('QC listings'!$H$5:$H$200,MATCH(INDEX('All reports'!$M$5:$M$249,$S9),'QC listings'!$A$5:$A$200,0)),"Open listing"),"") -> Open listing | R9: =IF($S9="","",INDEX('All reports'!$AC$5:$AC$249,$S9)) -> Link out; licence needed to display; run the PRD publication gate first (negative verdict) | S9: =IFERROR(MATCH($A9,'All reports'!$AA$5:$AA$249,0),"") -> 6
A10: 6 | B10: =IF($S10="","",INDEX('All reports'!$B$5:$B$249,$S10)) -> Tata | C10: =IF($S10="","",INDEX('All reports'!$C$5:$C$249,$S10)) -> Tata Salt | D10: =IF($S10="","",INDEX('All reports'!$E$5:$E$249,$S10)) -> Atta, rice & salt | E10: =IF($S10="","",INDEX('All reports'!$F$5:$F$249,$S10)) -> Passed | F10: =IF($S10="","",IF(INDEX('All reports'!$G$5:$G$249,$S10)="","",INDEX('All reports'!$G$5:$G$249,$S10))) -> 45984 | G10: =IF($S10="","",INDEX('All reports'!$I$5:$I$249,$S10)) -> Eurofins | H10: =IF($S10="","",IF(INDEX('All reports'!$H$5:$H$249,$S10)="","",INDEX('All reports'!$H$5:$H$249,$S10))) -> PU | I10: =IF($S10="","",INDEX('All reports'!$J$5:$J$249,$S10)) -> Trustified Pass/Fail | J10: =IF($S10="","",SUBSTITUTE(TRIM(IF(INDEX('All reports'!$O$5:$O$249,$S10)="Y","Blinkit",IF(INDEX('All reports'!$O$5:$O$249,$S10)="?","Blinkit?",""))&" "&IF(INDEX('All reports'!$P$5:$P$249,$S10)="Y","Zepto",IF(INDEX('All reports'!$P$5:$P$249,$S10)="?","Zepto?",""))&" "&IF(INDEX('All reports'!$Q$5:$Q$249,$S10)="Y","Instamart",IF(INDEX('All reports'!$Q$5:$Q$249,$S10)="?","Instamart?",""))&" "&IF(INDEX('All reports'!$R$5:$R$249,$S10)="Y","BigBasket",IF(INDEX('All reports'!$R$5:$R$249,$S10)="?","BigBasket?","")))," "," · ")) -> Blinkit · Zepto · Instamart | K10: =IF($S10="","",INDEX('All reports'!$T$5:$T$249,$S10)) -> 496464 | L10: =IF($S10="","",INDEX('All reports'!$U$5:$U$249,$S10)) -> 3 | M10: =IF($S10="","",INDEX('All reports'!$Y$5:$Y$249,$S10)) -> 11 | N10: =IF($S10="","",IF(INDEX('All reports'!$N$5:$N$249,$S10)="","",INDEX('All reports'!$N$5:$N$249,$S10))) -> Exact | O10: =IF($S10="","",COUNTIF('All reports'!$M$5:$M$249,INDEX('All reports'!$M$5:$M$249,$S10))-1) -> 0 | P10: =IFERROR(HYPERLINK(INDEX('All reports'!$L$5:$L$249,$S10),"Open report"),"") -> Open report | Q10: =IFERROR(HYPERLINK(INDEX('QC listings'!$H$5:$H$200,MATCH(INDEX('All reports'!$M$5:$M$249,$S10),'QC listings'!$A$5:$A$200,0)),"Open listing"),"") -> Open listing | R10: =IF($S10="","",INDEX('All reports'!$AC$5:$AC$249,$S10)) -> Link out; Trustified's written licence needed to display the report | S10: =IFERROR(MATCH($A10,'All reports'!$AA$5:$AA$249,0),"") -> 36
A11: 7 | B11: =IF($S11="","",INDEX('All reports'!$B$5:$B$249,$S11)) -> Haldiram's | C11: =IF($S11="","",INDEX('All reports'!$C$5:$C$249,$S11)) -> Salted Peanuts | D11: =IF($S11="","",INDEX('All reports'!$E$5:$E$249,$S11)) -> Packaged snacks | E11: =IF($S11="","",INDEX('All reports'!$F$5:$F$249,$S11)) -> Passed | F11: =IF($S11="","",IF(INDEX('All reports'!$G$5:$G$249,$S11)="","",INDEX('All reports'!$G$5:$G$249,$S11))) -> 45764 | G11: =IF($S11="","",INDEX('All reports'!$I$5:$I$249,$S11)) -> Eurofins | H11: =IF($S11="","",IF(INDEX('All reports'!$H$5:$H$249,$S11)="","",INDEX('All reports'!$H$5:$H$249,$S11))) -> 24018 | I11: =IF($S11="","",INDEX('All reports'!$J$5:$J$249,$S11)) -> Trustified Pass/Fail | J11: =IF($S11="","",SUBSTITUTE(TRIM(IF(INDEX('All reports'!$O$5:$O$249,$S11)="Y","Blinkit",IF(INDEX('All reports'!$O$5:$O$249,$S11)="?","Blinkit?",""))&" "&IF(INDEX('All reports'!$P$5:$P$249,$S11)="Y","Zepto",IF(INDEX('All reports'!$P$5:$P$249,$S11)="?","Zepto?",""))&" "&IF(INDEX('All reports'!$Q$5:$Q$249,$S11)="Y","Instamart",IF(INDEX('All reports'!$Q$5:$Q$249,$S11)="?","Instamart?",""))&" "&IF(INDEX('All reports'!$R$5:$R$249,$S11)="Y","BigBasket",IF(INDEX('All reports'!$R$5:$R$249,$S11)="?","BigBasket?","")))," "," · ")) -> Blinkit · Zepto · Instamart · BigBasket | K11: =IF($S11="","",INDEX('All reports'!$T$5:$T$249,$S11)) -> 38843 | L11: =IF($S11="","",INDEX('All reports'!$U$5:$U$249,$S11)) -> 2 | M11: =IF($S11="","",INDEX('All reports'!$Y$5:$Y$249,$S11)) -> 11 | N11: =IF($S11="","",IF(INDEX('All reports'!$N$5:$N$249,$S11)="","",INDEX('All reports'!$N$5:$N$249,$S11))) -> Exact | O11: =IF($S11="","",COUNTIF('All reports'!$M$5:$M$249,INDEX('All reports'!$M$5:$M$249,$S11))-1) -> 0 | P11: =IFERROR(HYPERLINK(INDEX('All reports'!$L$5:$L$249,$S11),"Open report"),"") -> Open report | Q11: =IFERROR(HYPERLINK(INDEX('QC listings'!$H$5:$H$200,MATCH(INDEX('All reports'!$M$5:$M$249,$S11),'QC listings'!$A$5:$A$200,0)),"Open listing"),"") -> Open listing | R11: =IF($S11="","",INDEX('All reports'!$AC$5:$AC$249,$S11)) -> Link out; Trustified's written licence needed to display the report | S11: =IFERROR(MATCH($A11,'All reports'!$AA$5:$AA$249,0),"") -> 11
A12: 8 | B12: =IF($S12="","",INDEX('All reports'!$B$5:$B$249,$S12)) -> Country Delight | C12: =IF($S12="","",INDEX('All reports'!$C$5:$C$249,$S12)) -> Cow Milk | D12: =IF($S12="","",INDEX('All reports'!$E$5:$E$249,$S12)) -> Milk | E12: =IF($S12="","",INDEX('All reports'!$F$5:$F$249,$S12)) -> Failed | F12: =IF($S12="","",IF(INDEX('All reports'!$G$5:$G$249,$S12)="","",INDEX('All reports'!$G$5:$G$249,$S12))) -> 46061 | G12: =IF($S12="","",INDEX('All reports'!$I$5:$I$249,$S12)) -> Eurofins | H12: =IF($S12="","",IF(INDEX('All reports'!$H$5:$H$249,$S12)="","",INDEX('All reports'!$H$5:$H$249,$S12))) -> DJCMG | I12: =IF($S12="","",INDEX('All reports'!$J$5:$J$249,$S12)) -> Trustified Pass/Fail | J12: =IF($S12="","",SUBSTITUTE(TRIM(IF(INDEX('All reports'!$O$5:$O$249,$S12)="Y","Blinkit",IF(INDEX('All reports'!$O$5:$O$249,$S12)="?","Blinkit?",""))&" "&IF(INDEX('All reports'!$P$5:$P$249,$S12)="Y","Zepto",IF(INDEX('All reports'!$P$5:$P$249,$S12)="?","Zepto?",""))&" "&IF(INDEX('All reports'!$Q$5:$Q$249,$S12)="Y","Instamart",IF(INDEX('All reports'!$Q$5:$Q$249,$S12)="?","Instamart?",""))&" "&IF(INDEX('All reports'!$R$5:$R$249,$S12)="Y","BigBasket",IF(INDEX('All reports'!$R$5:$R$249,$S12)="?","BigBasket?","")))," "," · ")) -> Blinkit · Zepto · Instamart | K12: =IF($S12="","",INDEX('All reports'!$T$5:$T$249,$S12)) -> 13966 | L12: =IF($S12="","",INDEX('All reports'!$U$5:$U$249,$S12)) -> 2 | M12: =IF($S12="","",INDEX('All reports'!$Y$5:$Y$249,$S12)) -> 11 | N12: =IF($S12="","",IF(INDEX('All reports'!$N$5:$N$249,$S12)="","",INDEX('All reports'!$N$5:$N$249,$S12))) -> Exact | O12: =IF($S12="","",COUNTIF('All reports'!$M$5:$M$249,INDEX('All reports'!$M$5:$M$249,$S12))-1) -> 0 | P12: =IFERROR(HYPERLINK(INDEX('All reports'!$L$5:$L$249,$S12),"Open report"),"") -> Open report | Q12: =IFERROR(HYPERLINK(INDEX('QC listings'!$H$5:$H$200,MATCH(INDEX('All reports'!$M$5:$M$249,$S12),'QC listings'!$A$5:$A$200,0)),"Open listing"),"") -> Open listing | R12: =IF($S12="","",INDEX('All reports'!$AC$5:$AC$249,$S12)) -> Link out; licence needed to display; run the PRD publication gate first (negative verdict) | S12: =IFERROR(MATCH($A12,'All reports'!$AA$5:$AA$249,0),"") -> 4
A13: 9 | B13: =IF($S13="","",INDEX('All reports'!$B$5:$B$249,$S13)) -> Maggi | C13: =IF($S13="","",INDEX('All reports'!$C$5:$C$249,$S13)) -> Masala-ae-Magic | D13: =IF($S13="","",INDEX('All reports'!$E$5:$E$249,$S13)) -> Spices & masala | E13: =IF($S13="","",INDEX('All reports'!$F$5:$F$249,$S13)) -> Passed | F13: =IF($S13="","",IF(INDEX('All reports'!$G$5:$G$249,$S13)="","",INDEX('All reports'!$G$5:$G$249,$S13))) -> 46068 | G13: =IF($S13="","",INDEX('All reports'!$I$5:$I$249,$S13)) -> Eurofins | H13: =IF($S13="","",IF(INDEX('All reports'!$H$5:$H$249,$S13)="","",INDEX('All reports'!$H$5:$H$249,$S13))) -> 50580455AA-M | I13: =IF($S13="","",INDEX('All reports'!$J$5:$J$249,$S13)) -> Trustified Pass/Fail | J13: =IF($S13="","",SUBSTITUTE(TRIM(IF(INDEX('All reports'!$O$5:$O$249,$S13)="Y","Blinkit",IF(INDEX('All reports'!$O$5:$O$249,$S13)="?","Blinkit?",""))&" "&IF(INDEX('All reports'!$P$5:$P$249,$S13)="Y","Zepto",IF(INDEX('All reports'!$P$5:$P$249,$S13)="?","Zepto?",""))&" "&IF(INDEX('All reports'!$Q$5:$Q$249,$S13)="Y","Instamart",IF(INDEX('All reports'!$Q$5:$Q$249,$S13)="?","Instamart?",""))&" "&IF(INDEX('All reports'!$R$5:$R$249,$S13)="Y","BigBasket",IF(INDEX('All reports'!$R$5:$R$249,$S13)="?","BigBasket?","")))," "," · ")) -> Blinkit · Zepto · Instamart · BigBasket | K13: =IF($S13="","",INDEX('All reports'!$T$5:$T$249,$S13)) -> 94808 | L13: =IF($S13="","",INDEX('All reports'!$U$5:$U$249,$S13)) -> 2 | M13: =IF($S13="","",INDEX('All reports'!$Y$5:$Y$249,$S13)) -> 10 | N13: =IF($S13="","",IF(INDEX('All reports'!$N$5:$N$249,$S13)="","",INDEX('All reports'!$N$5:$N$249,$S13))) -> Exact | O13: =IF($S13="","",COUNTIF('All reports'!$M$5:$M$249,INDEX('All reports'!$M$5:$M$249,$S13))-1) -> 0 | P13: =IFERROR(HYPERLINK(INDEX('All reports'!$L$5:$L$249,$S13),"Open report"),"") -> Open report | Q13: =IFERROR(HYPERLINK(INDEX('QC listings'!$H$5:$H$200,MATCH(INDEX('All reports'!$M$5:$M$249,$S13),'QC listings'!$A$5:$A$200,0)),"Open listing"),"") -> Open listing | R13: =IF($S13="","",INDEX('All reports'!$AC$5:$AC$249,$S13)) -> Link out; Trustified's written licence needed to display the report | S13: =IFERROR(MATCH($A13,'All reports'!$AA$5:$AA$249,0),"") -> 50
A14: 10 | B14: =IF($S14="","",INDEX('All reports'!$B$5:$B$249,$S14)) -> Aashirvaad | C14: =IF($S14="","",INDEX('All reports'!$C$5:$C$249,$S14)) -> Superior MP Atta | D14: =IF($S14="","",INDEX('All reports'!$E$5:$E$249,$S14)) -> Atta, rice & salt | E14: =IF($S14="","",INDEX('All reports'!$F$5:$F$249,$S14)) -> Passed | F14: =IF($S14="","",IF(INDEX('All reports'!$G$5:$G$249,$S14)="","",INDEX('All reports'!$G$5:$G$249,$S14))) -> 46223 | G14: =IF($S14="","",INDEX('All reports'!$I$5:$I$249,$S14)) -> Eurofins | H14: =IF($S14="","",IF(INDEX('All reports'!$H$5:$H$249,$S14)="","",INDEX('All reports'!$H$5:$H$249,$S14))) -> 04A72904 | I14: =IF($S14="","",INDEX('All reports'!$J$5:$J$249,$S14)) -> Trustified Pass/Fail | J14: =IF($S14="","",SUBSTITUTE(TRIM(IF(INDEX('All reports'!$O$5:$O$249,$S14)="Y","Blinkit",IF(INDEX('All reports'!$O$5:$O$249,$S14)="?","Blinkit?",""))&" "&IF(INDEX('All reports'!$P$5:$P$249,$S14)="Y","Zepto",IF(INDEX('All reports'!$P$5:$P$249,$S14)="?","Zepto?",""))&" "&IF(INDEX('All reports'!$Q$5:$Q$249,$S14)="Y","Instamart",IF(INDEX('All reports'!$Q$5:$Q$249,$S14)="?","Instamart?",""))&" "&IF(INDEX('All reports'!$R$5:$R$249,$S14)="Y","BigBasket",IF(INDEX('All reports'!$R$5:$R$249,$S14)="?","BigBasket?","")))," "," · ")) -> Blinkit · Zepto · Instamart · BigBasket | K14: =IF($S14="","",INDEX('All reports'!$T$5:$T$249,$S14)) -> 74917 | L14: =IF($S14="","",INDEX('All reports'!$U$5:$U$249,$S14)) -> 2 | M14: =IF($S14="","",INDEX('All reports'!$Y$5:$Y$249,$S14)) -> 10 | N14: =IF($S14="","",IF(INDEX('All reports'!$N$5:$N$249,$S14)="","",INDEX('All reports'!$N$5:$N$249,$S14))) -> Exact | O14: =IF($S14="","",COUNTIF('All reports'!$M$5:$M$249,INDEX('All reports'!$M$5:$M$249,$S14))-1) -> 0 | P14: =IFERROR(HYPERLINK(INDEX('All reports'!$L$5:$L$249,$S14),"Open report"),"") -> Open report | Q14: =IFERROR(HYPERLINK(INDEX('QC listings'!$H$5:$H$200,MATCH(INDEX('All reports'!$M$5:$M$249,$S14),'QC listings'!$A$5:$A$200,0)),"Open listing"),"") -> Open listing | R14: =IF($S14="","",INDEX('All reports'!$AC$5:$AC$249,$S14)) -> Link out; Trustified's written licence needed to display the report | S14: =IFERROR(MATCH($A14,'All reports'!$AA$5:$AA$249,0),"") -> 33
A15: 11 | B15: =IF($S15="","",INDEX('All reports'!$B$5:$B$249,$S15)) -> Amul | C15: =IF($S15="","",INDEX('All reports'!$C$5:$C$249,$S15)) -> Butter | D15: =IF($S15="","",INDEX('All reports'!$E$5:$E$249,$S15)) -> Butter, paneer & cheese | E15: =IF($S15="","",INDEX('All reports'!$F$5:$F$249,$S15)) -> Passed | F15: =IF($S15="","",IF(INDEX('All reports'!$G$5:$G$249,$S15)="","",INDEX('All reports'!$G$5:$G$249,$S15))) -> 45746 | G15: =IF($S15="","",INDEX('All reports'!$I$5:$I$249,$S15)) -> Eurofins | H15: =IF($S15="","",IF(INDEX('All reports'!$H$5:$H$249,$S15)="","",INDEX('All reports'!$H$5:$H$249,$S15))) -> SAN3211 | I15: =IF($S15="","",INDEX('All reports'!$J$5:$J$249,$S15)) -> Trustified Pass/Fail | J15: =IF($S15="","",SUBSTITUTE(TRIM(IF(INDEX('All reports'!$O$5:$O$249,$S15)="Y","Blinkit",IF(INDEX('All reports'!$O$5:$O$249,$S15)="?","Blinkit?",""))&" "&IF(INDEX('All reports'!$P$5:$P$249,$S15)="Y","Zepto",IF(INDEX('All reports'!$P$5:$P$249,$S15)="?","Zepto?",""))&" "&IF(INDEX('All reports'!$Q$5:$Q$249,$S15)="Y","Instamart",IF(INDEX('All reports'!$Q$5:$Q$249,$S15)="?","Instamart?",""))&" "&IF(INDEX('All reports'!$R$5:$R$249,$S15)="Y","BigBasket",IF(INDEX('All reports'!$R$5:$R$249,$S15)="?","BigBasket?","")))," "," · ")) -> Blinkit · Zepto · Instamart? | K15: =IF($S15="","",INDEX('All reports'!$T$5:$T$249,$S15)) -> 144000 | L15: =IF($S15="","",INDEX('All reports'!$U$5:$U$249,$S15)) -> 3 | M15: =IF($S15="","",INDEX('All reports'!$Y$5:$Y$249,$S15)) -> 9 | N15: =IF($S15="","",IF(INDEX('All reports'!$N$5:$N$249,$S15)="","",INDEX('All reports'!$N$5:$N$249,$S15))) -> Exact | O15: =IF($S15="","",COUNTIF('All reports'!$M$5:$M$249,INDEX('All reports'!$M$5:$M$249,$S15))-1) -> 0 | P15: =IFERROR(HYPERLINK(INDEX('All reports'!$L$5:$L$249,$S15),"Open report"),"") -> Open report | Q15: =IFERROR(HYPERLINK(INDEX('QC listings'!$H$5:$H$200,MATCH(INDEX('All reports'!$M$5:$M$249,$S15),'QC listings'!$A$5:$A$200,0)),"Open listing"),"") -> Open listing | R15: =IF($S15="","",INDEX('All reports'!$AC$5:$AC$249,$S15)) -> Link out; Trustified's written licence needed to display the report | S15: =IFERROR(MATCH($A15,'All reports'!$AA$5:$AA$249,0),"") -> 20
A16: 12 | B16: =IF($S16="","",INDEX('All reports'!$B$5:$B$249,$S16)) -> India Gate | C16: =IF($S16="","",INDEX('All reports'!$C$5:$C$249,$S16)) -> Feast Rozzana Basmati Rice | D16: =IF($S16="","",INDEX('All reports'!$E$5:$E$249,$S16)) -> Atta, rice & salt | E16: =IF($S16="","",INDEX('All reports'!$F$5:$F$249,$S16)) -> Failed | F16: =IF($S16="","",IF(INDEX('All reports'!$G$5:$G$249,$S16)="","",INDEX('All reports'!$G$5:$G$249,$S16))) -> 46103 | G16: =IF($S16="","",INDEX('All reports'!$I$5:$I$249,$S16)) -> Eurofins | H16: =IF($S16="","",IF(INDEX('All reports'!$H$5:$H$249,$S16)="","",INDEX('All reports'!$H$5:$H$249,$S16))) -> BW52E24400 | I16: =IF($S16="","",INDEX('All reports'!$J$5:$J$249,$S16)) -> Trustified Pass/Fail | J16: =IF($S16="","",SUBSTITUTE(TRIM(IF(INDEX('All reports'!$O$5:$O$249,$S16)="Y","Blinkit",IF(INDEX('All reports'!$O$5:$O$249,$S16)="?","Blinkit?",""))&" "&IF(INDEX('All reports'!$P$5:$P$249,$S16)="Y","Zepto",IF(INDEX('All reports'!$P$5:$P$249,$S16)="?","Zepto?",""))&" "&IF(INDEX('All reports'!$Q$5:$Q$249,$S16)="Y","Instamart",IF(INDEX('All reports'!$Q$5:$Q$249,$S16)="?","Instamart?",""))&" "&IF(INDEX('All reports'!$R$5:$R$249,$S16)="Y","BigBasket",IF(INDEX('All reports'!$R$5:$R$249,$S16)="?","BigBasket?","")))," "," · ")) -> Zepto · Instamart · BigBasket | K16: =IF($S16="","",INDEX('All reports'!$T$5:$T$249,$S16)) -> 23064 | L16: =IF($S16="","",INDEX('All reports'!$U$5:$U$249,$S16)) -> 2 | M16: =IF($S16="","",INDEX('All reports'!$Y$5:$Y$249,$S16)) -> 9 | N16: =IF($S16="","",IF(INDEX('All reports'!$N$5:$N$249,$S16)="","",INDEX('All reports'!$N$5:$N$249,$S16))) -> Exact | O16: =IF($S16="","",COUNTIF('All reports'!$M$5:$M$249,INDEX('All reports'!$M$5:$M$249,$S16))-1) -> 0 | P16: =IFERROR(HYPERLINK(INDEX('All reports'!$L$5:$L$249,$S16),"Open report"),"") -> Open report | Q16: =IFERROR(HYPERLINK(INDEX('QC listings'!$H$5:$H$200,MATCH(INDEX('All reports'!$M$5:$M$249,$S16),'QC listings'!$A$5:$A$200,0)),"Open listing"),"") -> Open listing | R16: =IF($S16="","",INDEX('All reports'!$AC$5:$AC$249,$S16)) -> Link out; licence needed to display; run the PRD publication gate first (negative verdict) | S16: =IFERROR(MATCH($A16,'All reports'!$AA$5:$AA$249,0),"") -> 35
... A43: 39 | B43: =IF($S43="","",INDEX('All reports'!$B$5:$B$249,$S43)) -> The Whole Truth | C43: =IF($S43="","",INDEX('All reports'!$C$5:$C$249,$S43)) -> Raw Whey Protein Isolate | D43: =IF($S43="","",INDEX('All reports'!$E$5:$E$249,$S43)) -> Whey protein | E43: =IF($S43="","",INDEX('All reports'!$F$5:$F$249,$S43)) -> Passed | F43: =IF($S43="","",IF(INDEX('All reports'!$G$5:$G$249,$S43)="","",INDEX('All reports'!$G$5:$G$249,$S43))) -> 45460 | G43: =IF($S43="","",INDEX('All reports'!$I$5:$I$249,$S43)) -> Eurofins | H43: =IF($S43="","",IF(INDEX('All reports'!$H$5:$H$249,$S43)="","",INDEX('All reports'!$H$5:$H$249,$S43))) -> TWTWIU087F2 | I43: =IF($S43="","",INDEX('All reports'!$J$5:$J$249,$S43)) -> Trustified Pass/Fail | J43: =IF($S43="","",SUBSTITUTE(TRIM(IF(INDEX('All reports'!$O$5:$O$249,$S43)="Y","Blinkit",IF(INDEX('All reports'!$O$5:$O$249,$S43)="?","Blinkit?",""))&" "&IF(INDEX('All reports'!$P$5:$P$249,$S43)="Y","Zepto",IF(INDEX('All reports'!$P$5:$P$249,$S43)="?","Zepto?",""))&" "&IF(INDEX('All reports'!$Q$5:$Q$249,$S43)="Y","Instamart",IF(INDEX('All reports'!$Q$5:$Q$249,$S43)="?","Instamart?",""))&" "&IF(INDEX('All reports'!$R$5:$R$249,$S43)="Y","BigBasket",IF(INDEX('All reports'!$R$5:$R$249,$S43)="?","BigBasket?","")))," "," · ")) -> Zepto | K43: =IF($S43="","",INDEX('All reports'!$T$5:$T$249,$S43)) -> 0 | L43: =IF($S43="","",INDEX('All reports'!$U$5:$U$249,$S43)) -> 0 | M43: =IF($S43="","",INDEX('All reports'!$Y$5:$Y$249,$S43)) -> 0.75 | N43: =IF($S43="","",IF(INDEX('All reports'!$N$5:$N$249,$S43)="","",INDEX('All reports'!$N$5:$N$249,$S43))) -> Same line | O43: =IF($S43="","",COUNTIF('All reports'!$M$5:$M$249,INDEX('All reports'!$M$5:$M$249,$S43))-1) -> 1 | P43: =IFERROR(HYPERLINK(INDEX('All reports'!$L$5:$L$249,$S43),"Open report"),"") -> Open report | Q43: =IFERROR(HYPERLINK(INDEX('QC listings'!$H$5:$H$200,MATCH(INDEX('All reports'!$M$5:$M$249,$S43),'QC listings'!$A$5:$A$200,0)),"Open listing"),"") -> Open listing | R43: =IF($S43="","",INDEX('All reports'!$AC$5:$AC$249,$S43)) -> Link out; Trustified's written licence needed to display the report | S43: =IFERROR(MATCH($A43,'All reports'!$AA$5:$AA$249,0),"") -> 168

Sheet All reports
A1: All lab-report rows (one row per published report or rating)
A2: Sources: Trustified Pass/Fail and NMR pages, The Whole Truth's batch hub, Unbox Health. Filter on any column. From 'QC key' onwards the columns are the quick-commerce overlay and scoring; weights are on the Scoring sheet.
A3: Product | F3: Lab report | M3: Quick-commerce listing check (2 Oct 2026) | S3: Demand and score | AB3: Access and notes | AE3: Helper
A4: ID | B4: Brand | C4: Product | D4: Segment | E4: Category | F4: Verdict | G4: Report date | H4: Batch tested | I4: Lab | J4: Source | K4: Unbox rating | L4: Report link | M4: QC key | N4: QC match | O4: Blinkit | P4: Zepto | Q4: Instamart | R4: BigBasket | S4: QC platforms | T4: Top ratings count | U4: Demand tier | V4: QC category | W4: Report age (months) | X4: Freshness | Y4: QC score | Z4: Primary for line | AA4: QC rank | AB4: Access | AC4: Publish route | AD4: Notes | AE4: Sort key (helper)
A5: R001 | B5: Amul | C5: Gold Milk | D5: Everyday food | E5: Milk | F5: Failed | G5: 46061 | H5: SR26DM | I5: Eurofins | J5: Trustified Pass/Fail | L5: https://www.trustified.in/passandfail/amulgoldmilk | M5: AMUL-GOLD | N5: Exact | O5: =IF($M5="","",IF(COUNTIFS('QC listings'!$A$5:$A$200,$M5,'QC listings'!$C$5:$C$200,O$4,'QC listings'!$F$5:$F$200,"Listing page")+COUNTIFS('QC listings'!$A$5:$A$200,$M5,'QC listings'!$C$5:$C$200,O$4,'QC listings'!$F$5:$F$200,"Brand page")>0,"Y",IF(COUNTIFS('QC listings'!$A$5:$A$200,$M5,'QC listings'!$C$5:$C$200,O$4)>0,"?","–"))) -> Y | P5: =IF($M5="","",IF(COUNTIFS('QC listings'!$A$5:$A$200,$M5,'QC listings'!$C$5:$C$200,P$4,'QC listings'!$F$5:$F$200,"Listing page")+COUNTIFS('QC listings'!$A$5:$A$200,$M5,'QC listings'!$C$5:$C$200,P$4,'QC listings'!$F$5:$F$200,"Brand page")>0,"Y",IF(COUNTIFS('QC listings'!$A$5:$A$200,$M5,'QC listings'!$C$5:$C$200,P$4)>0,"?","–"))) -> Y | Q5: =IF($M5="","",IF(COUNTIFS('QC listings'!$A$5:$A$200,$M5,'QC listings'!$C$5:$C$200,Q$4,'QC listings'!$F$5:$F$200,"Listing page")+COUNTIFS('QC listings'!$A$5:$A$200,$M5,'QC listings'!$C$5:$C$200,Q$4,'QC listings'!$F$5:$F$200,"Brand page")>0,"Y",IF(COUNTIFS('QC listings'!$A$5:$A$200,$M5,'QC listings'!$C$5:$C$200,Q$4)>0,"?","–"))) -> – | R5: =IF($M5="","",IF(COUNTIFS('QC listings'!$A$5:$A$200,$M5,'QC listings'!$C$5:$C$200,R$4,'QC listings'!$F$5:$F$200,"Listing page")+COUNTIFS('QC listings'!$A$5:$A$200,$M5,'QC listings'!$C$5:$C$200,R$4,'QC listings'!$F$5:$F$200,"Brand page")>0,"Y",IF(COUNTIFS('QC listings'!$A$5:$A$200,$M5,'QC listings'!$C$5:$C$200,R$4)>0,"?","–"))) -> Y | S5: =IF($M5="","",COUNTIF(O5:R5,"Y")) -> 3 | T5: =IF($M5="","",SUMPRODUCT(MAX(('QC listings'!$A$5:$A$200=$M5)*'QC listings'!$E$5:$E$200))) -> 1581833 | U5: =IF($M5="","",IF(T5>=Scoring!$B$11,3,IF(T5>=Scoring!$B$10,2,IF(T5>=Scoring!$B$9,1,0)))) -> 3 | V5: =IFERROR(INDEX(Scoring!$B$27:$B$56,MATCH($E5,Scoring!$A$27:$A$56,0)),0) -> 1 | W5: =IF($G5="","",ROUND((Scoring!$B$5-$G5)/30.4375,1)) -> 7.8 | X5: =IF($F5="Expired",Scoring!$B$18,IF($G5="",Scoring!$B$17,IF(W5<=Scoring!$B$12,Scoring!$B$13,IF(W5<=Scoring!$B$14,Scoring!$B$15,Scoring!$B$16)))) -> 2 | Y5: =IF($M5="","",ROUND((S5*Scoring!$B$6+U5*Scoring!$B$7)*IFERROR(INDEX(Scoring!$B$22:$B$24,MATCH($N5,Scoring!$A$22:$A$24,0)),1)+V5*Scoring!$B$8+X5,2)) -> 13 | Z5: =IF($M5="","",IF(SUMPRODUCT(($M$5:$M$249=$M5)*($G$5:$G$249>$G5))>0,0,IF(SUMPRODUCT(($M$5:$M$249=$M5)*($G$5:$G$249=$G5)*(ROW($M$5:$M$249)<ROW($M5)))>0,0,1))) -> 1 | AA5: =IF($Z5=1,RANK($AE5,$AE$5:$AE$249,0),"") -> 2 | AB5: Open | AC5: Link out; licence needed to display; run the PRD publication gate first (negative verdict) | AD5: QC: Instamart listing not seen in my checks. | AE5: =IF($Z5=1,$Y5+$T5/1000000000-ROW()/10000000,"") -> 13.001581
A6: R002 | B6: Amul | C6: Taaza Homogenised Toned Milk | D6: Everyday food | E6: Milk | F6: Passed | G6: 46061 | H6: MAC2691 | I6: Eurofins | J6: Trustified Pass/Fail | L6: https://www.trustified.in/passandfail/amulHomogenisedmilk | M6: AMUL-TAAZA | N6: Exact | O6: =IF($M6="","",IF(COUNTIFS('QC listings'!$A$5:$A$200,$M6,'QC listings'!$C$5:$C$200,O$4,'QC listings'!$F$5:$F$200,"Listing page")+COUNTIFS('QC listings'!$A$5:$A$200,$M6,'QC listings'!$C$5:$C$200,O$4,'QC listings'!$F$5:$F$200,"Brand page")>0,"Y",IF(COUNTIFS('QC listings'!$A$5:$A$200,$M6,'QC listings'!$C$5:$C$200,O$4)>0,"?","–"))) -> Y | P6: =IF($M6="","",IF(COUNTIFS('QC listings'!$A$5:$A$200,$M6,'QC listings'!$C$5:$C$200,P$4,'QC listings'!$F$5:$F$200,"Listing page")+COUNTIFS('QC listings'!$A$5:$A$200,$M6,'QC listings'!$C$5:$C$200,P$4,'QC listings'!$F$5:$F$200,"Brand page")>0,"Y",IF(COUNTIFS('QC listings'!$A$5:$A$200,$M6,'QC listings'!$C$5:$C$200,P$4)>0,"?","–"))) -> Y | Q6: =IF($M6="","",IF(COUNTIFS('QC listings'!$A$5:$A$200,$M6,'QC listings'!$C$5:$C$200,Q$4,'QC listings'!$F$5:$F$200,"Listing page")+COUNTIFS('QC listings'!$A$5:$A$200,$M6,'QC listings'!$C$5:$C$200,Q$4,'QC listings'!$F$5:$F$200,"Brand page")>0,"Y",IF(COUNTIFS('QC listings'!$A$5:$A$200,$M6,'QC listings'!$C$5:$C$200,Q$4)>0,"?","–"))) -> – | R6: =IF($M6="","",IF(COUNTIFS('QC listings'!$A$5:$A$200,$M6,'QC listings'!$C$5:$C$200,R$4,'QC listings'!$F$5:$F$200,"Listing page")+COUNTIFS('QC listings'!$A$5:$A$200,$M6,'QC listings'!$C$5:$C$200,R$4,'QC listings'!$F$5:$F$200,"Brand page")>0,"Y",IF(COUNTIFS('QC listings'!$A$5:$A$200,$M6,'QC listings'!$C$5:$C$200,R$4)>0,"?","–"))) -> Y | S6: =IF($M6="","",COUNTIF(O6:R6,"Y")) -> 3 | T6: =IF($M6="","",SUMPRODUCT(MAX(('QC listings'!$A$5:$A$200=$M6)*'QC listings'!$E$5:$E$200))) -> 1214721 | U6: =IF($M6="","",IF(T6>=Scoring!$B$11,3,IF(T6>=Scoring!$B$10,2,IF(T6>=Scoring!$B$9,1,0)))) -> 3 | V6: =IFERROR(INDEX(Scoring!$B$27:$B$56,MATCH($E6,Scoring!$A$27:$A$56,0)),0) -> 1 | W6: =IF($G6="","",ROUND((Scoring!$B$5-$G6)/30.4375,1)) -> 7.8 | X6: =IF($F6="Expired",Scoring!$B$18,IF($G6="",Scoring!$B$17,IF(W6<=Scoring!$B$12,Scoring!$B$13,IF(W6<=Scoring!$B$14,Scoring!$B$15,Scoring!$B$16)))) -> 2 | Y6: =IF($M6="","",ROUND((S6*Scoring!$B$6+U6*Scoring!$B$7)*IFERROR(INDEX(Scoring!$B$22:$B$24,MATCH($N6,Scoring!$A$22:$A$24,0)),1)+V6*Scoring!$B$8+X6,2)) -> 13 | Z6: =IF($M6="","",IF(SUMPRODUCT(($M$5:$M$249=$M6)*($G$5:$G$249>$G6))>0,0,IF(SUMPRODUCT(($M$5:$M$249=$M6)*($G$5:$G$249=$G6)*(ROW($M$5:$M$249)<ROW($M6)))>0,0,1))) -> 1 | AA6: =IF($Z6=1,RANK($AE6,$AE$5:$AE$249,0),"") -> 3 | AB6: Open | AC6: Link out; Trustified's written licence needed to display the report | AD6: QC: Instamart listing not seen in my checks. | AE6: =IF($Z6=1,$Y6+$T6/1000000000-ROW()/10000000,"") -> 13.001214
A7: R003 | B7: Amul | C7: Taaza Milky Milk | D7: Everyday food | E7: Milk | F7: Failed | G7: 46061 | H7: SR07FM1228 | I7: Eurofins | J7: Trustified Pass/Fail | L7: https://www.trustified.in/passandfail/amultaazamilk | O7: =IF($M7="","",IF(COUNTIFS('QC listings'!$A$5:$A$200,$M7,'QC listings'!$C$5:$C$200,O$4,'QC listings'!$F$5:$F$200,"Listing page")+COUNTIFS('QC listings'!$A$5:$A$200,$M7,'QC listings'!$C$5:$C$200,O$4,'QC listings'!$F$5:$F$200,"Brand page")>0,"Y",IF(COUNTIFS('QC listings'!$A$5:$A$200,$M7,'QC listings'!$C$5:$C$200,O$4)>0,"?","–"))) | P7: =IF($M7="","",IF(COUNTIFS('QC listings'!$A$5:$A$200,$M7,'QC listings'!$C$5:$C$200,P$4,'QC listings'!$F$5:$F$200,"Listing page")+COUNTIFS('QC listings'!$A$5:$A$200,$M7,'QC listings'!$C$5:$C$200,P$4,'QC listings'!$F$5:$F$200,"Brand page")>0,"Y",IF(COUNTIFS('QC listings'!$A$5:$A$200,$M7,'QC listings'!$C$5:$C$200,P$4)>0,"?","–"))) | Q7: =IF($M7="","",IF(COUNTIFS('QC listings'!$A$5:$A$200,$M7,'QC listings'!$C$5:$C$200,Q$4,'QC listings'!$F$5:$F$200,"Listing page")+COUNTIFS('QC listings'!$A$5:$A$200,$M7,'QC listings'!$C$5:$C$200,Q$4,'QC listings'!$F$5:$F$200,"Brand page")>0,"Y",IF(COUNTIFS('QC listings'!$A$5:$A$200,$M7,'QC listings'!$C$5:$C$200,Q$4)>0,"?","–"))) | R7: =IF($M7="","",IF(COUNTIFS('QC listings'!$A$5:$A$200,$M7,'QC listings'!$C$5:$C$200,R$4,'QC listings'!$F$5:$F$200,"Listing page")+COUNTIFS('QC listings'!$A$5:$A$200,$M7,'QC listings'!$C$5:$C$200,R$4,'QC listings'!$F$5:$F$200,"Brand page")>0,"Y",IF(COUNTIFS('QC listings'!$A$5:$A$200,$M7,'QC listings'!$C$5:$C$200,R$4)>0,"?","–"))) | S7: =IF($M7="","",COUNTIF(O7:R7,"Y")) | T7: =IF($M7="","",SUMPRODUCT(MAX(('QC listings'!$A$5:$A$200=$M7)*'QC listings'!$E$5:$E$200))) | U7: =IF($M7="","",IF(T7>=Scoring!$B$11,3,IF(T7>=Scoring!$B$10,2,IF(T7>=Scoring!$B$9,1,0)))) | V7: =IFERROR(INDEX(Scoring!$B$27:$B$56,MATCH($E7,Scoring!$A$27:$A$56,0)),0) -> 1 | W7: =IF($G7="","",ROUND((Scoring!$B$5-$G7)/30.4375,1)) -> 7.8 | X7: =IF($F7="Expired",Scoring!$B$18,IF($G7="",Scoring!$B$17,IF(W7<=Scoring!$B$12,Scoring!$B$13,IF(W7<=Scoring!$B$14,Scoring!$B$15,Scoring!$B$16)))) -> 2 | Y7: =IF($M7="","",ROUND((S7*Scoring!$B$6+U7*Scoring!$B$7)*IFERROR(INDEX(Scoring!$B$22:$B$24,MATCH($N7,Scoring!$A$22:$A$24,0)),1)+V7*Scoring!$B$8+X7,2)) | Z7: =IF($M7="","",IF(SUMPRODUCT(($M$5:$M$249=$M7)*($G$5:$G$249>$G7))>0,0,IF(SUMPRODUCT(($M$5:$M$249=$M7)*($G$5:$G$249=$G7)*(ROW($M$5:$M$249)<ROW($M7)))>0,0,1))) | AA7: =IF($Z7=1,RANK($AE7,$AE$5:$AE$249,0),"") | AB7: Open | AC7: Link out; licence needed to display; run the PRD publication gate first (negative verdict) | AE7: =IF($Z7=1,$Y7+$T7/1000000000-ROW()/10000000,"")
A8: R004 | B8: Country Delight | C8: Cow Milk | D8: Everyday food | E8: Milk | F8: Failed | G8: 46061 | H8: DJCMG | I8: Eurofins | J8: Trustified Pass/Fail | L8: https://www.trustified.in/passandfail/countrydelightmilk | M8: CD-COW | N8: Exact | O8: =IF($M8="","",IF(COUNTIFS('QC listings'!$A$5:$A$200,$M8,'QC listings'!$C$5:$C$200,O$4,'QC listings'!$F$5:$F$200,"Listing page")+COUNTIFS('QC listings'!$A$5:$A$200,$M8,'QC listings'!$C$5:$C$200,O$4,'QC listings'!$F$5:$F$200,"Brand page")>0,"Y",IF(COUNTIFS('QC listings'!$A$5:$A$200,$M8,'QC listings'!$C$5:$C$200,O$4)>0,"?","–"))) -> Y | P8: =IF($M8="","",IF(COUNTIFS('QC listings'!$A$5:$A$200,$M8,'QC listings'!$C$5:$C$200,P$4,'QC listings'!$F$5:$F$200,"Listing page")+COUNTIFS('QC listings'!$A$5:$A$200,$M8,'QC listings'!$C$5:$C$200,P$4,'QC listings'!$F$5:$F$200,"Brand page")>0,"Y",IF(COUNTIFS('QC listings'!$A$5:$A$200,$M8,'QC listings'!$C$5:$C$200,P$4)>0,"?","–"))) -> Y | Q8: =IF($M8="","",IF(COUNTIFS('QC listings'!$A$5:$A$200,$M8,'QC listings'!$C$5:$C$200,Q$4,'QC listings'!$F$5:$F$200,"Listing page")+COUNTIFS('QC listings'!$A$5:$A$200,$M8,'QC listings'!$C$5:$C$200,Q$4,'QC listings'!$F$5:$F$200,"Brand page")>0,"Y",IF(COUNTIFS('QC listings'!$A$5:$A$200,$M8,'QC listings'!$C$5:$C$200,Q$4)>0,"?","–"))) -> Y | R8: =IF($M8="","",IF(COUNTIFS('QC listings'!$A$5:$A$200,$M8,'QC listings'!$C$5:$C$200,R$4,'QC listings'!$F$5:$F$200,"Listing page")+COUNTIFS('QC listings'!$A$5:$A$200,$M8,'QC listings'!$C$5:$C$200,R$4,'QC listings'!$F$5:$F$200,"Brand page")>0,"Y",IF(COUNTIFS('QC listings'!$A$5:$A$200,$M8,'QC listings'!$C$5:$C$200,R$4)>0,"?","–"))) -> – | S8: =IF($M8="","",COUNTIF(O8:R8,"Y")) -> 3 | T8: =IF($M8="","",SUMPRODUCT(MAX(('QC listings'!$A$5:$A$200=$M8)*'QC listings'!$E$5:$E$200))) -> 13966 | U8: =IF($M8="","",IF(T8>=Scoring!$B$11,3,IF(T8>=Scoring!$B$10,2,IF(T8>=Scoring!$B$9,1,0)))) -> 2 | V8: =IFERROR(INDEX(Scoring!$B$27:$B$56,MATCH($E8,Scoring!$A$27:$A$56,0)),0) -> 1 | W8: =IF($G8="","",ROUND((Scoring!$B$5-$G8)/30.4375,1)) -> 7.8 | X8: =IF($F8="Expired",Scoring!$B$18,IF($G8="",Scoring!$B$17,IF(W8<=Scoring!$B$12,Scoring!$B$13,IF(W8<=Scoring!$B$14,Scoring!$B$15,Scoring!$B$16)))) -> 2 | Y8: =IF($M8="","",ROUND((S8*Scoring!$B$6+U8*Scoring!$B$7)*IFERROR(INDEX(Scoring!$B$22:$B$24,MATCH($N8,Scoring!$A$22:$A$24,0)),1)+V8*Scoring!$B$8+X8,2)) -> 11 | Z8: =IF($M8="","",IF(SUMPRODUCT(($M$5:$M$249=$M8)*($G$5:$G$249>$G8))>0,0,IF(SUMPRODUCT(($M$5:$M$249=$M8)*($G$5:$G$249=$G8)*(ROW($M$5:$M$249)<ROW($M8)))>0,0,1))) -> 1 | AA8: =IF($Z8=1,RANK($AE8,$AE$5:$AE$249,0),"") -> 8 | AB8: Open | AC8: Link out; licence needed to display; run the PRD publication gate first (negative verdict) | AD8: QC: BigBasket listing not seen in my checks. | AE8: =IF($Z8=1,$Y8+$T8/1000000000-ROW()/10000000,"") -> 11.000013
A9: R005 | B9: Mother Dairy | C9: Cow Milk | D9: Everyday food | E9: Milk | F9: Failed | G9: 46061 | H9: (05)05NOV25SZ5M | I9: Eurofins | J9: Trustified Pass/Fail | L9: https://www.trustified.in/passandfail/motherdairymilk | M9: MD-COW | N9: Exact | O9: =IF($M9="","",IF(COUNTIFS('QC listings'!$A$5:$A$200,$M9,'QC listings'!$C$5:$C$200,O$4,'QC listings'!$F$5:$F$200,"Listing page")+COUNTIFS('QC listings'!$A$5:$A$200,$M9,'QC listings'!$C$5:$C$200,O$4,'QC listings'!$F$5:$F$200,"Brand page")>0,"Y",IF(COUNTIFS('QC listings'!$A$5:$A$200,$M9,'QC listings'!$C$5:$C$200,O$4)>0,"?","–"))) -> Y | P9: =IF($M9="","",IF(COUNTIFS('QC listings'!$A$5:$A$200,$M9,'QC listings'!$C$5:$C$200,P$4,'QC listings'!$F$5:$F$200,"Listing page")+COUNTIFS('QC listings'!$A$5:$A$200,$M9,'QC listings'!$C$5:$C$200,P$4,'QC listings'!$F$5:$F$200,"Brand page")>0,"Y",IF(COUNTIFS('QC listings'!$A$5:$A$200,$M9,'QC listings'!$C$5:$C$200,P$4)>0,"?","–"))) -> Y | Q9: =IF($M9="","",IF(COUNTIFS('QC listings'!$A$5:$A$200,$M9,'QC listings'!$C$5:$C$200,Q$4,'QC listings'!$F$5:$F$200,"Listing page")+COUNTIFS('QC listings'!$A$5:$A$200,$M9,'QC listings'!$C$5:$C$200,Q$4,'QC listings'!$F$5:$F$200,"Brand page")>0,"Y",IF(COUNTIFS('QC listings'!$A$5:$A$200,$M9,'QC listings'!$C$5:$C$200,Q$4)>0,"?","–"))) -> Y | R9: =IF($M9="","",IF(COUNTIFS('QC listings'!$A$5:$A$200,$M9,'QC listings'!$C$5:$C$200,R$4,'QC listings'!$F$5:$F$200,"Listing page")+COUNTIFS('QC listings'!$A$5:$A$200,$M9,'QC listings'!$C$5:$C$200,R$4,'QC listings'!$F$5:$F$200,"Brand page")>0,"Y",IF(COUNTIFS('QC listings'!$A$5:$A$200,$M9,'QC listings'!$C$5:$C$200,R$4)>0,"?","–"))) -> Y | S9: =IF($M9="","",COUNTIF(O9:R9,"Y")) -> 4 | T9: =IF($M9="","",SUMPRODUCT(MAX(('QC listings'!$A$5:$A$200=$M9)*'QC listings'!$E$5:$E$200))) -> 302321 | U9: =IF($M9="","",IF(T9>=Scoring!$B$11,3,IF(T9>=Scoring!$B$10,2,IF(T9>=Scoring!$B$9,1,0)))) -> 3 | V9: =IFERROR(INDEX(Scoring!$B$27:$B$56,MATCH($E9,Scoring!$A$27:$A$56,0)),0) -> 1 | W9: =IF($G9="","",ROUND((Scoring!$B$5-$G9)/30.4375,1)) -> 7.8 | X9: =IF($F9="Expired",Scoring!$B$18,IF($G9="",Scoring!$B$17,IF(W9<=Scoring!$B$12,Scoring!$B$13,IF(W9<=Scoring!$B$14,Scoring!$B$15,Scoring!$B$16)))) -> 2 | Y9: =IF($M9="","",ROUND((S9*Scoring!$B$6+U9*Scoring!$B$7)*IFERROR(INDEX(Scoring!$B$22:$B$24,MATCH($N9,Scoring!$A$22:$A$24,0)),1)+V9*Scoring!$B$8+X9,2)) -> 14 | Z9: =IF($M9="","",IF(SUMPRODUCT(($M$5:$M$249=$M9)*($G$5:$G$249>$G9))>0,0,IF(SUMPRODUCT(($M$5:$M$249=$M9)*($G$5:$G$249=$G9)*(ROW($M$5:$M$249)<ROW($M9)))>0,0,1))) -> 1 | AA9: =IF($Z9=1,RANK($AE9,$AE$5:$AE$249,0),"") -> 1 | AB9: Open | AC9: Link out; licence needed to display; run the PRD publication gate first (negative verdict) | AE9: =IF($Z9=1,$Y9+$T9/1000000000-ROW()/10000000,"") -> 14.000301
A10: R006 | B10: Amul | C10: Masti Dahi | D10: Everyday food | E10: Curd & yoghurt | F10: Failed | G10: 46026 | H10: SR04CM | I10: Eurofins | J10: Trustified Pass/Fail | L10: https://www.trustified.in/passandfail/mastidahipouch | M10: AMUL-DAHI-POUCH | N10: Exact | O10: =IF($M10="","",IF(COUNTIFS('QC listings'!$A$5:$A$200,$M10,'QC listings'!$C$5:$C$200,O$4,'QC listings'!$F$5:$F$200,"Listing page")+COUNTIFS('QC listings'!$A$5:$A$200,$M10,'QC listings'!$C$5:$C$200,O$4,'QC listings'!$F$5:$F$200,"Brand page")>0,"Y",IF(COUNTIFS('QC listings'!$A$5:$A$200,$M10,'QC listings'!$C$5:$C$200,O$4)>0,"?","–"))) -> Y | P10: =IF($M10="","",IF(COUNTIFS('QC listings'!$A$5:$A$200,$M10,'QC listings'!$C$5:$C$200,P$4,'QC listings'!$F$5:$F$200,"Listing page")+COUNTIFS('QC listings'!$A$5:$A$200,$M10,'QC listings'!$C$5:$C$200,P$4,'QC listings'!$F$5:$F$200,"Brand page")>0,"Y",IF(COUNTIFS('QC listings'!$A$5:$A$200,$M10,'QC listings'!$C$5:$C$200,P$4)>0,"?","–"))) -> – | Q10: =IF($M10="","",IF(COUNTIFS('QC listings'!$A$5:$A$200,$M10,'QC listings'!$C$5:$C$200,Q$4,'QC listings'!$F$5:$F$200,"Listing page")+COUNTIFS('QC listings'!$A$5:$A$200,$M10,'QC listings'!$C$5:$C$200,Q$4,'QC listings'!$F$5:$F$200,"Brand page")>0,"Y",IF(COUNTIFS('QC listings'!$A$5:$A$200,$M10,'QC listings'!$C$5:$C$200,Q$4)>0,"?","–"))) -> – | R10: =IF($M10="","",IF(COUNTIFS('QC listings'!$A$5:$A$200,$M10,'QC listings'!$C$5:$C$200,R$4,'QC listings'!$F$5:$F$200,"Listing page")+COUNTIFS('QC listings'!$A$5:$A$200,$M10,'QC listings'!$C$5:$C$200,R$4,'QC listings'!$F$5:$F$200,"Brand page")>0,"Y",IF(COUNTIFS('QC listings'!$A$5:$A$200,$M10,'QC listings'!$C$5:$C$200,R$4)>0,"?","–"))) -> – | S10: =IF($M10="","",COUNTIF(O10:R10,"Y")) -> 1 | T10: =IF($M10="","",SUMPRODUCT(MAX(('QC listings'!$A$5:$A$200=$M10)*'QC listings'!$E$5:$E$200))) -> 660000 | U10: =IF($M10="","",IF(T10>=Scoring!$B$11,3,IF(T10>=Scoring!$B$10,2,IF(T10>=Scoring!$B$9,1,0)))) -> 3 | V10: =IFERROR(INDEX(Scoring!$B$27:$B$56,MATCH($E10,Scoring!$A$27:$A$56,0)),0) -> 1 | W10: =IF($G10="","",ROUND((Scoring!$B$5-$G10)/30.4375,1)) -> 8.9 | X10: =IF($F10="Expired",Scoring!$B$18,IF($G10="",Scoring!$B$17,IF(W10<=Scoring!$B$12,Scoring!$B$13,IF(W10<=Scoring!$B$14,Scoring!$B$15,Scoring!$B$16)))) -> 2 | Y10: =IF($M10="","",ROUND((S10*Scoring!$B$6+U10*Scoring!$B$7)*IFERROR(INDEX(Scoring!$B$22:$B$24,MATCH($N10,Scoring!$A$22:$A$24,0)),1)+V10*Scoring!$B$8+X10,2)) -> 11 | Z10: =IF($M10="","",IF(SUMPRODUCT(($M$5:$M$249=$M10)*($G$5:$G$249>$G10))>0,0,IF(SUMPRODUCT(($M$5:$M$249=$M10)*($G$5:$G$249=$G10)*(ROW($M$5:$M$249)<ROW($M10)))>0,0,1))) -> 1 | AA10: =IF($Z10=1,RANK($AE10,$AE$5:$AE$249,0),"") -> 5 | AB10: Open | AC10: Link out; licence needed to display; run the PRD publication gate first (negative verdict) | AD10: QC: Blinkit card shows '6.6 lac'; read as 660,000 ratings (assumed). Other platforms not checked. | AE10: =IF($Z10=1,$Y10+$T10/1000000000-ROW()/10000000,"") -> 11.000659
A11: R007 | B11: Amul | C11: Masti Dahi Cup | D11: Everyday food | E11: Curd & yoghurt | F11: Passed | G11: 46026 | H11: MPC 338/01 | I11: Eurofins | J11: Trustified Pass/Fail | L11: https://www.trustified.in/passandfail/mastidahicup | M11: AMUL-DAHI-CUP | N11: Exact | O11: =IF($M11="","",IF(COUNTIFS('QC listings'!$A$5:$A$200,$M11,'QC listings'!$C$5:$C$200,O$4,'QC listings'!$F$5:$F$200,"Listing page")+COUNTIFS('QC listings'!$A$5:$A$200,$M11,'QC listings'!$C$5:$C$200,O$4,'QC listings'!$F$5:$F$200,"Brand page")>0,"Y",IF(COUNTIFS('QC listings'!$A$5:$A$200,$M11,'QC listings'!$C$5:$C$200,O$4)>0,"?","–"))) -> – | P11: =IF($M11="","",IF(COUNTIFS('QC listings'!$A$5:$A$200,$M11,'QC listings'!$C$5:$C$200,P$4,'QC listings'!$F$5:$F$200,"Listing page")+COUNTIFS('QC listings'!$A$5:$A$200,$M11,'QC listings'!$C$5:$C$200,P$4,'QC listings'!$F$5:$F$200,"Brand page")>0,"Y",IF(COUNTIFS('QC listings'!$A$5:$A$200,$M11,'QC listings'!$C$5:$C$200,P$4)>0,"?","–"))) -> Y | Q11: =IF($M11="","",IF(COUNTIFS('QC listings'!$A$5:$A$200,$M11,'QC listings'!$C$5:$C$200,Q$4,'QC listings'!$F$5:$F$200,"Listing page")+COUNTIFS('QC listings'!$A$5:$A$200,$M11,'QC listings'!$C$5:$C$200,Q$4,'QC listings'!$F$5:$F$200,"Brand page")>0,"Y",IF(COUNTIFS('QC listings'!$A$5:$A$200,$M11,'QC listings'!$C$5:$C$200,Q$4)>0,"?","–"))) -> – | R11: =IF($M11="","",IF(COUNTIFS('QC listings'!$A$5:$A$200,$M11,'QC listings'!$C$5:$C$200,R$4,'QC listings'!$F$5:$F$200,"Listing page")+COUNTIFS('QC listings'!$A$5:$A$200,$M11,'QC listings'!$C$5:$C$200,R$4,'QC listings'!$F$5:$F$200,"Brand page")>0,"Y",IF(COUNTIFS('QC listings'!$A$5:$A$200,$M11,'QC listings'!$C$5:$C$200,R$4)>0,"?","–"))) -> Y | S11: =IF($M11="","",COUNTIF(O11:R11,"Y")) -> 2 | T11: =IF($M11="","",SUMPRODUCT(MAX(('QC listings'!$A$5:$A$200=$M11)*'QC listings'!$E$5:$E$200))) -> 103152 | U11: =IF($M11="","",IF(T11>=Scoring!$B$11,3,IF(T11>=Scoring!$B$10,2,IF(T11>=Scoring!$B$9,1,0)))) -> 3 | V11: =IFERROR(INDEX(Scoring!$B$27:$B$56,MATCH($E11,Scoring!$A$27:$A$56,0)),0) -> 1 | W11: =IF($G11="","",ROUND((Scoring!$B$5-$G11)/30.4375,1)) -> 8.9 | X11: =IF($F11="Expired",Scoring!$B$18,IF($G11="",Scoring!$B$17,IF(W11<=Scoring!$B$12,Scoring!$B$13,IF(W11<=Scoring!$B$14,Scoring!$B$15,Scoring!$B$16)))) -> 2 | Y11: =IF($M11="","",ROUND((S11*Scoring!$B$6+U11*Scoring!$B$7)*IFERROR(INDEX(Scoring!$B$22:$B$24,MATCH($N11,Scoring!$A$22:$A$24,0)),1)+V11*Scoring!$B$8+X11,2)) -> 12 | Z11: =IF($M11="","",IF(SUMPRODUCT(($M$5:$M$249=$M11)*($G$5:$G$249>$G11))>0,0,IF(SUMPRODUCT(($M$5:$M$249=$M11)*($G$5:$G$249=$G11)*(ROW($M$5:$M$249)<ROW($M11)))>0,0,1))) -> 1 | AA11: =IF($Z11=1,RANK($AE11,$AE$5:$AE$249,0),"") -> 4 | AB11: Open | AC11: Link out; Trustified's written licence needed to display the report | AD11: QC: Zepto listing seen is a tub, not the cup pack. Blinkit and Instamart not seen. | AE11: =IF($Z11=1,$Y11+$T11/1000000000-ROW()/10000000,"") -> 12.000102
A12: R008 | B12: Epigamia | C12: Turbo 50 g | D12: Everyday food | E12: Curd & yoghurt | F12: Passed | G12: 45718 | H12: J00131 | I12: Eurofins | J12: Trustified Pass/Fail | L12: https://www.trustified.in/passandfail/epigamiayoughurt50 | O12: =IF($M12="","",IF(COUNTIFS('QC listings'!$A$5:$A$200,$M12,'QC listings'!$C$5:$C$200,O$4,'QC listings'!$F$5:$F$200,"Listing page")+COUNTIFS('QC listings'!$A$5:$A$200,$M12,'QC listings'!$C$5:$C$200,O$4,'QC listings'!$F$5:$F$200,"Brand page")>0,"Y",IF(COUNTIFS('QC listings'!$A$5:$A$200,$M12,'QC listings'!$C$5:$C$200,O$4)>0,"?","–"))) | P12: =IF($M12="","",IF(COUNTIFS('QC listings'!$A$5:$A$200,$M12,'QC listings'!$C$5:$C$200,P$4,'QC listings'!$F$5:$F$200,"Listing page")+COUNTIFS('QC listings'!$A$5:$A$200,$M12,'QC listings'!$C$5:$C$200,P$4,'QC listings'!$F$5:$F$200,"Brand page")>0,"Y",IF(COUNTIFS('QC listings'!$A$5:$A$200,$M12,'QC listings'!$C$5:$C$200,P$4)>0,"?","–"))) | Q12: =IF($M12="","",IF(COUNTIFS('QC listings'!$A$5:$A$200,$M12,'QC listings'!$C$5:$C$200,Q$4,'QC listings'!$F$5:$F$200,"Listing page")+COUNTIFS('QC listings'!$A$5:$A$200,$M12,'QC listings'!$C$5:$C$200,Q$4,'QC listings'!$F$5:$F$200,"Brand page")>0,"Y",IF(COUNTIFS('QC listings'!$A$5:$A$200,$M12,'QC listings'!$C$5:$C$200,Q$4)>0,"?","–"))) | R12: =IF($M12="","",IF(COUNTIFS('QC listings'!$A$5:$A$200,$M12,'QC listings'!$C$5:$C$200,R$4,'QC listings'!$F$5:$F$200,"Listing page")+COUNTIFS('QC listings'!$A$5:$A$200,$M12,'QC listings'!$C$5:$C$200,R$4,'QC listings'!$F$5:$F$200,"Brand page")>0,"Y",IF(COUNTIFS('QC listings'!$A$5:$A$200,$M12,'QC listings'!$C$5:$C$200,R$4)>0,"?","–"))) | S12: =IF($M12="","",COUNTIF(O12:R12,"Y")) | T12: =IF($M12="","",SUMPRODUCT(MAX(('QC listings'!$A$5:$A$200=$M12)*'QC listings'!$E$5:$E$200))) | U12: =IF($M12="","",IF(T12>=Scoring!$B$11,3,IF(T12>=Scoring!$B$10,2,IF(T12>=Scoring!$B$9,1,0)))) | V12: =IFERROR(INDEX(Scoring!$B$27:$B$56,MATCH($E12,Scoring!$A$27:$A$56,0)),0) -> 1 | W12: =IF($G12="","",ROUND((Scoring!$B$5-$G12)/30.4375,1)) -> 19 | X12: =IF($F12="Expired",Scoring!$B$18,IF($G12="",Scoring!$B$17,IF(W12<=Scoring!$B$12,Scoring!$B$13,IF(W12<=Scoring!$B$14,Scoring!$B$15,Scoring!$B$16)))) -> 1 | Y12: =IF($M12="","",ROUND((S12*Scoring!$B$6+U12*Scoring!$B$7)*IFERROR(INDEX(Scoring!$B$22:$B$24,MATCH($N12,Scoring!$A$22:$A$24,0)),1)+V12*Scoring!$B$8+X12,2)) | Z12: =IF($M12="","",IF(SUMPRODUCT(($M$5:$M$249=$M12)*($G$5:$G$249>$G12))>0,0,IF(SUMPRODUCT(($M$5:$M$249=$M12)*($G$5:$G$249=$G12)*(ROW($M$5:$M$249)<ROW($M12)))>0,0,1))) | AA12: =IF($Z12=1,RANK($AE12,$AE$5:$AE$249,0),"") | AB12: Open | AC12: Link out; Trustified's written licence needed to display the report | AE12: =IF($Z12=1,$Y12+$T12/1000000000-ROW()/10000000,"")
A13: R009 | B13: Beyond Snack | C13: Kerala Banana Chips | D13: Everyday food | E13: Packaged snacks | F13: Listed, rating not captured | I13: NABL labs (up to 3 per sample) | J13: Unbox Health | L13: https://www.unboxhealth.in/explore/product/7b605075-0bb8-4064-937e-de95e33c6672 | O13: =IF($M13="","",IF(COUNTIFS('QC listings'!$A$5:$A$200,$M13,'QC listings'!$C$5:$C$200,O$4,'QC listings'!$F$5:$F$200,"Listing page")+COUNTIFS('QC listings'!$A$5:$A$200,$M13,'QC listings'!$C$5:$C$200,O$4,'QC listings'!$F$5:$F$200,"Brand page")>0,"Y",IF(COUNTIFS('QC listings'!$A$5:$A$200,$M13,'QC listings'!$C$5:$C$200,O$4)>0,"?","–"))) | P13: =IF($M13="","",IF(COUNTIFS('QC listings'!$A$5:$A$200,$M13,'QC listings'!$C$5:$C$200,P$4,'QC listings'!$F$5:$F$200,"Listing page")+COUNTIFS('QC listings'!$A$5:$A$200,$M13,'QC listings'!$C$5:$C$200,P$4,'QC listings'!$F$5:$F$200,"Brand page")>0,"Y",IF(COUNTIFS('QC listings'!$A$5:$A$200,$M13,'QC listings'!$C$5:$C$200,P$4)>0,"?","–"))) | Q13: =IF($M13="","",IF(COUNTIFS('QC listings'!$A$5:$A$200,$M13,'QC listings'!$C$5:$C$200,Q$4,'QC listings'!$F$5:$F$200,"Listing page")+COUNTIFS('QC listings'!$A$5:$A$200,$M13,'QC listings'!$C$5:$C$200,Q$4,'QC listings'!$F$5:$F$200,"Brand page")>0,"Y",IF(COUNTIFS('QC listings'!$A$5:$A$200,$M13,'QC listings'!$C$5:$C$200,Q$4)>0,"?","–"))) | R13: =IF($M13="","",IF(COUNTIFS('QC listings'!$A$5:$A$200,$M13,'QC listings'!$C$5:$C$200,R$4,'QC listings'!$F$5:$F$200,"Listing page")+COUNTIFS('QC listings'!$A$5:$A$200,$M13,'QC listings'!$C$5:$C$200,R$4,'QC listings'!$F$5:$F$200,"Brand page")>0,"Y",IF(COUNTIFS('QC listings'!$A$5:$A$200,$M13,'QC listings'!$C$5:$C$200,R$4)>0,"?","–"))) | S13: =IF($M13="","",COUNTIF(O13:R13,"Y")) | T13: =IF($M13="","",SUMPRODUCT(MAX(('QC listings'!$A$5:$A$200=$M13)*'QC listings'!$E$5:$E$200))) | U13: =IF($M13="","",IF(T13>=Scoring!$B$11,3,IF(T13>=Scoring!$B$10,2,IF(T13>=Scoring!$B$9,1,0)))) | V13: =IFERROR(INDEX(Scoring!$B$27:$B$56,MATCH($E13,Scoring!$A$27:$A$56,0)),0) -> 1 | W13: =IF($G13="","",ROUND((Scoring!$B$5-$G13)/30.4375,1)) | X13: =IF($F13="Expired",Scoring!$B$18,IF($G13="",Scoring!$B$17,IF(W13<=Scoring!$B$12,Scoring!$B$13,IF(W13<=Scoring!$B$14,Scoring!$B$15,Scoring!$B$16)))) -> 1 | Y13: =IF($M13="","",ROUND((S13*Scoring!$B$6+U13*Scoring!$B$7)*IFERROR(INDEX(Scoring!$B$22:$B$24,MATCH($N13,Scoring!$A$22:$A$24,0)),1)+V13*Scoring!$B$8+X13,2)) | Z13: =IF($M13="","",IF(SUMPRODUCT(($M$5:$M$249=$M13)*($G$5:$G$249>$G13))>0,0,IF(SUMPRODUCT(($M$5:$M$249=$M13)*($G$5:$G$249=$G13)*(ROW($M$5:$M$249)<ROW($M13)))>0,0,1))) | AA13: =IF($Z13=1,RANK($AE13,$AE$5:$AE$249,0),"") | AB13: Free login for full report | AC13: Competitor rating: link out only; full report needs a free login | AE13: =IF($Z13=1,$Y13+$T13/1000000000-ROW()/10000000,"")
A14: R010 | B14: Farmley | C14: Makhana | D14: Everyday food | E14: Packaged snacks | F14: Failed | G14: 45684 | H14: CO77G141125B | I14: Eurofins | J14: Trustified Pass/Fail | L14: https://www.trustified.in/passandfail/farmleymakhana | O14: =IF($M14="","",IF(COUNTIFS('QC listings'!$A$5:$A$200,$M14,'QC listings'!$C$5:$C$200,O$4,'QC listings'!$F$5:$F$200,"Listing page")+COUNTIFS('QC listings'!$A$5:$A$200,$M14,'QC listings'!$C$5:$C$200,O$4,'QC listings'!$F$5:$F$200,"Brand page")>0,"Y",IF(COUNTIFS('QC listings'!$A$5:$A$200,$M14,'QC listings'!$C$5:$C$200,O$4)>0,"?","–"))) | P14: =IF($M14="","",IF(COUNTIFS('QC listings'!$A$5:$A$200,$M14,'QC listings'!$C$5:$C$200,P$4,'QC listings'!$F$5:$F$200,"Listing page")+COUNTIFS('QC listings'!$A$5:$A$200,$M14,'QC listings'!$C$5:$C$200,P$4,'QC listings'!$F$5:$F$200,"Brand page")>0,"Y",IF(COUNTIFS('QC listings'!$A$5:$A$200,$M14,'QC listings'!$C$5:$C$200,P$4)>0,"?","–"))) | Q14: =IF($M14="","",IF(COUNTIFS('QC listings'!$A$5:$A$200,$M14,'QC listings'!$C$5:$C$200,Q$4,'QC listings'!$F$5:$F$200,"Listing page")+COUNTIFS('QC listings'!$A$5:$A$200,$M14,'QC listings'!$C$5:$C$200,Q$4,'QC listings'!$F$5:$F$200,"Brand page")>0,"Y",IF(COUNTIFS('QC listings'!$A$5:$A$200,$M14,'QC listings'!$C$5:$C$200,Q$4)>0,"?","–"))) | R14: =IF($M14="","",IF(COUNTIFS('QC listings'!$A$5:$A$200,$M14,'QC listings'!$C$5:$C$200,R$4,'QC listings'!$F$5:$F$200,"Listing page")+COUNTIFS('QC listings'!$A$5:$A$200,$M14,'QC listings'!$C$5:$C$200,R$4,'QC listings'!$F$5:$F$200,"Brand page")>0,"Y",IF(COUNTIFS('QC listings'!$A$5:$A$200,$M14,'QC listings'!$C$5:$C$200,R$4)>0,"?","–"))) | S14: =IF($M14="","",COUNTIF(O14:R14,"Y")) | T14: =IF($M14="","",SUMPRODUCT(MAX(('QC listings'!$A$5:$A$200=$M14)*'QC listings'!$E$5:$E$200))) | U14: =IF($M14="","",IF(T14>=Scoring!$B$11,3,IF(T14>=Scoring!$B$10,2,IF(T14>=Scoring!$B$9,1,0)))) | V14: =IFERROR(INDEX(Scoring!$B$27:$B$56,MATCH($E14,Scoring!$A$27:$A$56,0)),0) -> 1 | W14: =IF($G14="","",ROUND((Scoring!$B$5-$G14)/30.4375,1)) -> 20.1 | X14: =IF($F14="Expired",Scoring!$B$18,IF($G14="",Scoring!$B$17,IF(W14<=Scoring!$B$12,Scoring!$B$13,IF(W14<=Scoring!$B$14,Scoring!$B$15,Scoring!$B$16)))) -> 1 | Y14: =IF($M14="","",ROUND((S14*Scoring!$B$6+U14*Scoring!$B$7)*IFERROR(INDEX(Scoring!$B$22:$B$24,MATCH($N14,Scoring!$A$22:$A$24,0)),1)+V14*Scoring!$B$8+X14,2)) | Z14: =IF($M14="","",IF(SUMPRODUCT(($M$5:$M$249=$M14)*($G$5:$G$249>$G14))>0,0,IF(SUMPRODUCT(($M$5:$M$249=$M14)*($G$5:$G$249=$G14)*(ROW($M$5:$M$249)<ROW($M14)))>0,0,1))) | AA14: =IF($Z14=1,RANK($AE14,$AE$5:$AE$249,0),"") | AB14: Open | AC14: Link out; licence needed to display; run the PRD publication gate first (negative verdict) | AD14: Check the date: the published date (Jan 2025) looks earlier than the batch code implies | AE14: =IF($Z14=1,$Y14+$T14/1000000000-ROW()/10000000,"")
A15: R011 | B15: Haldiram's | C15: Salted Peanuts | D15: Everyday food | E15: Packaged snacks | F15: Passed | G15: 45764 | H15: 24018 | I15: Eurofins | J15: Trustified Pass/Fail | L15: https://www.trustified.in/passandfail/haldiramspeanuts | M15: HALDIRAMS-PEANUT | N15: Exact | O15: =IF($M15="","",IF(COUNTIFS('QC listings'!$A$5:$A$200,$M15,'QC listings'!$C$5:$C$200,O$4,'QC listings'!$F$5:$F$200,"Listing page")+COUNTIFS('QC listings'!$A$5:$A$200,$M15,'QC listings'!$C$5:$C$200,O$4,'QC listings'!$F$5:$F$200,"Brand page")>0,"Y",IF(COUNTIFS('QC listings'!$A$5:$A$200,$M15,'QC listings'!$C$5:$C$200,O$4)>0,"?","–"))) -> Y | P15: =IF($M15="","",IF(COUNTIFS('QC listings'!$A$5:$A$200,$M15,'QC listings'!$C$5:$C$200,P$4,'QC listings'!$F$5:$F$200,"Listing page")+COUNTIFS('QC listings'!$A$5:$A$200,$M15,'QC listings'!$C$5:$C$200,P$4,'QC listings'!$F$5:$F$200,"Brand page")>0,"Y",IF(COUNTIFS('QC listings'!$A$5:$A$200,$M15,'QC listings'!$C$5:$C$200,P$4)>0,"?","–"))) -> Y | Q15: =IF($M15="","",IF(COUNTIFS('QC listings'!$A$5:$A$200,$M15,'QC listings'!$C$5:$C$200,Q$4,'QC listings'!$F$5:$F$200,"Listing page")+COUNTIFS('QC listings'!$A$5:$A$200,$M15,'QC listings'!$C$5:$C$200,Q$4,'QC listings'!$F$5:$F$200,"Brand page")>0,"Y",IF(COUNTIFS('QC listings'!$A$5:$A$200,$M15,'QC listings'!$C$5:$C$200,Q$4)>0,"?","–"))) -> Y | R15: =IF($M15="","",IF(COUNTIFS('QC listings'!$A$5:$A$200,$M15,'QC listings'!$C$5:$C$200,R$4,'QC listings'!$F$5:$F$200,"Listing page")+COUNTIFS('QC listings'!$A$5:$A$200,$M15,'QC listings'!$C$5:$C$200,R$4,'QC listings'!$F$5:$F$200,"Brand page")>0,"Y",IF(COUNTIFS('QC listings'!$A$5:$A$200,$M15,'QC listings'!$C$5:$C$200,R$4)>0,"?","–"))) -> Y | S15: =IF($M15="","",COUNTIF(O15:R15,"Y")) -> 4 | T15: =IF($M15="","",SUMPRODUCT(MAX(('QC listings'!$A$5:$A$200=$M15)*'QC listings'!$E$5:$E$200))) -> 38843 | U15: =IF($M15="","",IF(T15>=Scoring!$B$11,3,IF(T15>=Scoring!$B$10,2,IF(T15>=Scoring!$B$9,1,0)))) -> 2 | V15: =IFERROR(INDEX(Scoring!$B$27:$B$56,MATCH($E15,Scoring!$A$27:$A$56,0)),0) -> 1 | W15: =IF($G15="","",ROUND((Scoring!$B$5-$G15)/30.4375,1)) -> 17.5 | X15: =IF($F15="Expired",Scoring!$B$18,IF($G15="",Scoring!$B$17,IF(W15<=Scoring!$B$12,Scoring!$B$13,IF(W15<=Scoring!$B$14,Scoring!$B$15,Scoring!$B$16)))) -> 1 | Y15: =IF($M15="","",ROUND((S15*Scoring!$B$6+U15*Scoring!$B$7)*IFERROR(INDEX(Scoring!$B$22:$B$24,MATCH($N15,Scoring!$A$22:$A$24,0)),1)+V15*Scoring!$B$8+X15,2)) -> 11 | Z15: =IF($M15="","",IF(SUMPRODUCT(($M$5:$M$249=$M15)*($G$5:$G$249>$G15))>0,0,IF(SUMPRODUCT(($M$5:$M$249=$M15)*($G$5:$G$249=$G15)*(ROW($M$5:$M$249)<ROW($M15)))>0,0,1))) -> 1 | AA15: =IF($Z15=1,RANK($AE15,$AE$5:$AE$249,0),"") -> 7 | AB15: Open | AC15: Link out; Trustified's written licence needed to display the report | AE15: =IF($Z15=1,$Y15+$T15/1000000000-ROW()/10000000,"") -> 11.000037
A16: R012 | B16: Lay's | C16: India's Magic Masala Potato Chips | D16: Everyday food | E16: Packaged snacks | F16: Rated | I16: NABL labs (up to 3 per sample) | J16: Unbox Health | K16: 7.4 / 10 | L16: https://www.unboxhealth.in/explore/product/lays-potato-chips---indias-magic-masala/c7bdd404-97eb-4470-812d-d4fc4a68c944 | O16: =IF($M16="","",IF(COUNTIFS('QC listings'!$A$5:$A$200,$M16,'QC listings'!$C$5:$C$200,O$4,'QC listings'!$F$5:$F$200,"Listing page")+COUNTIFS('QC listings'!$A$5:$A$200,$M16,'QC listings'!$C$5:$C$200,O$4,'QC listings'!$F$5:$F$200,"Brand page")>0,"Y",IF(COUNTIFS('QC listings'!$A$5:$A$200,$M16,'QC listings'!$C$5:$C$200,O$4)>0,"?","–"))) | P16: =IF($M16="","",IF(COUNTIFS('QC listings'!$A$5:$A$200,$M16,'QC listings'!$C$5:$C$200,P$4,'QC listings'!$F$5:$F$200,"Listing page")+COUNTIFS('QC listings'!$A$5:$A$200,$M16,'QC listings'!$C$5:$C$200,P$4,'QC listings'!$F$5:$F$200,"Brand page")>0,"Y",IF(COUNTIFS('QC listings'!$A$5:$A$200,$M16,'QC listings'!$C$5:$C$200,P$4)>0,"?","–"))) | Q16: =IF($M16="","",IF(COUNTIFS('QC listings'!$A$5:$A$200,$M16,'QC listings'!$C$5:$C$200,Q$4,'QC listings'!$F$5:$F$200,"Listing page")+COUNTIFS('QC listings'!$A$5:$A$200,$M16,'QC listings'!$C$5:$C$200,Q$4,'QC listings'!$F$5:$F$200,"Brand page")>0,"Y",IF(COUNTIFS('QC listings'!$A$5:$A$200,$M16,'QC listings'!$C$5:$C$200,Q$4)>0,"?","–"))) | R16: =IF($M16="","",IF(COUNTIFS('QC listings'!$A$5:$A$200,$M16,'QC listings'!$C$5:$C$200,R$4,'QC listings'!$F$5:$F$200,"Listing page")+COUNTIFS('QC listings'!$A$5:$A$200,$M16,'QC listings'!$C$5:$C$200,R$4,'QC listings'!$F$5:$F$200,"Brand page")>0,"Y",IF(COUNTIFS('QC listings'!$A$5:$A$200,$M16,'QC listings'!$C$5:$C$200,R$4)>0,"?","–"))) | S16: =IF($M16="","",COUNTIF(O16:R16,"Y")) | T16: =IF($M16="","",SUMPRODUCT(MAX(('QC listings'!$A$5:$A$200=$M16)*'QC listings'!$E$5:$E$200))) | U16: =IF($M16="","",IF(T16>=Scoring!$B$11,3,IF(T16>=Scoring!$B$10,2,IF(T16>=Scoring!$B$9,1,0)))) | V16: =IFERROR(INDEX(Scoring!$B$27:$B$56,MATCH($E16,Scoring!$A$27:$A$56,0)),0) -> 1 | W16: =IF($G16="","",ROUND((Scoring!$B$5-$G16)/30.4375,1)) | X16: =IF($F16="Expired",Scoring!$B$18,IF($G16="",Scoring!$B$17,IF(W16<=Scoring!$B$12,Scoring!$B$13,IF(W16<=Scoring!$B$14,Scoring!$B$15,Scoring!$B$16)))) -> 1 | Y16: =IF($M16="","",ROUND((S16*Scoring!$B$6+U16*Scoring!$B$7)*IFERROR(INDEX(Scoring!$B$22:$B$24,MATCH($N16,Scoring!$A$22:$A$24,0)),1)+V16*Scoring!$B$8+X16,2)) | Z16: =IF($M16="","",IF(SUMPRODUCT(($M$5:$M$249=$M16)*($G$5:$G$249>$G16))>0,0,IF(SUMPRODUCT(($M$5:$M$249=$M16)*($G$5:$G$249=$G16)*(ROW($M$5:$M$249)<ROW($M16)))>0,0,1))) | AA16: =IF($Z16=1,RANK($AE16,$AE$5:$AE$249,0),"") | AB16: Free login for full report | AC16: Competitor rating: link out only; full report needs a free login | AD16: Score 7.4 out of 10; letter grade not captured | AE16: =IF($Z16=1,$Y16+$T16/1000000000-ROW()/10000000,"")
A17: R013 | B17: RiteBite | C17: Max Protein Chips – Cheese Jalapeno | D17: Everyday food | E17: Packaged snacks | F17: Rated | I17: NABL labs (up to 3 per sample) | J17: Unbox Health | K17: B+ · 8.6 | L17: https://www.unboxhealth.in/explore/product/ritebite-max-protein-cheese-jalapeno-chips/b733c200-c16b-4468-9c91-0cea00930364 | O17: =IF($M17="","",IF(COUNTIFS('QC listings'!$A$5:$A$200,$M17,'QC listings'!$C$5:$C$200,O$4,'QC listings'!$F$5:$F$200,"Listing page")+COUNTIFS('QC listings'!$A$5:$A$200,$M17,'QC listings'!$C$5:$C$200,O$4,'QC listings'!$F$5:$F$200,"Brand page")>0,"Y",IF(COUNTIFS('QC listings'!$A$5:$A$200,$M17,'QC listings'!$C$5:$C$200,O$4)>0,"?","–"))) | P17: =IF($M17="","",IF(COUNTIFS('QC listings'!$A$5:$A$200,$M17,'QC listings'!$C$5:$C$200,P$4,'QC listings'!$F$5:$F$200,"Listing page")+COUNTIFS('QC listings'!$A$5:$A$200,$M17,'QC listings'!$C$5:$C$200,P$4,'QC listings'!$F$5:$F$200,"Brand page")>0,"Y",IF(COUNTIFS('QC listings'!$A$5:$A$200,$M17,'QC listings'!$C$5:$C$200,P$4)>0,"?","–"))) | Q17: =IF($M17="","",IF(COUNTIFS('QC listings'!$A$5:$A$200,$M17,'QC listings'!$C$5:$C$200,Q$4,'QC listings'!$F$5:$F$200,"Listing page")+COUNTIFS('QC listings'!$A$5:$A$200,$M17,'QC listings'!$C$5:$C$200,Q$4,'QC listings'!$F$5:$F$200,"Brand page")>0,"Y",IF(COUNTIFS('QC listings'!$A$5:$A$200,$M17,'QC listings'!$C$5:$C$200,Q$4)>0,"?","–"))) | R17: =IF($M17="","",IF(COUNTIFS('QC listings'!$A$5:$A$200,$M17,'QC listings'!$C$5:$C$200,R$4,'QC listings'!$F$5:$F$200,"Listing page")+COUNTIFS('QC listings'!$A$5:$A$200,$M17,'QC listings'!$C$5:$C$200,R$4,'QC listings'!$F$5:$F$200,"Brand page")>0,"Y",IF(COUNTIFS('QC listings'!$A$5:$A$200,$M17,'QC listings'!$C$5:$C$200,R$4)>0,"?","–"))) | S17: =IF($M17="","",COUNTIF(O17:R17,"Y")) | T17: =IF($M17="","",SUMPRODUCT(MAX(('QC listings'!$A$5:$A$200=$M17)*'QC listings'!$E$5:$E$200))) | U17: =IF($M17="","",IF(T17>=Scoring!$B$11,3,IF(T17>=Scoring!$B$10,2,IF(T17>=Scoring!$B$9,1,0)))) | V17: =IFERROR(INDEX(Scoring!$B$27:$B$56,MATCH($E17,Scoring!$A$27:$A$56,0)),0) -> 1 | W17: =IF($G17="","",ROUND((Scoring!$B$5-$G17)/30.4375,1)) | X17: =IF($F17="Expired",Scoring!$B$18,IF($G17="",Scoring!$B$17,IF(W17<=Scoring!$B$12,Scoring!$B$13,IF(W17<=Scoring!$B$14,Scoring!$B$15,Scoring!$B$16)))) -> 1 | Y17: =IF($M17="","",ROUND((S17*Scoring!$B$6+U17*Scoring!$B$7)*IFERROR(INDEX(Scoring!$B$22:$B$24,MATCH($N17,Scoring!$A$22:$A$24,0)),1)+V17*Scoring!$B$8+X17,2)) | Z17: =IF($M17="","",IF(SUMPRODUCT(($M$5:$M$249=$M17)*($G$5:$G$249>$G17))>0,0,IF(SUMPRODUCT(($M$5:$M$249=$M17)*($G$5:$G$249=$G17)*(ROW($M$5:$M$249)<ROW($M17)))>0,0,1))) | AA17: =IF($Z17=1,RANK($AE17,$AE$5:$AE$249,0),"") | AB17: Free login for full report | AC17: Competitor rating: link out only; full report needs a free login | AE17: =IF($Z17=1,$Y17+$T17/1000000000-ROW()/10000000,"")
A18: R014 | B18: Snackible | C18: Ragi Chips – Peri Peri | D18: Everyday food | E18: Packaged snacks | F18: Listed, rating not captured | I18: NABL labs (up to 3 per sample) | J18: Unbox Health | L18: https://www.unboxhealth.in/explore/product/3dfb3950-582e-4b56-ba0b-0c2391329388 | O18: =IF($M18="","",IF(COUNTIFS('QC listings'!$A$5:$A$200,$M18,'QC listings'!$C$5:$C$200,O$4,'QC listings'!$F$5:$F$200,"Listing page")+COUNTIFS('QC listings'!$A$5:$A$200,$M18,'QC listings'!$C$5:$C$200,O$4,'QC listings'!$F$5:$F$200,"Brand page")>0,"Y",IF(COUNTIFS('QC listings'!$A$5:$A$200,$M18,'QC listings'!$C$5:$C$200,O$4)>0,"?","–"))) | P18: =IF($M18="","",IF(COUNTIFS('QC listings'!$A$5:$A$200,$M18,'QC listings'!$C$5:$C$200,P$4,'QC listings'!$F$5:$F$200,"Listing page")+COUNTIFS('QC listings'!$A$5:$A$200,$M18,'QC listings'!$C$5:$C$200,P$4,'QC listings'!$F$5:$F$200,"Brand page")>0,"Y",IF(COUNTIFS('QC listings'!$A$5:$A$200,$M18,'QC listings'!$C$5:$C$200,P$4)>0,"?","–"))) | Q18: =IF($M18="","",IF(COUNTIFS('QC listings'!$A$5:$A$200,$M18,'QC listings'!$C$5:$C$200,Q$4,'QC listings'!$F$5:$F$200,"Listing page")+COUNTIFS('QC listings'!$A$5:$A$200,$M18,'QC listings'!$C$5:$C$200,Q$4,'QC listings'!$F$5:$F$200,"Brand page")>0,"Y",IF(COUNTIFS('QC listings'!$A$5:$A$200,$M18,'QC listings'!$C$5:$C$200,Q$4)>0,"?","–"))) | R18: =IF($M18="","",IF(COUNTIFS('QC listings'!$A$5:$A$200,$M18,'QC listings'!$C$5:$C$200,R$4,'QC listings'!$F$5:$F$200,"Listing page")+COUNTIFS('QC listings'!$A$5:$A$200,$M18,'QC listings'!$C$5:$C$200,R$4,'QC listings'!$F$5:$F$200,"Brand page")>0,"Y",IF(COUNTIFS('QC listings'!$A$5:$A$200,$M18,'QC listings'!$C$5:$C$200,R$4)>0,"?","–"))) | S18: =IF($M18="","",COUNTIF(O18:R18,"Y")) | T18: =IF($M18="","",SUMPRODUCT(MAX(('QC listings'!$A$5:$A$200=$M18)*'QC listings'!$E$5:$E$200))) | U18: =IF($M18="","",IF(T18>=Scoring!$B$11,3,IF(T18>=Scoring!$B$10,2,IF(T18>=Scoring!$B$9,1,0)))) | V18: =IFERROR(INDEX(Scoring!$B$27:$B$56,MATCH($E18,Scoring!$A$27:$A$56,0)),0) -> 1 | W18: =IF($G18="","",ROUND((Scoring!$B$5-$G18)/30.4375,1)) | X18: =IF($F18="Expired",Scoring!$B$18,IF($G18="",Scoring!$B$17,IF(W18<=Scoring!$B$12,Scoring!$B$13,IF(W18<=Scoring!$B$14,Scoring!$B$15,Scoring!$B$16)))) -> 1 | Y18: =IF($M18="","",ROUND((S18*Scoring!$B$6+U18*Scoring!$B$7)*IFERROR(INDEX(Scoring!$B$22:$B$24,MATCH($N18,Scoring!$A$22:$A$24,0)),1)+V18*Scoring!$B$8+X18,2)) | Z18: =IF($M18="","",IF(SUMPRODUCT(($M$5:$M$249=$M18)*($G$5:$G$249>$G18))>0,0,IF(SUMPRODUCT(($M$5:$M$249=$M18)*($G$5:$G$249=$G18)*(ROW($M$5:$M$249)<ROW($M18)))>0,0,1))) | AA18: =IF($Z18=1,RANK($AE18,$AE$5:$AE$249,0),"") | AB18: Free login for full report | AC18: Competitor rating: link out only; full report needs a free login | AE18: =IF($Z18=1,$Y18+$T18/1000000000-ROW()/10000000,"")
A19: R015 | B19: SuperYou | C19: Multigrain Protein Chips – Sour Cream & Onion | D19: Everyday food | E19: Packaged snacks | F19: Rated | I19: NABL labs (up to 3 per sample) | J19: Unbox Health | K19: B · 8.4 | L19: https://www.unboxhealth.in/explore/product/superyou-multigrain-protein-chips-sour-cream-onion/4c5f0fc0-347f-40ee-9ec8-348e967804b5 | O19: =IF($M19="","",IF(COUNTIFS('QC listings'!$A$5:$A$200,$M19,'QC listings'!$C$5:$C$200,O$4,'QC listings'!$F$5:$F$200,"Listing page")+COUNTIFS('QC listings'!$A$5:$A$200,$M19,'QC listings'!$C$5:$C$200,O$4,'QC listings'!$F$5:$F$200,"Brand page")>0,"Y",IF(COUNTIFS('QC listings'!$A$5:$A$200,$M19,'QC listings'!$C$5:$C$200,O$4)>0,"?","–"))) | P19: =IF($M19="","",IF(COUNTIFS('QC listings'!$A$5:$A$200,$M19,'QC listings'!$C$5:$C$200,P$4,'QC listings'!$F$5:$F$200,"Listing page")+COUNTIFS('QC listings'!$A$5:$A$200,$M19,'QC listings'!$C$5:$C$200,P$4,'QC listings'!$F$5:$F$200,"Brand page")>0,"Y",IF(COUNTIFS('QC listings'!$A$5:$A$200,$M19,'QC listings'!$C$5:$C$200,P$4)>0,"?","–"))) | Q19: =IF($M19="","",IF(COUNTIFS('QC listings'!$A$5:$A$200,$M19,'QC listings'!$C$5:$C$200,Q$4,'QC listings'!$F$5:$F$200,"Listing page")+COUNTIFS('QC listings'!$A$5:$A$200,$M19,'QC listings'!$C$5:$C$200,Q$4,'QC listings'!$F$5:$F$200,"Brand page")>0,"Y",IF(COUNTIFS('QC listings'!$A$5:$A$200,$M19,'QC listings'!$C$5:$C$200,Q$4)>0,"?","–"))) | R19: =IF($M19="","",IF(COUNTIFS('QC listings'!$A$5:$A$200,$M19,'QC listings'!$C$5:$C$200,R$4,'QC listings'!$F$5:$F$200,"Listing page")+COUNTIFS('QC listings'!$A$5:$A$200,$M19,'QC listings'!$C$5:$C$200,R$4,'QC listings'!$F$5:$F$200,"Brand page")>0,"Y",IF(COUNTIFS('QC listings'!$A$5:$A$200,$M19,'QC listings'!$C$5:$C$200,R$4)>0,"?","–"))) | S19: =IF($M19="","",COUNTIF(O19:R19,"Y")) | T19: =IF($M19="","",SUMPRODUCT(MAX(('QC listings'!$A$5:$A$200=$M19)*'QC listings'!$E$5:$E$200))) | U19: =IF($M19="","",IF(T19>=Scoring!$B$11,3,IF(T19>=Scoring!$B$10,2,IF(T19>=Scoring!$B$9,1,0)))) | V19: =IFERROR(INDEX(Scoring!$B$27:$B$56,MATCH($E19,Scoring!$A$27:$A$56,0)),0) -> 1 | W19: =IF($G19="","",ROUND((Scoring!$B$5-$G19)/30.4375,1)) | X19: =IF($F19="Expired",Scoring!$B$18,IF($G19="",Scoring!$B$17,IF(W19<=Scoring!$B$12,Scoring!$B$13,IF(W19<=Scoring!$B$14,Scoring!$B$15,Scoring!$B$16)))) -> 1 | Y19: =IF($M19="","",ROUND((S19*Scoring!$B$6+U19*Scoring!$B$7)*IFERROR(INDEX(Scoring!$B$22:$B$24,MATCH($N19,Scoring!$A$22:$A$24,0)),1)+V19*Scoring!$B$8+X19,2)) | Z19: =IF($M19="","",IF(SUMPRODUCT(($M$5:$M$249=$M19)*($G$5:$G$249>$G19))>0,0,IF(SUMPRODUCT(($M$5:$M$249=$M19)*($G$5:$G$249=$G19)*(ROW($M$5:$M$249)<ROW($M19)))>0,0,1))) | AA19: =IF($Z19=1,RANK($AE19,$AE$5:$AE$249,0),"") | AB19: Free login for full report | AC19: Competitor rating: link out only; full report needs a free login | AE19: =IF($Z19=1,$Y19+$T19/1000000000-ROW()/10000000,"")
A20: R016 | B20: Taali | C20: Jowar Protein Puffs – Masala Mania | D20: Everyday food | E20: Packaged snacks | F20: Rated | I20: NABL labs (up to 3 per sample) | J20: Unbox Health | K20: A · 9.3 | L20: https://www.unboxhealth.in/explore/product/taali-jowar-protein-puffs-masala-mania/9f25514e-fea0-4fce-8e84-999aea95b452 | O20: =IF($M20="","",IF(COUNTIFS('QC listings'!$A$5:$A$200,$M20,'QC listings'!$C$5:$C$200,O$4,'QC listings'!$F$5:$F$200,"Listing page")+COUNTIFS('QC listings'!$A$5:$A$200,$M20,'QC listings'!$C$5:$C$200,O$4,'QC listings'!$F$5:$F$200,"Brand page")>0,"Y",IF(COUNTIFS('QC listings'!$A$5:$A$200,$M20,'QC listings'!$C$5:$C$200,O$4)>0,"?","–"))) | P20: =IF($M20="","",IF(COUNTIFS('QC listings'!$A$5:$A$200,$M20,'QC listings'!$C$5:$C$200,P$4,'QC listings'!$F$5:$F$200,"Listing page")+COUNTIFS('QC listings'!$A$5:$A$200,$M20,'QC listings'!$C$5:$C$200,P$4,'QC listings'!$F$5:$F$200,"Brand page")>0,"Y",IF(COUNTIFS('QC listings'!$A$5:$A$200,$M20,'QC listings'!$C$5:$C$200,P$4)>0,"?","–"))) | Q20: =IF($M20="","",IF(COUNTIFS('QC listings'!$A$5:$A$200,$M20,'QC listings'!$C$5:$C$200,Q$4,'QC listings'!$F$5:$F$200,"Listing page")+COUNTIFS('QC listings'!$A$5:$A$200,$M20,'QC listings'!$C$5:$C$200,Q$4,'QC listings'!$F$5:$F$200,"Brand page")>0,"Y",IF(COUNTIFS('QC listings'!$A$5:$A$200,$M20,'QC listings'!$C$5:$C$200,Q$4)>0,"?","–"))) | R20: =IF($M20="","",IF(COUNTIFS('QC listings'!$A$5:$A$200,$M20,'QC listings'!$C$5:$C$200,R$4,'QC listings'!$F$5:$F$200,"Listing page")+COUNTIFS('QC listings'!$A$5:$A$200,$M20,'QC listings'!$C$5:$C$200,R$4,'QC listings'!$F$5:$F$200,"Brand page")>0,"Y",IF(COUNTIFS('QC listings'!$A$5:$A$200,$M20,'QC listings'!$C$5:$C$200,R$4)>0,"?","–"))) | S20: =IF($M20="","",COUNTIF(O20:R20,"Y")) | T20: =IF($M20="","",SUMPRODUCT(MAX(('QC listings'!$A$5:$A$200=$M20)*'QC listings'!$E$5:$E$200))) | U20: =IF($M20="","",IF(T20>=Scoring!$B$11,3,IF(T20>=Scoring!$B$10,2,IF(T20>=Scoring!$B$9,1,0)))) | V20: =IFERROR(INDEX(Scoring!$B$27:$B$56,MATCH($E20,Scoring!$A$27:$A$56,0)),0) -> 1 | W20: =IF($G20="","",ROUND((Scoring!$B$5-$G20)/30.4375,1)) | X20: =IF($F20="Expired",Scoring!$B$18,IF($G20="",Scoring!$B$17,IF(W20<=Scoring!$B$12,Scoring!$B$13,IF(W20<=Scoring!$B$14,Scoring!$B$15,Scoring!$B$16)))) -> 1 | Y20: =IF($M20="","",ROUND((S20*Scoring!$B$6+U20*Scoring!$B$7)*IFERROR(INDEX(Scoring!$B$22:$B$24,MATCH($N20,Scoring!$A$22:$A$24,0)),1)+V20*Scoring!$B$8+X20,2)) | Z20: =IF($M20="","",IF(SUMPRODUCT(($M$5:$M$249=$M20)*($G$5:$G$249>$G20))>0,0,IF(SUMPRODUCT(($M$5:$M$249=$M20)*($G$5:$G$249=$G20)*(ROW($M$5:$M$249)<ROW($M20)))>0,0,1))) | AA20: =IF($Z20=1,RANK($AE20,$AE$5:$AE$249,0),"") | AB20: Free login for full report | AC20: Competitor rating: link out only; full report needs a free login | AE20: =IF($Z20=1,$Y20+$T20/1000000000-ROW()/10000000,"")
A21: R017 | B21: Too Yumm | C21: Spicy Chilli Wafers (potato chips) | D21: Everyday food | E21: Packaged snacks | F21: Rated | I21: NABL labs (up to 3 per sample) | J21: Unbox Health | K21: C · 7.5 | L21: https://www.unboxhealth.in/explore/product/too-yumm-spicy-chilli-wafers-potato-chips/8c2e8764-4b6a-4370-b2bd-ce354f3f66a6 | O21: =IF($M21="","",IF(COUNTIFS('QC listings'!$A$5:$A$200,$M21,'QC listings'!$C$5:$C$200,O$4,'QC listings'!$F$5:$F$200,"Listing page")+COUNTIFS('QC listings'!$A$5:$A$200,$M21,'QC listings'!$C$5:$C$200,O$4,'QC listings'!$F$5:$F$200,"Brand page")>0,"Y",IF(COUNTIFS('QC listings'!$A$5:$A$200,$M21,'QC listings'!$C$5:$C$200,O$4)>0,"?","–"))) | P21: =IF($M21="","",IF(COUNTIFS('QC listings'!$A$5:$A$200,$M21,'QC listings'!$C$5:$C$200,P$4,'QC listings'!$F$5:$F$200,"Listing page")+COUNTIFS('QC listings'!$A$5:$A$200,$M21,'QC listings'!$C$5:$C$200,P$4,'QC listings'!$F$5:$F$200,"Brand page")>0,"Y",IF(COUNTIFS('QC listings'!$A$5:$A$200,$M21,'QC listings'!$C$5:$C$200,P$4)>0,"?","–"))) | Q21: =IF($M21="","",IF(COUNTIFS('QC listings'!$A$5:$A$200,$M21,'QC listings'!$C$5:$C$200,Q$4,'QC listings'!$F$5:$F$200,"Listing page")+COUNTIFS('QC listings'!$A$5:$A$200,$M21,'QC listings'!$C$5:$C$200,Q$4,'QC listings'!$F$5:$F$200,"Brand page")>0,"Y",IF(COUNTIFS('QC listings'!$A$5:$A$200,$M21,'QC listings'!$C$5:$C$200,Q$4)>0,"?","–"))) | R21: =IF($M21="","",IF(COUNTIFS('QC listings'!$A$5:$A$200,$M21,'QC listings'!$C$5:$C$200,R$4,'QC listings'!$F$5:$F$200,"Listing page")+COUNTIFS('QC listings'!$A$5:$A$200,$M21,'QC listings'!$C$5:$C$200,R$4,'QC listings'!$F$5:$F$200,"Brand page")>0,"Y",IF(COUNTIFS('QC listings'!$A$5:$A$200,$M21,'QC listings'!$C$5:$C$200,R$4)>0,"?","–"))) | S21: =IF($M21="","",COUNTIF(O21:R21,"Y")) | T21: =IF($M21="","",SUMPRODUCT(MAX(('QC listings'!$A$5:$A$200=$M21)*'QC listings'!$E$5:$E$200))) | U21: =IF($M21="","",IF(T21>=Scoring!$B$11,3,IF(T21>=Scoring!$B$10,2,IF(T21>=Scoring!$B$9,1,0)))) | V21: =IFERROR(INDEX(Scoring!$B$27:$B$56,MATCH($E21,Scoring!$A$27:$A$56,0)),0) -> 1 | W21: =IF($G21="","",ROUND((Scoring!$B$5-$G21)/30.4375,1)) | X21: =IF($F21="Expired",Scoring!$B$18,IF($G21="",Scoring!$B$17,IF(W21<=Scoring!$B$12,Scoring!$B$13,IF(W21<=Scoring!$B$14,Scoring!$B$15,Scoring!$B$16)))) -> 1 | Y21: =IF($M21="","",ROUND((S21*Scoring!$B$6+U21*Scoring!$B$7)*IFERROR(INDEX(Scoring!$B$22:$B$24,MATCH($N21,Scoring!$A$22:$A$24,0)),1)+V21*Scoring!$B$8+X21,2)) | Z21: =IF($M21="","",IF(SUMPRODUCT(($M$5:$M$249=$M21)*($G$5:$G$249>$G21))>0,0,IF(SUMPRODUCT(($M$5:$M$249=$M21)*($G$5:$G$249=$G21)*(ROW($M$5:$M$249)<ROW($M21)))>0,0,1))) | AA21: =IF($Z21=1,RANK($AE21,$AE$5:$AE$249,0),"") | AB21: Free login for full report | AC21: Competitor rating: link out only; full report needs a free login | AE21: =IF($Z21=1,$Y21+$T21/1000000000-ROW()/10000000,"")
A22: R018 | B22: Minus 30 | C22: Mini Vegan & Sugar Free | D22: Everyday food | E22: Ice cream | F22: Failed | G22: 45674 | H22: 6 | I22: Eurofins | J22: Trustified Pass/Fail | L22: https://www.trustified.in/passandfail/minus30icecream | O22: =IF($M22="","",IF(COUNTIFS('QC listings'!$A$5:$A$200,$M22,'QC listings'!$C$5:$C$200,O$4,'QC listings'!$F$5:$F$200,"Listing page")+COUNTIFS('QC listings'!$A$5:$A$200,$M22,'QC listings'!$C$5:$C$200,O$4,'QC listings'!$F$5:$F$200,"Brand page")>0,"Y",IF(COUNTIFS('QC listings'!$A$5:$A$200,$M22,'QC listings'!$C$5:$C$200,O$4)>0,"?","–"))) | P22: =IF($M22="","",IF(COUNTIFS('QC listings'!$A$5:$A$200,$M22,'QC listings'!$C$5:$C$200,P$4,'QC listings'!$F$5:$F$200,"Listing page")+COUNTIFS('QC listings'!$A$5:$A$200,$M22,'QC listings'!$C$5:$C$200,P$4,'QC listings'!$F$5:$F$200,"Brand page")>0,"Y",IF(COUNTIFS('QC listings'!$A$5:$A$200,$M22,'QC listings'!$C$5:$C$200,P$4)>0,"?","–"))) | Q22: =IF($M22="","",IF(COUNTIFS('QC listings'!$A$5:$A$200,$M22,'QC listings'!$C$5:$C$200,Q$4,'QC listings'!$F$5:$F$200,"Listing page")+COUNTIFS('QC listings'!$A$5:$A$200,$M22,'QC listings'!$C$5:$C$200,Q$4,'QC listings'!$F$5:$F$200,"Brand page")>0,"Y",IF(COUNTIFS('QC listings'!$A$5:$A$200,$M22,'QC listings'!$C$5:$C$200,Q$4)>0,"?","–"))) | R22: =IF($M22="","",IF(COUNTIFS('QC listings'!$A$5:$A$200,$M22,'QC listings'!$C$5:$C$200,R$4,'QC listings'!$F$5:$F$200,"Listing page")+COUNTIFS('QC listings'!$A$5:$A$200,$M22,'QC listings'!$C$5:$C$200,R$4,'QC listings'!$F$5:$F$200,"Brand page")>0,"Y",IF(COUNTIFS('QC listings'!$A$5:$A$200,$M22,'QC listings'!$C$5:$C$200,R$4)>0,"?","–"))) | S22: =IF($M22="","",COUNTIF(O22:R22,"Y")) | T22: =IF($M22="","",SUMPRODUCT(MAX(('QC listings'!$A$5:$A$200=$M22)*'QC listings'!$E$5:$E$200))) | U22: =IF($M22="","",IF(T22>=Scoring!$B$11,3,IF(T22>=Scoring!$B$10,2,IF(T22>=Scoring!$B$9,1,0)))) | V22: =IFERROR(INDEX(Scoring!$B$27:$B$56,MATCH($E22,Scoring!$A$27:$A$56,0)),0) -> 1 | W22: =IF($G22="","",ROUND((Scoring!$B$5-$G22)/30.4375,1)) -> 20.5 | X22: =IF($F22="Expired",Scoring!$B$18,IF($G22="",Scoring!$B$17,IF(W22<=Scoring!$B$12,Scoring!$B$13,IF(W22<=Scoring!$B$14,Scoring!$B$15,Scoring!$B$16)))) -> 1 | Y22: =IF($M22="","",ROUND((S22*Scoring!$B$6+U22*Scoring!$B$7)*IFERROR(INDEX(Scoring!$B$22:$B$24,MATCH($N22,Scoring!$A$22:$A$24,0)),1)+V22*Scoring!$B$8+X22,2)) | Z22: =IF($M22="","",IF(SUMPRODUCT(($M$5:$M$249=$M22)*($G$5:$G$249>$G22))>0,0,IF(SUMPRODUCT(($M$5:$M$249=$M22)*($G$5:$G$249=$G22)*(ROW($M$5:$M$249)<ROW($M22)))>0,0,1))) | AA22: =IF($Z22=1,RANK($AE22,$AE$5:$AE$249,0),"") | AB22: Open | AC22: Link out; licence needed to display; run the PRD publication gate first (negative verdict) | AD22: Check the date: the published date (Jan 2025) looks earlier than the batch code implies | AE22: =IF($Z22=1,$Y22+$T22/1000000000-ROW()/10000000,"")
A23: R019 | B23: Noto | C23: Ice cream Dark Chocolate | D23: Everyday food | E23: Ice cream | F23: Failed | G23: 45674 | H23: N15042609 | I23: Eurofins | J23: Trustified Pass/Fail | L23: https://www.trustified.in/passandfail/notoicecream | O23: =IF($M23="","",IF(COUNTIFS('QC listings'!$A$5:$A$200,$M23,'QC listings'!$C$5:$C$200,O$4,'QC listings'!$F$5:$F$200,"Listing page")+COUNTIFS('QC listings'!$A$5:$A$200,$M23,'QC listings'!$C$5:$C$200,O$4,'QC listings'!$F$5:$F$200,"Brand page")>0,"Y",IF(COUNTIFS('QC listings'!$A$5:$A$200,$M23,'QC listings'!$C$5:$C$200,O$4)>0,"?","–"))) | P23: =IF($M23="","",IF(COUNTIFS('QC listings'!$A$5:$A$200,$M23,'QC listings'!$C$5:$C$200,P$4,'QC listings'!$F$5:$F$200,"Listing page")+COUNTIFS('QC listings'!$A$5:$A$200,$M23,'QC listings'!$C$5:$C$200,P$4,'QC listings'!$F$5:$F$200,"Brand page")>0,"Y",IF(COUNTIFS('QC listings'!$A$5:$A$200,$M23,'QC listings'!$C$5:$C$200,P$4)>0,"?","–"))) | Q23: =IF($M23="","",IF(COUNTIFS('QC listings'!$A$5:$A$200,$M23,'QC listings'!$C$5:$C$200,Q$4,'QC listings'!$F$5:$F$200,"Listing page")+COUNTIFS('QC listings'!$A$5:$A$200,$M23,'QC listings'!$C$5:$C$200,Q$4,'QC listings'!$F$5:$F$200,"Brand page")>0,"Y",IF(COUNTIFS('QC listings'!$A$5:$A$200,$M23,'QC listings'!$C$5:$C$200,Q$4)>0,"?","–"))) | R23: =IF($M23="","",IF(COUNTIFS('QC listings'!$A$5:$A$200,$M23,'QC listings'!$C$5:$C$200,R$4,'QC listings'!$F$5:$F$200,"Listing page")+COUNTIFS('QC listings'!$A$5:$A$200,$M23,'QC listings'!$C$5:$C$200,R$4,'QC listings'!$F$5:$F$200,"Brand page")>0,"Y",IF(COUNTIFS('QC listings'!$A$5:$A$200,$M23,'QC listings'!$C$5:$C$200,R$4)>0,"?","–"))) | S23: =IF($M23="","",COUNTIF(O23:R23,"Y")) | T23: =IF($M23="","",SUMPRODUCT(MAX(('QC listings'!$A$5:$A$200=$M23)*'QC listings'!$E$5:$E$200))) | U23: =IF($M23="","",IF(T23>=Scoring!$B$11,3,IF(T23>=Scoring!$B$10,2,IF(T23>=Scoring!$B$9,1,0)))) | V23: =IFERROR(INDEX(Scoring!$B$27:$B$56,MATCH($E23,Scoring!$A$27:$A$56,0)),0) -> 1 | W23: =IF($G23="","",ROUND((Scoring!$B$5-$G23)/30.4375,1)) -> 20.5 | X23: =IF($F23="Expired",Scoring!$B$18,IF($G23="",Scoring!$B$17,IF(W23<=Scoring!$B$12,Scoring!$B$13,IF(W23<=Scoring!$B$14,Scoring!$B$15,Scoring!$B$16)))) -> 1 | Y23: =IF($M23="","",ROUND((S23*Scoring!$B$6+U23*Scoring!$B$7)*IFERROR(INDEX(Scoring!$B$22:$B$24,MATCH($N23,Scoring!$A$22:$A$24,0)),1)+V23*Scoring!$B$8+X23,2)) | Z23: =IF($M23="","",IF(SUMPRODUCT(($M$5:$M$249=$M23)*($G$5:$G$249>$G23))>0,0,IF(SUMPRODUCT(($M$5:$M$249=$M23)*($G$5:$G$249=$G23)*(ROW($M$5:$M$249)<ROW($M23)))>0,0,1))) | AA23: =IF($Z23=1,RANK($AE23,$AE$5:$AE$249,0),"") | AB23: Open | AC23: Link out; licence needed to display; run the PRD publication gate first (negative verdict) | AD23: Check the date: the published date (Jan 2025) looks earlier than the batch code implies | AE23: =IF($Z23=1,$Y23+$T23/1000000000-ROW()/10000000,"")
A24: R020 | B24: Amul | C24: Butter | D24: Everyday food | E24: Butter, paneer & cheese | F24: Passed | G24: 45746 | H24: SAN3211 | I24: Eurofins | J24: Trustified Pass/Fail | L24: https://www.trustified.in/passandfail/amulbutter | M24: AMUL-BUTTER | N24: Exact | O24: =IF($M24="","",IF(COUNTIFS('QC listings'!$A$5:$A$200,$M24,'QC listings'!$C$5:$C$200,O$4,'QC listings'!$F$5:$F$200,"Listing page")+COUNTIFS('QC listings'!$A$5:$A$200,$M24,'QC listings'!$C$5:$C$200,O$4,'QC listings'!$F$5:$F$200,"Brand page")>0,"Y",IF(COUNTIFS('QC listings'!$A$5:$A$200,$M24,'QC listings'!$C$5:$C$200,O$4)>0,"?","–"))) -> Y | P24: =IF($M24="","",IF(COUNTIFS('QC listings'!$A$5:$A$200,$M24,'QC listings'!$C$5:$C$200,P$4,'QC listings'!$F$5:$F$200,"Listing page")+COUNTIFS('QC listings'!$A$5:$A$200,$M24,'QC listings'!$C$5:$C$200,P$4,'QC listings'!$F$5:$F$200,"Brand page")>0,"Y",IF(COUNTIFS('QC listings'!$A$5:$A$200,$M24,'QC listings'!$C$5:$C$200,P$4)>0,"?","–"))) -> Y | Q24: =IF($M24="","",IF(COUNTIFS('QC listings'!$A$5:$A$200,$M24,'QC listings'!$C$5:$C$200,Q$4,'QC listings'!$F$5:$F$200,"Listing page")+COUNTIFS('QC listings'!$A$5:$A$200,$M24,'QC listings'!$C$5:$C$200,Q$4,'QC listings'!$F$5:$F$200,"Brand page")>0,"Y",IF(COUNTIFS('QC listings'!$A$5:$A$200,$M24,'QC listings'!$C$5:$C$200,Q$4)>0,"?","–"))) -> ? | R24: =IF($M24="","",IF(COUNTIFS('QC listings'!$A$5:$A$200,$M24,'QC listings'!$C$5:$C$200,R$4,'QC listings'!$F$5:$F$200,"Listing page")+COUNTIFS('QC listings'!$A$5:$A$200,$M24,'QC listings'!$C$5:$C$200,R$4,'QC listings'!$F$5:$F$200,"Brand page")>0,"Y",IF(COUNTIFS('QC listings'!$A$5:$A$200,$M24,'QC listings'!$C$5:$C$200,R$4)>0,"?","–"))) -> – | S24: =IF($M24="","",COUNTIF(O24:R24,"Y")) -> 2 | T24: =IF($M24="","",SUMPRODUCT(MAX(('QC listings'!$A$5:$A$200=$M24)*'QC listings'!$E$5:$E$200))) -> 144000 | U24: =IF($M24="","",IF(T24>=Scoring!$B$11,3,IF(T24>=Scoring!$B$10,2,IF(T24>=Scoring!$B$9,1,0)))) -> 3 | V24: =IFERROR(INDEX(Scoring!$B$27:$B$56,MATCH($E24,Scoring!$A$27:$A$56,0)),0) -> 0 | W24: =IF($G24="","",ROUND((Scoring!$B$5-$G24)/30.4375,1)) -> 18.1 | X24: =IF($F24="Expired",Scoring!$B$18,IF($G24="",Scoring!$B$17,IF(W24<=Scoring!$B$12,Scoring!$B$13,IF(W24<=Scoring!$B$14,Scoring!$B$15,Scoring!$B$16)))) -> 1 | Y24: =IF($M24="","",ROUND((S24*Scoring!$B$6+U24*Scoring!$B$7)*IFERROR(INDEX(Scoring!$B$22:$B$24,MATCH($N24,Scoring!$A$22:$A$24,0)),1)+V24*Scoring!$B$8+X24,2)) -> 9 | Z24: =IF($M24="","",IF(SUMPRODUCT(($M$5:$M$249=$M24)*($G$5:$G$249>$G24))>0,0,IF(SUMPRODUCT(($M$5:$M$249=$M24)*($G$5:$G$249=$G24)*(ROW($M$5:$M$249)<ROW($M24)))>0,0,1))) -> 1 | AA24: =IF($Z24=1,RANK($AE24,$AE$5:$AE$249,0),"") -> 11 | AB24: Open | AC24: Link out; Trustified's written licence needed to display the report | AD24: QC: Instamart evidence is a third-party page dated 19 Jun 2026, so flagged '?'. afaqs reported a 500 g shortage in Surat/Gujarat; fake-butter claims unverified. | AE24: =IF($Z24=1,$Y24+$T24/1000000000-ROW()/10000000,"") -> 9.0001416
A25: R021 | B25: Amul | C25: Cheese Cubes | D25: Everyday food | E25: Butter, paneer & cheese | F25: Passed | G25: 45790 | H25: BAN3662,BAN2712 | I25: Eurofins | J25: Trustified Pass/Fail | L25: https://www.trustified.in/passandfail/amulcheesecubes | O25: =IF($M25="","",IF(COUNTIFS('QC listings'!$A$5:$A$200,$M25,'QC listings'!$C$5:$C$200,O$4,'QC listings'!$F$5:$F$200,"Listing page")+COUNTIFS('QC listings'!$A$5:$A$200,$M25,'QC listings'!$C$5:$C$200,O$4,'QC listings'!$F$5:$F$200,"Brand page")>0,"Y",IF(COUNTIFS('QC listings'!$A$5:$A$200,$M25,'QC listings'!$C$5:$C$200,O$4)>0,"?","–"))) | P25: =IF($M25="","",IF(COUNTIFS('QC listings'!$A$5:$A$200,$M25,'QC listings'!$C$5:$C$200,P$4,'QC listings'!$F$5:$F$200,"Listing page")+COUNTIFS('QC listings'!$A$5:$A$200,$M25,'QC listings'!$C$5:$C$200,P$4,'QC listings'!$F$5:$F$200,"Brand page")>0,"Y",IF(COUNTIFS('QC listings'!$A$5:$A$200,$M25,'QC listings'!$C$5:$C$200,P$4)>0,"?","–"))) | Q25: =IF($M25="","",IF(COUNTIFS('QC listings'!$A$5:$A$200,$M25,'QC listings'!$C$5:$C$200,Q$4,'QC listings'!$F$5:$F$200,"Listing page")+COUNTIFS('QC listings'!$A$5:$A$200,$M25,'QC listings'!$C$5:$C$200,Q$4,'QC listings'!$F$5:$F$200,"Brand page")>0,"Y",IF(COUNTIFS('QC listings'!$A$5:$A$200,$M25,'QC listings'!$C$5:$C$200,Q$4)>0,"?","–"))) | R25: =IF($M25="","",IF(COUNTIFS('QC listings'!$A$5:$A$200,$M25,'QC listings'!$C$5:$C$200,R$4,'QC listings'!$F$5:$F$200,"Listing page")+COUNTIFS('QC listings'!$A$5:$A$200,$M25,'QC listings'!$C$5:$C$200,R$4,'QC listings'!$F$5:$F$200,"Brand page")>0,"Y",IF(COUNTIFS('QC listings'!$A$5:$A$200,$M25,'QC listings'!$C$5:$C$200,R$4)>0,"?","–"))) | S25: =IF($M25="","",COUNTIF(O25:R25,"Y")) | T25: =IF($M25="","",SUMPRODUCT(MAX(('QC listings'!$A$5:$A$200=$M25)*'QC listings'!$E$5:$E$200))) | U25: =IF($M25="","",IF(T25>=Scoring!$B$11,3,IF(T25>=Scoring!$B$10,2,IF(T25>=Scoring!$B$9,1,0)))) | V25: =IFERROR(INDEX(Scoring!$B$27:$B$56,MATCH($E25,Scoring!$A$27:$A$56,0)),0) -> 0 | W25: =IF($G25="","",ROUND((Scoring!$B$5-$G25)/30.4375,1)) -> 16.7 | X25: =IF($F25="Expired",Scoring!$B$18,IF($G25="",Scoring!$B$17,IF(W25<=Scoring!$B$12,Scoring!$B$13,IF(W25<=Scoring!$B$14,Scoring!$B$15,Scoring!$B$16)))) -> 1 | Y25: =IF($M25="","",ROUND((S25*Scoring!$B$6+U25*Scoring!$B$7)*IFERROR(INDEX(Scoring!$B$22:$B$24,MATCH($N25,Scoring!$A$22:$A$24,0)),1)+V25*Scoring!$B$8+X25,2)) | Z25: =IF($M25="","",IF(SUMPRODUCT(($M$5:$M$249=$M25)*($G$5:$G$249>$G25))>0,0,IF(SUMPRODUCT(($M$5:$M$249=$M25)*($G$5:$G$249=$G25)*(ROW($M$5:$M$249)<ROW($M25)))>0,0,1))) | AA25: =IF($Z25=1,RANK($AE25,$AE$5:$AE$249,0),"") | AB25: Open | AC25: Link out; Trustified's written licence needed to display the report | AE25: =IF($Z25=1,$Y25+$T25/1000000000-ROW()/10000000,"")
A26: R022 | B26: Amul | C26: Paneer | D26: Everyday food | E26: Butter, paneer & cheese | F26: Passed | G26: 45713 | H26: MPC 018A | I26: Eurofins | J26: Trustified Pass/Fail | L26: https://www.trustified.in/passandfail/amulpaneer | M26: AMUL-PANEER | N26: Same line | O26: =IF($M26="","",IF(COUNTIFS('QC listings'!$A$5:$A$200,$M26,'QC listings'!$C$5:$C$200,O$4,'QC listings'!$F$5:$F$200,"Listing page")+COUNTIFS('QC listings'!$A$5:$A$200,$M26,'QC listings'!$C$5:$C$200,O$4,'QC listings'!$F$5:$F$200,"Brand page")>0,"Y",IF(COUNTIFS('QC listings'!$A$5:$A$200,$M26,'QC listings'!$C$5:$C$200,O$4)>0,"?","–"))) -> Y | P26: =IF($M26="","",IF(COUNTIFS('QC listings'!$A$5:$A$200,$M26,'QC listings'!$C$5:$C$200,P$4,'QC listings'!$F$5:$F$200,"Listing page")+COUNTIFS('QC listings'!$A$5:$A$200,$M26,'QC listings'!$C$5:$C$200,P$4,'QC listings'!$F$5:$F$200,"Brand page")>0,"Y",IF(COUNTIFS('QC listings'!$A$5:$A$200,$M26,'QC listings'!$C$5:$C$200,P$4)>0,"?","–"))) -> Y | Q26: =IF($M26="","",IF(COUNTIFS('QC listings'!$A$5:$A$200,$M26,'QC listings'!$C$5:$C$200,Q$4,'QC listings'!$F$5:$F$200,"Listing page")+COUNTIFS('QC listings'!$A$5:$A$200,$M26,'QC listings'!$C$5:$C$200,Q$4,'QC listings'!$F$5:$F$200,"Brand page")>0,"Y",IF(COUNTIFS('QC listings'!$A$5:$A$200,$M26,'QC listings'!$C$5:$C$200,Q$4)>0,"?","–"))) -> – | R26: =IF($M26="","",IF(COUNTIFS('QC listings'!$A$5:$A$200,$M26,'QC listings'!$C$5:$C$200,R$4,'QC listings'!$F$5:$F$200,"Listing page")+COUNTIFS('QC listings'!$A$5:$A$200,$M26,'QC listings'!$C$5:$C$200,R$4,'QC listings'!$F$5:$F$200,"Brand page")>0,"Y",IF(COUNTIFS('QC listings'!$A$5:$A$200,$M26,'QC listings'!$C$5:$C$200,R$4)>0,"?","–"))) -> Y | S26: =IF($M26="","",COUNTIF(O26:R26,"Y")) -> 3 | T26: =IF($M26="","",SUMPRODUCT(MAX(('QC listings'!$A$5:$A$200=$M26)*'QC listings'!$E$5:$E$200))) -> 397166 | U26: =IF($M26="","",IF(T26>=Scoring!$B$11,3,IF(T26>=Scoring!$B$10,2,IF(T26>=Scoring!$B$9,1,0)))) -> 3 | V26: =IFERROR(INDEX(Scoring!$B$27:$B$56,MATCH($E26,Scoring!$A$27:$A$56,0)),0) -> 0 | W26: =IF($G26="","",ROUND((Scoring!$B$5-$G26)/30.4375,1)) -> 19.2 | X26: =IF($F26="Expired",Scoring!$B$18,IF($G26="",Scoring!$B$17,IF(W26<=Scoring!$B$12,Scoring!$B$13,IF(W26<=Scoring!$B$14,Scoring!$B$15,Scoring!$B$16)))) -> 1 | Y26: =IF($M26="","",ROUND((S26*Scoring!$B$6+U26*Scoring!$B$7)*IFERROR(INDEX(Scoring!$B$22:$B$24,MATCH($N26,Scoring!$A$22:$A$24,0)),1)+V26*Scoring!$B$8+X26,2)) -> 7.75 | Z26: =IF($M26="","",IF(SUMPRODUCT(($M$5:$M$249=$M26)*($G$5:$G$249>$G26))>0,0,IF(SUMPRODUCT(($M$5:$M$249=$M26)*($G$5:$G$249=$G26)*(ROW($M$5:$M$249)<ROW($M26)))>0,0,1))) -> 1 | AA26: =IF($Z26=1,RANK($AE26,$AE$5:$AE$249,0),"") -> 16 | AB26: Open | AC26: Link out; Trustified's written licence needed to display the report | AD26: QC: Instamart listing not seen in my checks. | AE26: =IF($Z26=1,$Y26+$T26/1000000000-ROW()/10000000,"") -> 7.7503946
A27: R023 | B27: Aashirvaad | C27: Organic Cow Ghee | D27: Everyday food | E27: Ghee | F27: Listed, rating not captured | I27: NABL labs (up to 3 per sample) | J27: Unbox Health | L27: https://www.unboxhealth.in/explore/product/ceb7eace-c8ba-49e5-a2cd-0dd8d881f5df | M27: AASHIRVAAD-GHEE | N27: Variant differs | O27: =IF($M27="","",IF(COUNTIFS('QC listings'!$A$5:$A$200,$M27,'QC listings'!$C$5:$C$200,O$4,'QC listings'!$F$5:$F$200,"Listing page")+COUNTIFS('QC listings'!$A$5:$A$200,$M27,'QC listings'!$C$5:$C$200,O$4,'QC listings'!$F$5:$F$200,"Brand page")>0,"Y",IF(COUNTIFS('QC listings'!$A$5:$A$200,$M27,'QC listings'!$C$5:$C$200,O$4)>0,"?","–"))) -> – | P27: =IF($M27="","",IF(COUNTIFS('QC listings'!$A$5:$A$200,$M27,'QC listings'!$C$5:$C$200,P$4,'QC listings'!$F$5:$F$200,"Listing page")+COUNTIFS('QC listings'!$A$5:$A$200,$M27,'QC listings'!$C$5:$C$200,P$4,'QC listings'!$F$5:$F$200,"Brand page")>0,"Y",IF(COUNTIFS('QC listings'!$A$5:$A$200,$M27,'QC listings'!$C$5:$C$200,P$4)>0,"?","–"))) -> Y | Q27: =IF($M27="","",IF(COUNTIFS('QC listings'!$A$5:$A$200,$M27,'QC listings'!$C$5:$C$200,Q$4,'QC listings'!$F$5:$F$200,"Listing page")+COUNTIFS('QC listings'!$A$5:$A$200,$M27,'QC listings'!$C$5:$C$200,Q$4,'QC listings'!$F$5:$F$200,"Brand page")>0,"Y",IF(COUNTIFS('QC listings'!$A$5:$A$200,$M27,'QC listings'!$C$5:$C$200,Q$4)>0,"?","–"))) -> Y | R27: =IF($M27="","",IF(COUNTIFS('QC listings'!$A$5:$A$200,$M27,'QC listings'!$C$5:$C$200,R$4,'QC listings'!$F$5:$F$200,"Listing page")+COUNTIFS('QC listings'!$A$5:$A$200,$M27,'QC listings'!$C$5:$C$200,R$4,'QC listings'!$F$5:$F$200,"Brand page")>0,"Y",IF(COUNTIFS('QC listings'!$A$5:$A$200,$M27,'QC listings'!$C$5:$C$200,R$4)>0,"?","–"))) -> Y | S27: =IF($M27="","",COUNTIF(O27:R27,"Y")) -> 3 | T27: =IF($M27="","",SUMPRODUCT(MAX(('QC listings'!$A$5:$A$200=$M27)*'QC listings'!$E$5:$E$200))) -> 5008 | U27: =IF($M27="","",IF(T27>=Scoring!$B$11,3,IF(T27>=Scoring!$B$10,2,IF(T27>=Scoring!$B$9,1,0)))) -> 1 | V27: =IFERROR(INDEX(Scoring!$B$27:$B$56,MATCH($E27,Scoring!$A$27:$A$56,0)),0) -> 0 | W27: =IF($G27="","",ROUND((Scoring!$B$5-$G27)/30.4375,1)) | X27: =IF($F27="Expired",Scoring!$B$18,IF($G27="",Scoring!$B$17,IF(W27<=Scoring!$B$12,Scoring!$B$13,IF(W27<=Scoring!$B$14,Scoring!$B$15,Scoring!$B$16)))) -> 1 | Y27: =IF($M27="","",ROUND((S27*Scoring!$B$6+U27*Scoring!$B$7)*IFERROR(INDEX(Scoring!$B$22:$B$24,MATCH($N27,Scoring!$A$22:$A$24,0)),1)+V27*Scoring!$B$8+X27,2)) -> 3.5 | Z27: =IF($M27="","",IF(SUMPRODUCT(($M$5:$M$249=$M27)*($G$5:$G$249>$G27))>0,0,IF(SUMPRODUCT(($M$5:$M$249=$M27)*($G$5:$G$249=$G27)*(ROW($M$5:$M$249)<ROW($M27)))>0,0,1))) -> 0 | AA27: =IF($Z27=1,RANK($AE27,$AE$5:$AE$249,0),"") | AB27: Free login for full report | AC27: Competitor rating: link out only; full report needs a free login | AD27: QC: Listings are Svasti and Select cow ghee; Blinkit not seen. | AE27: =IF($Z27=1,$Y27+$T27/1000000000-ROW()/10000000,"")
A28: R024 | B28: Aashirvaad | C28: Svasti Pure Cow Ghee | D28: Everyday food | E28: Ghee | F28: Failed | G28: 45859 | H28: KCGA14ECP | I28: Eurofins | J28: Trustified Pass/Fail | L28: https://www.trustified.in/passandfail/ashirvaadghee | M28: AASHIRVAAD-GHEE | N28: Same line | O28: =IF($M28="","",IF(COUNTIFS('QC listings'!$A$5:$A$200,$M28,'QC listings'!$C$5:$C$200,O$4,'QC listings'!$F$5:$F$200,"Listing page")+COUNTIFS('QC listings'!$A$5:$A$200,$M28,'QC listings'!$C$5:$C$200,O$4,'QC listings'!$F$5:$F$200,"Brand page")>0,"Y",IF(COUNTIFS('QC listings'!$A$5:$A$200,$M28,'QC listings'!$C$5:$C$200,O$4)>0,"?","–"))) -> – | P28: =IF($M28="","",IF(COUNTIFS('QC listings'!$A$5:$A$200,$M28,'QC listings'!$C$5:$C$200,P$4,'QC listings'!$F$5:$F$200,"Listing page")+COUNTIFS('QC listings'!$A$5:$A$200,$M28,'QC listings'!$C$5:$C$200,P$4,'QC listings'!$F$5:$F$200,"Brand page")>0,"Y",IF(COUNTIFS('QC listings'!$A$5:$A$200,$M28,'QC listings'!$C$5:$C$200,P$4)>0,"?","–"))) -> Y | Q28: =IF($M28="","",IF(COUNTIFS('QC listings'!$A$5:$A$200,$M28,'QC listings'!$C$5:$C$200,Q$4,'QC listings'!$F$5:$F$200,"Listing page")+COUNTIFS('QC listings'!$A$5:$A$200,$M28,'QC listings'!$C$5:$C$200,Q$4,'QC listings'!$F$5:$F$200,"Brand page")>0,"Y",IF(COUNTIFS('QC listings'!$A$5:$A$200,$M28,'QC listings'!$C$5:$C$200,Q$4)>0,"?","–"))) -> Y | R28: =IF($M28="","",IF(COUNTIFS('QC listings'!$A$5:$A$200,$M28,'QC listings'!$C$5:$C$200,R$4,'QC listings'!$F$5:$F$200,"Listing page")+COUNTIFS('QC listings'!$A$5:$A$200,$M28,'QC listings'!$C$5:$C$200,R$4,'QC listings'!$F$5:$F$200,"Brand page")>0,"Y",IF(COUNTIFS('QC listings'!$A$5:$A$200,$M28,'QC listings'!$C$5:$C$200,R$4)>0,"?","–"))) -> Y | S28: =IF($M28="","",COUNTIF(O28:R28,"Y")) -> 3 | T28: =IF($M28="","",SUMPRODUCT(MAX(('QC listings'!$A$5:$A$200=$M28)*'QC listings'!$E$5:$E$200))) -> 5008 | U28: =IF($M28="","",IF(T28>=Scoring!$B$11,3,IF(T28>=Scoring!$B$10,2,IF(T28>=Scoring!$B$9,1,0)))) -> 1 | V28: =IFERROR(INDEX(Scoring!$B$27:$B$56,MATCH($E28,Scoring!$A$27:$A$56,0)),0) -> 0 | W28: =IF($G28="","",ROUND((Scoring!$B$5-$G28)/30.4375,1)) -> 14.4 | X28: =IF($F28="Expired",Scoring!$B$18,IF($G28="",Scoring!$B$17,IF(W28<=Scoring!$B$12,Scoring!$B$13,IF(W28<=Scoring!$B$14,Scoring!$B$15,Scoring!$B$16)))) -> 1 | Y28: =IF($M28="","",ROUND((S28*Scoring!$B$6+U28*Scoring!$B$7)*IFERROR(INDEX(Scoring!$B$22:$B$24,MATCH($N28,Scoring!$A$22:$A$24,0)),1)+V28*Scoring!$B$8+X28,2)) -> 4.75 | Z28: =IF($M28="","",IF(SUMPRODUCT(($M$5:$M$249=$M28)*($G$5:$G$249>$G28))>0,0,IF(SUMPRODUCT(($M$5:$M$249=$M28)*($G$5:$G$249=$G28)*(ROW($M$5:$M$249)<ROW($M28)))>0,0,1))) -> 1 | AA28: =IF($Z28=1,RANK($AE28,$AE$5:$AE$249,0),"") -> 24 | AB28: Open | AC28: Link out; licence needed to display; run the PRD publication gate first (negative verdict) | AD28: QC: Listings are Svasti and Select cow ghee; Blinkit not seen. | AE28: =IF($Z28=1,$Y28+$T28/1000000000-ROW()/10000000,"") -> 4.7500022
A29: R025 | B29: Amul | C29: Cow Ghee | D29: Everyday food | E29: Ghee | F29: Failed | G29: 45669 | H29: MVN2722A | I29: Eurofins | J29: Trustified Pass/Fail | L29: https://www.trustified.in/passandfail/amulghee | M29: AMUL-GHEE | N29: Same line | O29: =IF($M29="","",IF(COUNTIFS('QC listings'!$A$5:$A$200,$M29,'QC listings'!$C$5:$C$200,O$4,'QC listings'!$F$5:$F$200,"Listing page")+COUNTIFS('QC listings'!$A$5:$A$200,$M29,'QC listings'!$C$5:$C$200,O$4,'QC listings'!$F$5:$F$200,"Brand page")>0,"Y",IF(COUNTIFS('QC listings'!$A$5:$A$200,$M29,'QC listings'!$C$5:$C$200,O$4)>0,"?","–"))) -> – | P29: =IF($M29="","",IF(COUNTIFS('QC listings'!$A$5:$A$200,$M29,'QC listings'!$C$5:$C$200,P$4,'QC listings'!$F$5:$F$200,"Listing page")+COUNTIFS('QC listings'!$A$5:$A$200,$M29,'QC listings'!$C$5:$C$200,P$4,'QC listings'!$F$5:$F$200,"Brand page")>0,"Y",IF(COUNTIFS('QC listings'!$A$5:$A$200,$M29,'QC listings'!$C$5:$C$200,P$4)>0,"?","–"))) -> Y | Q29: =IF($M29="","",IF(COUNTIFS('QC listings'!$A$5:$A$200,$M29,'QC listings'!$C$5:$C$200,Q$4,'QC listings'!$F$5:$F$200,"Listing page")+COUNTIFS('QC listings'!$A$5:$A$200,$M29,'QC listings'!$C$5:$C$200,Q$4,'QC listings'!$F$5:$F$200,"Brand page")>0,"Y",IF(COUNTIFS('QC listings'!$A$5:$A$200,$M29,'QC listings'!$C$5:$C$200,Q$4)>0,"?","–"))) -> Y | R29: =IF($M29="","",IF(COUNTIFS('QC listings'!$A$5:$A$200,$M29,'QC listings'!$C$5:$C$200,R$4,'QC listings'!$F$5:$F$200,"Listing page")+COUNTIFS('QC listings'!$A$5:$A$200,$M29,'QC listings'!$C$5:$C$200,R$4,'QC listings'!$F$5:$F$200,"Brand page")>0,"Y",IF(COUNTIFS('QC listings'!$A$5:$A$200,$M29,'QC listings'!$C$5:$C$200,R$4)>0,"?","–"))) -> Y | S29: =IF($M29="","",COUNTIF(O29:R29,"Y")) -> 3 | T29: =IF($M29="","",SUMPRODUCT(MAX(('QC listings'!$A$5:$A$200=$M29)*'QC listings'!$E$5:$E$200))) -> 0 | U29: =IF($M29="","",IF(T29>=Scoring!$B$11,3,IF(T29>=Scoring!$B$10,2,IF(T29>=Scoring!$B$9,1,0)))) -> 0 | V29: =IFERROR(INDEX(Scoring!$B$27:$B$56,MATCH($E29,Scoring!$A$27:$A$56,0)),0) -> 0 | W29: =IF($G29="","",ROUND((Scoring!$B$5-$G29)/30.4375,1)) -> 20.6 | X29: =IF($F29="Expired",Scoring!$B$18,IF($G29="",Scoring!$B$17,IF(W29<=Scoring!$B$12,Scoring!$B$13,IF(W29<=Scoring!$B$14,Scoring!$B$15,Scoring!$B$16)))) -> 1 | Y29: =IF($M29="","",ROUND((S29*Scoring!$B$6+U29*Scoring!$B$7)*IFERROR(INDEX(Scoring!$B$22:$B$24,MATCH($N29,Scoring!$A$22:$A$24,0)),1)+V29*Scoring!$B$8+X29,2)) -> 3.25 | Z29: =IF($M29="","",IF(SUMPRODUCT(($M$5:$M$249=$M29)*($G$5:$G$249>$G29))>0,0,IF(SUMPRODUCT(($M$5:$M$249=$M29)*($G$5:$G$249=$G29)*(ROW($M$5:$M$249)<ROW($M29)))>0,0,1))) -> 1 | AA29: =IF($Z29=1,RANK($AE29,$AE$5:$AE$249,0),"") -> 28 | AB29: Open | AC29: Link out; licence needed to display; run the PRD publication gate first (negative verdict) | AD29: QC: Blinkit lists only Amul Pure Ghee (buffalo, prid/15520), not counted. | AE29: =IF($Z29=1,$Y29+$T29/1000000000-ROW()/10000000,"") -> 3.2499971
A30: R026 | B30: Amul | C30: High Aroma Cow Ghee | D30: Everyday food | E30: Ghee | F30: Listed, rating not captured | I30: NABL labs (up to 3 per sample) | J30: Unbox Health | L30: https://www.unboxhealth.in/explore/product/dc334a51-2a93-4257-be64-178a33956e2b | M30: AMUL-GHEE | N30: Same line | O30: =IF($M30="","",IF(COUNTIFS('QC listings'!$A$5:$A$200,$M30,'QC listings'!$C$5:$C$200,O$4,'QC listings'!$F$5:$F$200,"Listing page")+COUNTIFS('QC listings'!$A$5:$A$200,$M30,'QC listings'!$C$5:$C$200,O$4,'QC listings'!$F$5:$F$200,"Brand page")>0,"Y",IF(COUNTIFS('QC listings'!$A$5:$A$200,$M30,'QC listings'!$C$5:$C$200,O$4)>0,"?","–"))) -> – | P30: =IF($M30="","",IF(COUNTIFS('QC listings'!$A$5:$A$200,$M30,'QC listings'!$C$5:$C$200,P$4,'QC listings'!$F$5:$F$200,"Listing page")+COUNTIFS('QC listings'!$A$5:$A$200,$M30,'QC listings'!$C$5:$C$200,P$4,'QC listings'!$F$5:$F$200,"Brand page")>0,"Y",IF(COUNTIFS('QC listings'!$A$5:$A$200,$M30,'QC listings'!$C$5:$C$200,P$4)>0,"?","–"))) -> Y | Q30: =IF($M30="","",IF(COUNTIFS('QC listings'!$A$5:$A$200,$M30,'QC listings'!$C$5:$C$200,Q$4,'QC listings'!$F$5:$F$200,"Listing page")+COUNTIFS('QC listings'!$A$5:$A$200,$M30,'QC listings'!$C$5:$C$200,Q$4,'QC listings'!$F$5:$F$200,"Brand page")>0,"Y",IF(COUNTIFS('QC listings'!$A$5:$A$200,$M30,'QC listings'!$C$5:$C$200,Q$4)>0,"?","–"))) -> Y | R30: =IF($M30="","",IF(COUNTIFS('QC listings'!$A$5:$A$200,$M30,'QC listings'!$C$5:$C$200,R$4,'QC listings'!$F$5:$F$200,"Listing page")+COUNTIFS('QC listings'!$A$5:$A$200,$M30,'QC listings'!$C$5:$C$200,R$4,'QC listings'!$F$5:$F$200,"Brand page")>0,"Y",IF(COUNTIFS('QC listings'!$A$5:$A$200,$M30,'QC listings'!$C$5:$C$200,R$4)>0,"?","–"))) -> Y | S30: =IF($M30="","",COUNTIF(O30:R30,"Y")) -> 3 | T30: =IF($M30="","",SUMPRODUCT(MAX(('QC listings'!$A$5:$A$200=$M30)*'QC listings'!$E$5:$E$200))) -> 0 | U30: =IF($M30="","",IF(T30>=Scoring!$B$11,3,IF(T30>=Scoring!$B$10,2,IF(T30>=Scoring!$B$9,1,0)))) -> 0 | V30: =IFERROR(INDEX(Scoring!$B$27:$B$56,MATCH($E30,Scoring!$A$27:$A$56,0)),0) -> 0 | W30: =IF($G30="","",ROUND((Scoring!$B$5-$G30)/30.4375,1)) | X30: =IF($F30="Expired",Scoring!$B$18,IF($G30="",Scoring!$B$17,IF(W30<=Scoring!$B$12,Scoring!$B$13,IF(W30<=Scoring!$B$14,Scoring!$B$15,Scoring!$B$16)))) -> 1 | Y30: =IF($M30="","",ROUND((S30*Scoring!$B$6+U30*Scoring!$B$7)*IFERROR(INDEX(Scoring!$B$22:$B$24,MATCH($N30,Scoring!$A$22:$A$24,0)),1)+V30*Scoring!$B$8+X30,2)) -> 3.25 | Z30: =IF($M30="","",IF(SUMPRODUCT(($M$5:$M$249=$M30)*($G$5:$G$249>$G30))>0,0,IF(SUMPRODUCT(($M$5:$M$249=$M30)*($G$5:$G$249=$G30)*(ROW($M$5:$M$249)<ROW($M30)))>0,0,1))) -> 0 | AA30: =IF($Z30=1,RANK($AE30,$AE$5:$AE$249,0),"") | AB30: Free login for full report | AC30: Competitor rating: link out only; full report needs a free login | AD30: QC: Blinkit lists only Amul Pure Ghee (buffalo, prid/15520), not counted. | AE30: =IF($Z30=1,$Y30+$T30/1000000000-ROW()/10000000,"")
A31: R027 | B31: Country Delight | C31: Desi Cow Ghee | D31: Everyday food | E31: Ghee | F31: Listed, rating not captured | I31: NABL labs (up to 3 per sample) | J31: Unbox Health | L31: https://www.unboxhealth.in/explore/product/1b38aa3a-6707-49d8-b956-5c7c581a949f | O31: =IF($M31="","",IF(COUNTIFS('QC listings'!$A$5:$A$200,$M31,'QC listings'!$C$5:$C$200,O$4,'QC listings'!$F$5:$F$200,"Listing page")+COUNTIFS('QC listings'!$A$5:$A$200,$M31,'QC listings'!$C$5:$C$200,O$4,'QC listings'!$F$5:$F$200,"Brand page")>0,"Y",IF(COUNTIFS('QC listings'!$A$5:$A$200,$M31,'QC listings'!$C$5:$C$200,O$4)>0,"?","–"))) | P31: =IF($M31="","",IF(COUNTIFS('QC listings'!$A$5:$A$200,$M31,'QC listings'!$C$5:$C$200,P$4,'QC listings'!$F$5:$F$200,"Listing page")+COUNTIFS('QC listings'!$A$5:$A$200,$M31,'QC listings'!$C$5:$C$200,P$4,'QC listings'!$F$5:$F$200,"Brand page")>0,"Y",IF(COUNTIFS('QC listings'!$A$5:$A$200,$M31,'QC listings'!$C$5:$C$200,P$4)>0,"?","–"))) | Q31: =IF($M31="","",IF(COUNTIFS('QC listings'!$A$5:$A$200,$M31,'QC listings'!$C$5:$C$200,Q$4,'QC listings'!$F$5:$F$200,"Listing page")+COUNTIFS('QC listings'!$A$5:$A$200,$M31,'QC listings'!$C$5:$C$200,Q$4,'QC listings'!$F$5:$F$200,"Brand page")>0,"Y",IF(COUNTIFS('QC listings'!$A$5:$A$200,$M31,'QC listings'!$C$5:$C$200,Q$4)>0,"?","–"))) | R31: =IF($M31="","",IF(COUNTIFS('QC listings'!$A$5:$A$200,$M31,'QC listings'!$C$5:$C$200,R$4,'QC listings'!$F$5:$F$200,"Listing page")+COUNTIFS('QC listings'!$A$5:$A$200,$M31,'QC listings'!$C$5:$C$200,R$4,'QC listings'!$F$5:$F$200,"Brand page")>0,"Y",IF(COUNTIFS('QC listings'!$A$5:$A$200,$M31,'QC listings'!$C$5:$C$200,R$4)>0,"?","–"))) | S31: =IF($M31="","",COUNTIF(O31:R31,"Y")) | T31: =IF($M31="","",SUMPRODUCT(MAX(('QC listings'!$A$5:$A$200=$M31)*'QC listings'!$E$5:$E$200))) | U31: =IF($M31="","",IF(T31>=Scoring!$B$11,3,IF(T31>=Scoring!$B$10,2,IF(T31>=Scoring!$B$9,1,0)))) | V31: =IFERROR(INDEX(Scoring!$B$27:$B$56,MATCH($E31,Scoring!$A$27:$A$56,0)),0) -> 0 | W31: =IF($G31="","",ROUND((Scoring!$B$5-$G31)/30.4375,1)) | X31: =IF($F31="Expired",Scoring!$B$18,IF($G31="",Scoring!$B$17,IF(W31<=Scoring!$B$12,Scoring!$B$13,IF(W31<=Scoring!$B$14,Scoring!$B$15,Scoring!$B$16)))) -> 1 | Y31: =IF($M31="","",ROUND((S31*Scoring!$B$6+U31*Scoring!$B$7)*IFERROR(INDEX(Scoring!$B$22:$B$24,MATCH($N31,Scoring!$A$22:$A$24,0)),1)+V31*Scoring!$B$8+X31,2)) | Z31: =IF($M31="","",IF(SUMPRODUCT(($M$5:$M$249=$M31)*($G$5:$G$249>$G31))>0,0,IF(SUMPRODUCT(($M$5:$M$249=$M31)*($G$5:$G$249=$G31)*(ROW($M$5:$M$249)<ROW($M31)))>0,0,1))) | AA31: =IF($Z31=1,RANK($AE31,$AE$5:$AE$249,0),"") | AB31: Free login for full report | AC31: Competitor rating: link out only; full report needs a free login | AE31: =IF($Z31=1,$Y31+$T31/1000000000-ROW()/10000000,"")
A32: R028 | B32: Country Delight | C32: Desi Danedar Ghee | D32: Everyday food | E32: Ghee | F32: Failed | G32: 45767 | H32: DPDG039 | I32: Eurofins | J32: Trustified Pass/Fail | L32: https://www.trustified.in/passandfail/Countrydelightghee | O32: =IF($M32="","",IF(COUNTIFS('QC listings'!$A$5:$A$200,$M32,'QC listings'!$C$5:$C$200,O$4,'QC listings'!$F$5:$F$200,"Listing page")+COUNTIFS('QC listings'!$A$5:$A$200,$M32,'QC listings'!$C$5:$C$200,O$4,'QC listings'!$F$5:$F$200,"Brand page")>0,"Y",IF(COUNTIFS('QC listings'!$A$5:$A$200,$M32,'QC listings'!$C$5:$C$200,O$4)>0,"?","–"))) | P32: =IF($M32="","",IF(COUNTIFS('QC listings'!$A$5:$A$200,$M32,'QC listings'!$C$5:$C$200,P$4,'QC listings'!$F$5:$F$200,"Listing page")+COUNTIFS('QC listings'!$A$5:$A$200,$M32,'QC listings'!$C$5:$C$200,P$4,'QC listings'!$F$5:$F$200,"Brand page")>0,"Y",IF(COUNTIFS('QC listings'!$A$5:$A$200,$M32,'QC listings'!$C$5:$C$200,P$4)>0,"?","–"))) | Q32: =IF($M32="","",IF(COUNTIFS('QC listings'!$A$5:$A$200,$M32,'QC listings'!$C$5:$C$200,Q$4,'QC listings'!$F$5:$F$200,"Listing page")+COUNTIFS('QC listings'!$A$5:$A$200,$M32,'QC listings'!$C$5:$C$200,Q$4,'QC listings'!$F$5:$F$200,"Brand page")>0,"Y",IF(COUNTIFS('QC listings'!$A$5:$A$200,$M32,'QC listings'!$C$5:$C$200,Q$4)>0,"?","–"))) | R32: =IF($M32="","",IF(COUNTIFS('QC listings'!$A$5:$A$200,$M32,'QC listings'!$C$5:$C$200,R$4,'QC listings'!$F$5:$F$200,"Listing page")+COUNTIFS('QC listings'!$A$5:$A$200,$M32,'QC listings'!$C$5:$C$200,R$4,'QC listings'!$F$5:$F$200,"Brand page")>0,"Y",IF(COUNTIFS('QC listings'!$A$5:$A$200,$M32,'QC listings'!$C$5:$C$200,R$4)>0,"?","–"))) | S32: =IF($M32="","",COUNTIF(O32:R32,"Y")) | T32: =IF($M32="","",SUMPRODUCT(MAX(('QC listings'!$A$5:$A$200=$M32)*'QC listings'!$E$5:$E$200))) | U32: =IF($M32="","",IF(T32>=Scoring!$B$11,3,IF(T32>=Scoring!$B$10,2,IF(T32>=Scoring!$B$9,1,0)))) | V32: =IFERROR(INDEX(Scoring!$B$27:$B$56,MATCH($E32,Scoring!$A$27:$A$56,0)),0) -> 0 | W32: =IF($G32="","",ROUND((Scoring!$B$5-$G32)/30.4375,1)) -> 17.4 | X32: =IF($F32="Expired",Scoring!$B$18,IF($G32="",Scoring!$B$17,IF(W32<=Scoring!$B$12,Scoring!$B$13,IF(W32<=Scoring!$B$14,Scoring!$B$15,Scoring!$B$16)))) -> 1 | Y32: =IF($M32="","",ROUND((S32*Scoring!$B$6+U32*Scoring!$B$7)*IFERROR(INDEX(Scoring!$B$22:$B$24,MATCH($N32,Scoring!$A$22:$A$24,0)),1)+V32*Scoring!$B$8+X32,2)) | Z32: =IF($M32="","",IF(SUMPRODUCT(($M$5:$M$249=$M32)*($G$5:$G$249>$G32))>0,0,IF(SUMPRODUCT(($M$5:$M$249=$M32)*($G$5:$G$249=$G32)*(ROW($M$5:$M$249)<ROW($M32)))>0,0,1))) | AA32: =IF($Z32=1,RANK($AE32,$AE$5:$AE$249,0),"") | AB32: Open | AC32: Link out; licence needed to display; run the PRD publication gate first (negative verdict) | AE32: =IF($Z32=1,$Y32+$T32/1000000000-ROW()/10000000,"")
A33: R029 | B33: Organic India | C33: Cow Ghee (2024) | D33: Everyday food | E33: Ghee | F33: Listed, rating not captured | I33: NABL labs (up to 3 per sample) | J33: Unbox Health | L33: https://www.unboxhealth.in/explore/product/b89ecab2-2626-4946-9650-593f54970dd8 | O33: =IF($M33="","",IF(COUNTIFS('QC listings'!$A$5:$A$200,$M33,'QC listings'!$C$5:$C$200,O$4,'QC listings'!$F$5:$F$200,"Listing page")+COUNTIFS('QC listings'!$A$5:$A$200,$M33,'QC listings'!$C$5:$C$200,O$4,'QC listings'!$F$5:$F$200,"Brand page")>0,"Y",IF(COUNTIFS('QC listings'!$A$5:$A$200,$M33,'QC listings'!$C$5:$C$200,O$4)>0,"?","–"))) | P33: =IF($M33="","",IF(COUNTIFS('QC listings'!$A$5:$A$200,$M33,'QC listings'!$C$5:$C$200,P$4,'QC listings'!$F$5:$F$200,"Listing page")+COUNTIFS('QC listings'!$A$5:$A$200,$M33,'QC listings'!$C$5:$C$200,P$4,'QC listings'!$F$5:$F$200,"Brand page")>0,"Y",IF(COUNTIFS('QC listings'!$A$5:$A$200,$M33,'QC listings'!$C$5:$C$200,P$4)>0,"?","–"))) | Q33: =IF($M33="","",IF(COUNTIFS('QC listings'!$A$5:$A$200,$M33,'QC listings'!$C$5:$C$200,Q$4,'QC listings'!$F$5:$F$200,"Listing page")+COUNTIFS('QC listings'!$A$5:$A$200,$M33,'QC listings'!$C$5:$C$200,Q$4,'QC listings'!$F$5:$F$200,"Brand page")>0,"Y",IF(COUNTIFS('QC listings'!$A$5:$A$200,$M33,'QC listings'!$C$5:$C$200,Q$4)>0,"?","–"))) | R33: =IF($M33="","",IF(COUNTIFS('QC listings'!$A$5:$A$200,$M33,'QC listings'!$C$5:$C$200,R$4,'QC listings'!$F$5:$F$200,"Listing page")+COUNTIFS('QC listings'!$A$5:$A$200,$M33,'QC listings'!$C$5:$C$200,R$4,'QC listings'!$F$5:$F$200,"Brand page")>0,"Y",IF(COUNTIFS('QC listings'!$A$5:$A$200,$M33,'QC listings'!$C$5:$C$200,R$4)>0,"?","–"))) | S33: =IF($M33="","",COUNTIF(O33:R33,"Y")) | T33: =IF($M33="","",SUMPRODUCT(MAX(('QC listings'!$A$5:$A$200=$M33)*'QC listings'!$E$5:$E$200))) | U33: =IF($M33="","",IF(T33>=Scoring!$B$11,3,IF(T33>=Scoring!$B$10,2,IF(T33>=Scoring!$B$9,1,0)))) | V33: =IFERROR(INDEX(Scoring!$B$27:$B$56,MATCH($E33,Scoring!$A$27:$A$56,0)),0) -> 0 | W33: =IF($G33="","",ROUND((Scoring!$B$5-$G33)/30.4375,1)) | X33: =IF($F33="Expired",Scoring!$B$18,IF($G33="",Scoring!$B$17,IF(W33<=Scoring!$B$12,Scoring!$B$13,IF(W33<=Scoring!$B$14,Scoring!$B$15,Scoring!$B$16)))) -> 1 | Y33: =IF($M33="","",ROUND((S33*Scoring!$B$6+U33*Scoring!$B$7)*IFERROR(INDEX(Scoring!$B$22:$B$24,MATCH($N33,Scoring!$A$22:$A$24,0)),1)+V33*Scoring!$B$8+X33,2)) | Z33: =IF($M33="","",IF(SUMPRODUCT(($M$5:$M$249=$M33)*($G$5:$G$249>$G33))>0,0,IF(SUMPRODUCT(($M$5:$M$249=$M33)*($G$5:$G$249=$G33)*(ROW($M$5:$M$249)<ROW($M33)))>0,0,1))) | AA33: =IF($Z33=1,RANK($AE33,$AE$5:$AE$249,0),"") | AB33: Free login for full report | AC33: Competitor rating: link out only; full report needs a free login | AE33: =IF($Z33=1,$Y33+$T33/1000000000-ROW()/10000000,"")
A34: R030 | B34: Organic India | C34: Ghee | D34: Everyday food | E34: Ghee | F34: Listed, rating not captured | I34: NABL labs (up to 3 per sample) | J34: Unbox Health | L34: https://www.unboxhealth.in/explore/product/36f4c341-54a9-4b14-a77e-31c9bf7ceb1d | O34: =IF($M34="","",IF(COUNTIFS('QC listings'!$A$5:$A$200,$M34,'QC listings'!$C$5:$C$200,O$4,'QC listings'!$F$5:$F$200,"Listing page")+COUNTIFS('QC listings'!$A$5:$A$200,$M34,'QC listings'!$C$5:$C$200,O$4,'QC listings'!$F$5:$F$200,"Brand page")>0,"Y",IF(COUNTIFS('QC listings'!$A$5:$A$200,$M34,'QC listings'!$C$5:$C$200,O$4)>0,"?","–"))) | P34: =IF($M34="","",IF(COUNTIFS('QC listings'!$A$5:$A$200,$M34,'QC listings'!$C$5:$C$200,P$4,'QC listings'!$F$5:$F$200,"Listing page")+COUNTIFS('QC listings'!$A$5:$A$200,$M34,'QC listings'!$C$5:$C$200,P$4,'QC listings'!$F$5:$F$200,"Brand page")>0,"Y",IF(COUNTIFS('QC listings'!$A$5:$A$200,$M34,'QC listings'!$C$5:$C$200,P$4)>0,"?","–"))) | Q34: =IF($M34="","",IF(COUNTIFS('QC listings'!$A$5:$A$200,$M34,'QC listings'!$C$5:$C$200,Q$4,'QC listings'!$F$5:$F$200,"Listing page")+COUNTIFS('QC listings'!$A$5:$A$200,$M34,'QC listings'!$C$5:$C$200,Q$4,'QC listings'!$F$5:$F$200,"Brand page")>0,"Y",IF(COUNTIFS('QC listings'!$A$5:$A$200,$M34,'QC listings'!$C$5:$C$200,Q$4)>0,"?","–"))) | R34: =IF($M34="","",IF(COUNTIFS('QC listings'!$A$5:$A$200,$M34,'QC listings'!$C$5:$C$200,R$4,'QC listings'!$F$5:$F$200,"Listing page")+COUNTIFS('QC listings'!$A$5:$A$200,$M34,'QC listings'!$C$5:$C$200,R$4,'QC listings'!$F$5:$F$200,"Brand page")>0,"Y",IF(COUNTIFS('QC listings'!$A$5:$A$200,$M34,'QC listings'!$C$5:$C$200,R$4)>0,"?","–"))) | S34: =IF($M34="","",COUNTIF(O34:R34,"Y")) | T34: =IF($M34="","",SUMPRODUCT(MAX(('QC listings'!$A$5:$A$200=$M34)*'QC listings'!$E$5:$E$200))) | U34: =IF($M34="","",IF(T34>=Scoring!$B$11,3,IF(T34>=Scoring!$B$10,2,IF(T34>=Scoring!$B$9,1,0)))) | V34: =IFERROR(INDEX(Scoring!$B$27:$B$56,MATCH($E34,Scoring!$A$27:$A$56,0)),0) -> 0 | W34: =IF($G34="","",ROUND((Scoring!$B$5-$G34)/30.4375,1)) | X34: =IF($F34="Expired",Scoring!$B$18,IF($G34="",Scoring!$B$17,IF(W34<=Scoring!$B$12,Scoring!$B$13,IF(W34<=Scoring!$B$14,Scoring!$B$15,Scoring!$B$16)))) -> 1 | Y34: =IF($M34="","",ROUND((S34*Scoring!$B$6+U34*Scoring!$B$7)*IFERROR(INDEX(Scoring!$B$22:$B$24,MATCH($N34,Scoring!$A$22:$A$24,0)),1)+V34*Scoring!$B$8+X34,2)) | Z34: =IF($M34="","",IF(SUMPRODUCT(($M$5:$M$249=$M34)*($G$5:$G$249>$G34))>0,0,IF(SUMPRODUCT(($M$5:$M$249=$M34)*($G$5:$G$249=$G34)*(ROW($M$5:$M$249)<ROW($M34)))>0,0,1))) | AA34: =IF($Z34=1,RANK($AE34,$AE$5:$AE$249,0),"") | AB34: Free login for full report | AC34: Competitor rating: link out only; full report needs a free login | AE34: =IF($Z34=1,$Y34+$T34/1000000000-ROW()/10000000,"")
A35: R031 | B35: Patanjali | C35: Cow's Ghee | D35: Everyday food | E35: Ghee | F35: Failed | G35: 46005 | H35: NAWC250164 | I35: Eurofins | J35: Trustified Pass/Fail | L35: https://www.trustified.in/passandfail/patanjalighee | O35: =IF($M35="","",IF(COUNTIFS('QC listings'!$A$5:$A$200,$M35,'QC listings'!$C$5:$C$200,O$4,'QC listings'!$F$5:$F$200,"Listing page")+COUNTIFS('QC listings'!$A$5:$A$200,$M35,'QC listings'!$C$5:$C$200,O$4,'QC listings'!$F$5:$F$200,"Brand page")>0,"Y",IF(COUNTIFS('QC listings'!$A$5:$A$200,$M35,'QC listings'!$C$5:$C$200,O$4)>0,"?","–"))) | P35: =IF($M35="","",IF(COUNTIFS('QC listings'!$A$5:$A$200,$M35,'QC listings'!$C$5:$C$200,P$4,'QC listings'!$F$5:$F$200,"Listing page")+COUNTIFS('QC listings'!$A$5:$A$200,$M35,'QC listings'!$C$5:$C$200,P$4,'QC listings'!$F$5:$F$200,"Brand page")>0,"Y",IF(COUNTIFS('QC listings'!$A$5:$A$200,$M35,'QC listings'!$C$5:$C$200,P$4)>0,"?","–"))) | Q35: =IF($M35="","",IF(COUNTIFS('QC listings'!$A$5:$A$200,$M35,'QC listings'!$C$5:$C$200,Q$4,'QC listings'!$F$5:$F$200,"Listing page")+COUNTIFS('QC listings'!$A$5:$A$200,$M35,'QC listings'!$C$5:$C$200,Q$4,'QC listings'!$F$5:$F$200,"Brand page")>0,"Y",IF(COUNTIFS('QC listings'!$A$5:$A$200,$M35,'QC listings'!$C$5:$C$200,Q$4)>0,"?","–"))) | R35: =IF($M35="","",IF(COUNTIFS('QC listings'!$A$5:$A$200,$M35,'QC listings'!$C$5:$C$200,R$4,'QC listings'!$F$5:$F$200,"Listing page")+COUNTIFS('QC listings'!$A$5:$A$200,$M35,'QC listings'!$C$5:$C$200,R$4,'QC listings'!$F$5:$F$200,"Brand page")>0,"Y",IF(COUNTIFS('QC listings'!$A$5:$A$200,$M35,'QC listings'!$C$5:$C$200,R$4)>0,"?","–"))) | S35: =IF($M35="","",COUNTIF(O35:R35,"Y")) | T35: =IF($M35="","",SUMPRODUCT(MAX(('QC listings'!$A$5:$A$200=$M35)*'QC listings'!$E$5:$E$200))) | U35: =IF($M35="","",IF(T35>=Scoring!$B$11,3,IF(T35>=Scoring!$B$10,2,IF(T35>=Scoring!$B$9,1,0)))) | V35: =IFERROR(INDEX(Scoring!$B$27:$B$56,MATCH($E35,Scoring!$A$27:$A$56,0)),0) -> 0 | W35: =IF($G35="","",ROUND((Scoring!$B$5-$G35)/30.4375,1)) -> 9.6 | X35: =IF($F35="Expired",Scoring!$B$18,IF($G35="",Scoring!$B$17,IF(W35<=Scoring!$B$12,Scoring!$B$13,IF(W35<=Scoring!$B$14,Scoring!$B$15,Scoring!$B$16)))) -> 2 | Y35: =IF($M35="","",ROUND((S35*Scoring!$B$6+U35*Scoring!$B$7)*IFERROR(INDEX(Scoring!$B$22:$B$24,MATCH($N35,Scoring!$A$22:$A$24,0)),1)+V35*Scoring!$B$8+X35,2)) | Z35: =IF($M35="","",IF(SUMPRODUCT(($M$5:$M$249=$M35)*($G$5:$G$249>$G35))>0,0,IF(SUMPRODUCT(($M$5:$M$249=$M35)*($G$5:$G$249=$G35)*(ROW($M$5:$M$249)<ROW($M35)))>0,0,1))) | AA35: =IF($Z35=1,RANK($AE35,$AE$5:$AE$249,0),"") | AB35: Open | AC35: Link out; licence needed to display; run the PRD publication gate first (negative verdict) | AE35: =IF($Z35=1,$Y35+$T35/1000000000-ROW()/10000000,"")
A36: R032 | B36: Vedic | C36: A2 Gir Cow Ghee | D36: Everyday food | E36: Ghee | F36: Listed, rating not captured | I36: NABL labs (up to 3 per sample) | J36: Unbox Health | L36: https://www.unboxhealth.in/explore/product/f1e1a714-059f-4583-bef1-67bb8afafb00 | O36: =IF($M36="","",IF(COUNTIFS('QC listings'!$A$5:$A$200,$M36,'QC listings'!$C$5:$C$200,O$4,'QC listings'!$F$5:$F$200,"Listing page")+COUNTIFS('QC listings'!$A$5:$A$200,$M36,'QC listings'!$C$5:$C$200,O$4,'QC listings'!$F$5:$F$200,"Brand page")>0,"Y",IF(COUNTIFS('QC listings'!$A$5:$A$200,$M36,'QC listings'!$C$5:$C$200,O$4)>0,"?","–"))) | P36: =IF($M36="","",IF(COUNTIFS('QC listings'!$A$5:$A$200,$M36,'QC listings'!$C$5:$C$200,P$4,'QC listings'!$F$5:$F$200,"Listing page")+COUNTIFS('QC listings'!$A$5:$A$200,$M36,'QC listings'!$C$5:$C$200,P$4,'QC listings'!$F$5:$F$200,"Brand page")>0,"Y",IF(COUNTIFS('QC listings'!$A$5:$A$200,$M36,'QC listings'!$C$5:$C$200,P$4)>0,"?","–"))) | Q36: =IF($M36="","",IF(COUNTIFS('QC listings'!$A$5:$A$200,$M36,'QC listings'!$C$5:$C$200,Q$4,'QC listings'!$F$5:$F$200,"Listing page")+COUNTIFS('QC listings'!$A$5:$A$200,$M36,'QC listings'!$C$5:$C$200,Q$4,'QC listings'!$F$5:$F$200,"Brand page")>0,"Y",IF(COUNTIFS('QC listings'!$A$5:$A$200,$M36,'QC listings'!$C$5:$C$200,Q$4)>0,"?","–"))) | R36: =IF($M36="","",IF(COUNTIFS('QC listings'!$A$5:$A$200,$M36,'QC listings'!$C$5:$C$200,R$4,'QC listings'!$F$5:$F$200,"Listing page")+COUNTIFS('QC listings'!$A$5:$A$200,$M36,'QC listings'!$C$5:$C$200,R$4,'QC listings'!$F$5:$F$200,"Brand page")>0,"Y",IF(COUNTIFS('QC listings'!$A$5:$A$200,$M36,'QC listings'!$C$5:$C$200,R$4)>0,"?","–"))) | S36: =IF($M36="","",COUNTIF(O36:R36,"Y")) | T36: =IF($M36="","",SUMPRODUCT(MAX(('QC listings'!$A$5:$A$200=$M36)*'QC listings'!$E$5:$E$200))) | U36: =IF($M36="","",IF(T36>=Scoring!$B$11,3,IF(T36>=Scoring!$B$10,2,IF(T36>=Scoring!$B$9,1,0)))) | V36: =IFERROR(INDEX(Scoring!$B$27:$B$56,MATCH($E36,Scoring!$A$27:$A$56,0)),0) -> 0 | W36: =IF($G36="","",ROUND((Scoring!$B$5-$G36)/30.4375,1)) | X36: =IF($F36="Expired",Scoring!$B$18,IF($G36="",Scoring!$B$17,IF(W36<=Scoring!$B$12,Scoring!$B$13,IF(W36<=Scoring!$B$14,Scoring!$B$15,Scoring!$B$16)))) -> 1 | Y36: =IF($M36="","",ROUND((S36*Scoring!$B$6+U36*Scoring!$B$7)*IFERROR(INDEX(Scoring!$B$22:$B$24,MATCH($N36,Scoring!$A$22:$A$24,0)),1)+V36*Scoring!$B$8+X36,2)) | Z36: =IF($M36="","",IF(SUMPRODUCT(($M$5:$M$249=$M36)*($G$5:$G$249>$G36))>0,0,IF(SUMPRODUCT(($M$5:$M$249=$M36)*($G$5:$G$249=$G36)*(ROW($M$5:$M$249)<ROW($M36)))>0,0,1))) | AA36: =IF($Z36=1,RANK($AE36,$AE$5:$AE$249,0),"") | AB36: Free login for full report | AC36: Competitor rating: link out only; full report needs a free login | AD36: Unbox brand score 10/10 | AE36: =IF($Z36=1,$Y36+$T36/1000000000-ROW()/10000000,"")
A37: R033 | B37: Aashirvaad | C37: Superior MP Atta | D37: Everyday food | E37: Atta, rice & salt | F37: Passed | G37: 46223 | H37: 04A72904 | I37: Eurofins | J37: Trustified Pass/Fail | L37: https://www.trustified.in/passandfail/aashirvaadatta | M37: AASHIRVAAD-ATTA | N37: Exact | O37: =IF($M37="","",IF(COUNTIFS('QC listings'!$A$5:$A$200,$M37,'QC listings'!$C$5:$C$200,O$4,'QC listings'!$F$5:$F$200,"Listing page")+COUNTIFS('QC listings'!$A$5:$A$200,$M37,'QC listings'!$C$5:$C$200,O$4,'QC listings'!$F$5:$F$200,"Brand page")>0,"Y",IF(COUNTIFS('QC listings'!$A$5:$A$200,$M37,'QC listings'!$C$5:$C$200,O$4)>0,"?","–"))) -> Y | P37: =IF($M37="","",IF(COUNTIFS('QC listings'!$A$5:$A$200,$M37,'QC listings'!$C$5:$C$200,P$4,'QC listings'!$F$5:$F$200,"Listing page")+COUNTIFS('QC listings'!$A$5:$A$200,$M37,'QC listings'!$C$5:$C$200,P$4,'QC listings'!$F$5:$F$200,"Brand page")>0,"Y",IF(COUNTIFS('QC listings'!$A$5:$A$200,$M37,'QC listings'!$C$5:$C$200,P$4)>0,"?","–"))) -> Y | Q37: =IF($M37="","",IF(COUNTIFS('QC listings'!$A$5:$A$200,$M37,'QC listings'!$C$5:$C$200,Q$4,'QC listings'!$F$5:$F$200,"Listing page")+COUNTIFS('QC listings'!$A$5:$A$200,$M37,'QC listings'!$C$5:$C$200,Q$4,'QC listings'!$F$5:$F$200,"Brand page")>0,"Y",IF(COUNTIFS('QC listings'!$A$5:$A$200,$M37,'QC listings'!$C$5:$C$200,Q$4)>0,"?","–"))) -> Y | R37: =IF($M37="","",IF(COUNTIFS('QC listings'!$A$5:$A$200,$M37,'QC listings'!$C$5:$C$200,R$4,'QC listings'!$F$5:$F$200,"Listing page")+COUNTIFS('QC listings'!$A$5:$A$200,$M37,'QC listings'!$C$5:$C$200,R$4,'QC listings'!$F$5:$F$200,"Brand page")>0,"Y",IF(COUNTIFS('QC listings'!$A$5:$A$200,$M37,'QC listings'!$C$5:$C$200,R$4)>0,"?","–"))) -> Y | S37: =IF($M37="","",COUNTIF(O37:R37,"Y")) -> 4 | T37: =IF($M37="","",SUMPRODUCT(MAX(('QC listings'!$A$5:$A$200=$M37)*'QC listings'!$E$5:$E$200))) -> 74917 | U37: =IF($M37="","",IF(T37>=Scoring!$B$11,3,IF(T37>=Scoring!$B$10,2,IF(T37>=Scoring!$B$9,1,0)))) -> 2 | V37: =IFERROR(INDEX(Scoring!$B$27:$B$56,MATCH($E37,Scoring!$A$27:$A$56,0)),0) -> 0 | W37: =IF($G37="","",ROUND((Scoring!$B$5-$G37)/30.4375,1)) -> 2.4 | X37: =IF($F37="Expired",Scoring!$B$18,IF($G37="",Scoring!$B$17,IF(W37<=Scoring!$B$12,Scoring!$B$13,IF(W37<=Scoring!$B$14,Scoring!$B$15,Scoring!$B$16)))) -> 2 | Y37: =IF($M37="","",ROUND((S37*Scoring!$B$6+U37*Scoring!$B$7)*IFERROR(INDEX(Scoring!$B$22:$B$24,MATCH($N37,Scoring!$A$22:$A$24,0)),1)+V37*Scoring!$B$8+X37,2)) -> 10 | Z37: =IF($M37="","",IF(SUMPRODUCT(($M$5:$M$249=$M37)*($G$5:$G$249>$G37))>0,0,IF(SUMPRODUCT(($M$5:$M$249=$M37)*($G$5:$G$249=$G37)*(ROW($M$5:$M$249)<ROW($M37)))>0,0,1))) -> 1 | AA37: =IF($Z37=1,RANK($AE37,$AE$5:$AE$249,0),"") -> 10 | AB37: Open | AC37: Link out; Trustified's written licence needed to display the report | AE37: =IF($Z37=1,$Y37+$T37/1000000000-ROW()/10000000,"") -> 10.000071
A38: R034 | B38: Daawat | C38: Brown Rice | D38: Everyday food | E38: Atta, rice & salt | F38: Failed | G38: 45837 | H38: B160048520 | I38: Eurofins | J38: Trustified Pass/Fail | L38: https://www.trustified.in/passandfail/daawatrice | O38: =IF($M38="","",IF(COUNTIFS('QC listings'!$A$5:$A$200,$M38,'QC listings'!$C$5:$C$200,O$4,'QC listings'!$F$5:$F$200,"Listing page")+COUNTIFS('QC listings'!$A$5:$A$200,$M38,'QC listings'!$C$5:$C$200,O$4,'QC listings'!$F$5:$F$200,"Brand page")>0,"Y",IF(COUNTIFS('QC listings'!$A$5:$A$200,$M38,'QC listings'!$C$5:$C$200,O$4)>0,"?","–"))) | P38: =IF($M38="","",IF(COUNTIFS('QC listings'!$A$5:$A$200,$M38,'QC listings'!$C$5:$C$200,P$4,'QC listings'!$F$5:$F$200,"Listing page")+COUNTIFS('QC listings'!$A$5:$A$200,$M38,'QC listings'!$C$5:$C$200,P$4,'QC listings'!$F$5:$F$200,"Brand page")>0,"Y",IF(COUNTIFS('QC listings'!$A$5:$A$200,$M38,'QC listings'!$C$5:$C$200,P$4)>0,"?","–"))) | Q38: =IF($M38="","",IF(COUNTIFS('QC listings'!$A$5:$A$200,$M38,'QC listings'!$C$5:$C$200,Q$4,'QC listings'!$F$5:$F$200,"Listing page")+COUNTIFS('QC listings'!$A$5:$A$200,$M38,'QC listings'!$C$5:$C$200,Q$4,'QC listings'!$F$5:$F$200,"Brand page")>0,"Y",IF(COUNTIFS('QC listings'!$A$5:$A$200,$M38,'QC listings'!$C$5:$C$200,Q$4)>0,"?","–"))) | R38: =IF($M38="","",IF(COUNTIFS('QC listings'!$A$5:$A$200,$M38,'QC listings'!$C$5:$C$200,R$4,'QC listings'!$F$5:$F$200,"Listing page")+COUNTIFS('QC listings'!$A$5:$A$200,$M38,'QC listings'!$C$5:$C$200,R$4,'QC listings'!$F$5:$F$200,"Brand page")>0,"Y",IF(COUNTIFS('QC listings'!$A$5:$A$200,$M38,'QC listings'!$C$5:$C$200,R$4)>0,"?","–"))) | S38: =IF($M38="","",COUNTIF(O38:R38,"Y")) | T38: =IF($M38="","",SUMPRODUCT(MAX(('QC listings'!$A$5:$A$200=$M38)*'QC listings'!$E$5:$E$200))) | U38: =IF($M38="","",IF(T38>=Scoring!$B$11,3,IF(T38>=Scoring!$B$10,2,IF(T38>=Scoring!$B$9,1,0)))) | V38: =IFERROR(INDEX(Scoring!$B$27:$B$56,MATCH($E38,Scoring!$A$27:$A$56,0)),0) -> 0 | W38: =IF($G38="","",ROUND((Scoring!$B$5-$G38)/30.4375,1)) -> 15.1 | X38: =IF($F38="Expired",Scoring!$B$18,IF($G38="",Scoring!$B$17,IF(W38<=Scoring!$B$12,Scoring!$B$13,IF(W38<=Scoring!$B$14,Scoring!$B$15,Scoring!$B$16)))) -> 1 | Y38: =IF($M38="","",ROUND((S38*Scoring!$B$6+U38*Scoring!$B$7)*IFERROR(INDEX(Scoring!$B$22:$B$24,MATCH($N38,Scoring!$A$22:$A$24,0)),1)+V38*Scoring!$B$8+X38,2)) | Z38: =IF($M38="","",IF(SUMPRODUCT(($M$5:$M$249=$M38)*($G$5:$G$249>$G38))>0,0,IF(SUMPRODUCT(($M$5:$M$249=$M38)*($G$5:$G$249=$G38)*(ROW($M$5:$M$249)<ROW($M38)))>0,0,1))) | AA38: =IF($Z38=1,RANK($AE38,$AE$5:$AE$249,0),"") | AB38: Open | AC38: Link out; licence needed to display; run the PRD publication gate first (negative verdict) | AE38: =IF($Z38=1,$Y38+$T38/1000000000-ROW()/10000000,"")
A39: R035 | B39: India Gate | C39: Feast Rozzana Basmati Rice | D39: Everyday food | E39: Atta, rice & salt | F39: Failed | G39: 46103 | H39: BW52E24400 | I39: Eurofins | J39: Trustified Pass/Fail | L39: https://www.trustified.in/passandfail/indiagatebasmatirice | M39: INDIAGATE-FEAST | N39: Exact | O39: =IF($M39="","",IF(COUNTIFS('QC listings'!$A$5:$A$200,$M39,'QC listings'!$C$5:$C$200,O$4,'QC listings'!$F$5:$F$200,"Listing page")+COUNTIFS('QC listings'!$A$5:$A$200,$M39,'QC listings'!$C$5:$C$200,O$4,'QC listings'!$F$5:$F$200,"Brand page")>0,"Y",IF(COUNTIFS('QC listings'!$A$5:$A$200,$M39,'QC listings'!$C$5:$C$200,O$4)>0,"?","–"))) -> – | P39: =IF($M39="","",IF(COUNTIFS('QC listings'!$A$5:$A$200,$M39,'QC listings'!$C$5:$C$200,P$4,'QC listings'!$F$5:$F$200,"Listing page")+COUNTIFS('QC listings'!$A$5:$A$200,$M39,'QC listings'!$C$5:$C$200,P$4,'QC listings'!$F$5:$F$200,"Brand page")>0,"Y",IF(COUNTIFS('QC listings'!$A$5:$A$200,$M39,'QC listings'!$C$5:$C$200,P$4)>0,"?","–"))) -> Y | Q39: =IF($M39="","",IF(COUNTIFS('QC listings'!$A$5:$A$200,$M39,'QC listings'!$C$5:$C$200,Q$4,'QC listings'!$F$5:$F$200,"Listing page")+COUNTIFS('QC listings'!$A$5:$A$200,$M39,'QC listings'!$C$5:$C$200,Q$4,'QC listings'!$F$5:$F$200,"Brand page")>0,"Y",IF(COUNTIFS('QC listings'!$A$5:$A$200,$M39,'QC listings'!$C$5:$C$200,Q$4)>0,"?","–"))) -> Y | R39: =IF($M39="","",IF(COUNTIFS('QC listings'!$A$5:$A$200,$M39,'QC listings'!$C$5:$C$200,R$4,'QC listings'!$F$5:$F$200,"Listing page")+COUNTIFS('QC listings'!$A$5:$A$200,$M39,'QC listings'!$C$5:$C$200,R$4,'QC listings'!$F$5:$F$200,"Brand page")>0,"Y",IF(COUNTIFS('QC listings'!$A$5:$A$200,$M39,'QC listings'!$C$5:$C$200,R$4)>0,"?","–"))) -> Y | S39: =IF($M39="","",COUNTIF(O39:R39,"Y")) -> 3 | T39: =IF($M39="","",SUMPRODUCT(MAX(('QC listings'!$A$5:$A$200=$M39)*'QC listings'!$E$5:$E$200))) -> 23064 | U39: =IF($M39="","",IF(T39>=Scoring!$B$11,3,IF(T39>=Scoring!$B$10,2,IF(T39>=Scoring!$B$9,1,0)))) -> 2 | V39: =IFERROR(INDEX(Scoring!$B$27:$B$56,MATCH($E39,Scoring!$A$27:$A$56,0)),0) -> 0 | W39: =IF($G39="","",ROUND((Scoring!$B$5-$G39)/30.4375,1)) -> 6.4 | X39: =IF($F39="Expired",Scoring!$B$18,IF($G39="",Scoring!$B$17,IF(W39<=Scoring!$B$12,Scoring!$B$13,IF(W39<=Scoring!$B$14,Scoring!$B$15,Scoring!$B$16)))) -> 2 | Y39: =IF($M39="","",ROUND((S39*Scoring!$B$6+U39*Scoring!$B$7)*IFERROR(INDEX(Scoring!$B$22:$B$24,MATCH($N39,Scoring!$A$22:$A$24,0)),1)+V39*Scoring!$B$8+X39,2)) -> 9 | Z39: =IF($M39="","",IF(SUMPRODUCT(($M$5:$M$249=$M39)*($G$5:$G$249>$G39))>0,0,IF(SUMPRODUCT(($M$5:$M$249=$M39)*($G$5:$G$249=$G39)*(ROW($M$5:$M$249)<ROW($M39)))>0,0,1))) -> 1 | AA39: =IF($Z39=1,RANK($AE39,$AE$5:$AE$249,0),"") -> 12 | AB39: Open | AC39: Link out; licence needed to display; run the PRD publication gate first (negative verdict) | AD39: QC: Blinkit listing not seen in my checks. | AE39: =IF($Z39=1,$Y39+$T39/1000000000-ROW()/10000000,"") -> 9.0000192
A40: R036 | B40: Tata | C40: Tata Salt | D40: Everyday food | E40: Atta, rice & salt | F40: Passed | G40: 45984 | H40: PU | I40: Eurofins | J40: Trustified Pass/Fail | L40: https://www.trustified.in/passandfail/tatasalt | M40: TATA-SALT | N40: Exact | O40: =IF($M40="","",IF(COUNTIFS('QC listings'!$A$5:$A$200,$M40,'QC listings'!$C$5:$C$200,O$4,'QC listings'!$F$5:$F$200,"Listing page")+COUNTIFS('QC listings'!$A$5:$A$200,$M40,'QC listings'!$C$5:$C$200,O$4,'QC listings'!$F$5:$F$200,"Brand page")>0,"Y",IF(COUNTIFS('QC listings'!$A$5:$A$200,$M40,'QC listings'!$C$5:$C$200,O$4)>0,"?","–"))) -> Y | P40: =IF($M40="","",IF(COUNTIFS('QC listings'!$A$5:$A$200,$M40,'QC listings'!$C$5:$C$200,P$4,'QC listings'!$F$5:$F$200,"Listing page")+COUNTIFS('QC listings'!$A$5:$A$200,$M40,'QC listings'!$C$5:$C$200,P$4,'QC listings'!$F$5:$F$200,"Brand page")>0,"Y",IF(COUNTIFS('QC listings'!$A$5:$A$200,$M40,'QC listings'!$C$5:$C$200,P$4)>0,"?","–"))) -> Y | Q40: =IF($M40="","",IF(COUNTIFS('QC listings'!$A$5:$A$200,$M40,'QC listings'!$C$5:$C$200,Q$4,'QC listings'!$F$5:$F$200,"Listing page")+COUNTIFS('QC listings'!$A$5:$A$200,$M40,'QC listings'!$C$5:$C$200,Q$4,'QC listings'!$F$5:$F$200,"Brand page")>0,"Y",IF(COUNTIFS('QC listings'!$A$5:$A$200,$M40,'QC listings'!$C$5:$C$200,Q$4)>0,"?","–"))) -> Y | R40: =IF($M40="","",IF(COUNTIFS('QC listings'!$A$5:$A$200,$M40,'QC listings'!$C$5:$C$200,R$4,'QC listings'!$F$5:$F$200,"Listing page")+COUNTIFS('QC listings'!$A$5:$A$200,$M40,'QC listings'!$C$5:$C$200,R$4,'QC listings'!$F$5:$F$200,"Brand page")>0,"Y",IF(COUNTIFS('QC listings'!$A$5:$A$200,$M40,'QC listings'!$C$5:$C$200,R$4)>0,"?","–"))) -> – | S40: =IF($M40="","",COUNTIF(O40:R40,"Y")) -> 3 | T40: =IF($M40="","",SUMPRODUCT(MAX(('QC listings'!$A$5:$A$200=$M40)*'QC listings'!$E$5:$E$200))) -> 496464 | U40: =IF($M40="","",IF(T40>=Scoring!$B$11,3,IF(T40>=Scoring!$B$10,2,IF(T40>=Scoring!$B$9,1,0)))) -> 3 | V40: =IFERROR(INDEX(Scoring!$B$27:$B$56,MATCH($E40,Scoring!$A$27:$A$56,0)),0) -> 0 | W40: =IF($G40="","",ROUND((Scoring!$B$5-$G40)/30.4375,1)) -> 10.3 | X40: =IF($F40="Expired",Scoring!$B$18,IF($G40="",Scoring!$B$17,IF(W40<=Scoring!$B$12,Scoring!$B$13,IF(W40<=Scoring!$B$14,Scoring!$B$15,Scoring!$B$16)))) -> 2 | Y40: =IF($M40="","",ROUND((S40*Scoring!$B$6+U40*Scoring!$B$7)*IFERROR(INDEX(Scoring!$B$22:$B$24,MATCH($N40,Scoring!$A$22:$A$24,0)),1)+V40*Scoring!$B$8+X40,2)) -> 11 | Z40: =IF($M40="","",IF(SUMPRODUCT(($M$5:$M$249=$M40)*($G$5:$G$249>$G40))>0,0,IF(SUMPRODUCT(($M$5:$M$249=$M40)*($G$5:$G$249=$G40)*(ROW($M$5:$M$249)<ROW($M40)))>0,0,1))) -> 1 | AA40: =IF($Z40=1,RANK($AE40,$AE$5:$AE$249,0),"") -> 6 | AB40: Open | AC40: Link out; Trustified's written licence needed to display the report | AD40: QC: BigBasket listing not seen in my checks. | AE40: =IF($Z40=1,$Y40+$T40/1000000000-ROW()/10000000,"") -> 11.000492
A41: R037 | B41: Fortune | C41: Kachi Ghani Pure Mustard Oil | D41: Everyday food | E41: Cooking oil | F41: Passed | G41: 45926 | H41: (AB)KM09N05 | I41: Eurofins | J41: Trustified Pass/Fail | L41: https://www.trustified.in/passandfail/fortunemustardoil | M41: FORTUNE-MUSTARD | N41: Exact | O41: =IF($M41="","",IF(COUNTIFS('QC listings'!$A$5:$A$200,$M41,'QC listings'!$C$5:$C$200,O$4,'QC listings'!$F$5:$F$200,"Listing page")+COUNTIFS('QC listings'!$A$5:$A$200,$M41,'QC listings'!$C$5:$C$200,O$4,'QC listings'!$F$5:$F$200,"Brand page")>0,"Y",IF(COUNTIFS('QC listings'!$A$5:$A$200,$M41,'QC listings'!$C$5:$C$200,O$4)>0,"?","–"))) -> Y | P41: =IF($M41="","",IF(COUNTIFS('QC listings'!$A$5:$A$200,$M41,'QC listings'!$C$5:$C$200,P$4,'QC listings'!$F$5:$F$200,"Listing page")+COUNTIFS('QC listings'!$A$5:$A$200,$M41,'QC listings'!$C$5:$C$200,P$4,'QC listings'!$F$5:$F$200,"Brand page")>0,"Y",IF(COUNTIFS('QC listings'!$A$5:$A$200,$M41,'QC listings'!$C$5:$C$200,P$4)>0,"?","–"))) -> Y | Q41: =IF($M41="","",IF(COUNTIFS('QC listings'!$A$5:$A$200,$M41,'QC listings'!$C$5:$C$200,Q$4,'QC listings'!$F$5:$F$200,"Listing page")+COUNTIFS('QC listings'!$A$5:$A$200,$M41,'QC listings'!$C$5:$C$200,Q$4,'QC listings'!$F$5:$F$200,"Brand page")>0,"Y",IF(COUNTIFS('QC listings'!$A$5:$A$200,$M41,'QC listings'!$C$5:$C$200,Q$4)>0,"?","–"))) -> – | R41: =IF($M41="","",IF(COUNTIFS('QC listings'!$A$5:$A$200,$M41,'QC listings'!$C$5:$C$200,R$4,'QC listings'!$F$5:$F$200,"Listing page")+COUNTIFS('QC listings'!$A$5:$A$200,$M41,'QC listings'!$C$5:$C$200,R$4,'QC listings'!$F$5:$F$200,"Brand page")>0,"Y",IF(COUNTIFS('QC listings'!$A$5:$A$200,$M41,'QC listings'!$C$5:$C$200,R$4)>0,"?","–"))) -> Y | S41: =IF($M41="","",COUNTIF(O41:R41,"Y")) -> 3 | T41: =IF($M41="","",SUMPRODUCT(MAX(('QC listings'!$A$5:$A$200=$M41)*'QC listings'!$E$5:$E$200))) -> 19850 | U41: =IF($M41="","",IF(T41>=Scoring!$B$11,3,IF(T41>=Scoring!$B$10,2,IF(T41>=Scoring!$B$9,1,0)))) -> 2 | V41: =IFERROR(INDEX(Scoring!$B$27:$B$56,MATCH($E41,Scoring!$A$27:$A$56,0)),0) -> 0 | W41: =IF($G41="","",ROUND((Scoring!$B$5-$G41)/30.4375,1)) -> 12.2 | X41: =IF($F41="Expired",Scoring!$B$18,IF($G41="",Scoring!$B$17,IF(W41<=Scoring!$B$12,Scoring!$B$13,IF(W41<=Scoring!$B$14,Scoring!$B$15,Scoring!$B$16)))) -> 1 | Y41: =IF($M41="","",ROUND((S41*Scoring!$B$6+U41*Scoring!$B$7)*IFERROR(INDEX(Scoring!$B$22:$B$24,MATCH($N41,Scoring!$A$22:$A$24,0)),1)+V41*Scoring!$B$8+X41,2)) -> 8 | Z41: =IF($M41="","",IF(SUMPRODUCT(($M$5:$M$249=$M41)*($G$5:$G$249>$G41))>0,0,IF(SUMPRODUCT(($M$5:$M$249=$M41)*($G$5:$G$249=$G41)*(ROW($M$5:$M$249)<ROW($M41)))>0,0,1))) -> 1 | AA41: =IF($Z41=1,RANK($AE41,$AE$5:$AE$249,0),"") -> 15 | AB41: Open | AC41: Link out; Trustified's written licence needed to display the report | AD41: Verdict taken from the Pass/Fail tile; the status line on the list page is blank; QC: Instamart not seen. | AE41: =IF($Z41=1,$Y41+$T41/1000000000-ROW()/10000000,"") -> 8.0000157
A42: R038 | B42: Jivo | C42: Extra Light Olive Oil | D42: Everyday food | E42: Cooking oil | F42: Failed | G42: 45909 | H42: 007676.28 | I42: Eurofins | J42: Trustified Pass/Fail | L42: https://www.trustified.in/passandfail/jivooliveoil | O42: =IF($M42="","",IF(COUNTIFS('QC listings'!$A$5:$A$200,$M42,'QC listings'!$C$5:$C$200,O$4,'QC listings'!$F$5:$F$200,"Listing page")+COUNTIFS('QC listings'!$A$5:$A$200,$M42,'QC listings'!$C$5:$C$200,O$4,'QC listings'!$F$5:$F$200,"Brand page")>0,"Y",IF(COUNTIFS('QC listings'!$A$5:$A$200,$M42,'QC listings'!$C$5:$C$200,O$4)>0,"?","–"))) | P42: =IF($M42="","",IF(COUNTIFS('QC listings'!$A$5:$A$200,$M42,'QC listings'!$C$5:$C$200,P$4,'QC listings'!$F$5:$F$200,"Listing page")+COUNTIFS('QC listings'!$A$5:$A$200,$M42,'QC listings'!$C$5:$C$200,P$4,'QC listings'!$F$5:$F$200,"Brand page")>0,"Y",IF(COUNTIFS('QC listings'!$A$5:$A$200,$M42,'QC listings'!$C$5:$C$200,P$4)>0,"?","–"))) | Q42: =IF($M42="","",IF(COUNTIFS('QC listings'!$A$5:$A$200,$M42,'QC listings'!$C$5:$C$200,Q$4,'QC listings'!$F$5:$F$200,"Listing page")+COUNTIFS('QC listings'!$A$5:$A$200,$M42,'QC listings'!$C$5:$C$200,Q$4,'QC listings'!$F$5:$F$200,"Brand page")>0,"Y",IF(COUNTIFS('QC listings'!$A$5:$A$200,$M42,'QC listings'!$C$5:$C$200,Q$4)>0,"?","–"))) | R42: =IF($M42="","",IF(COUNTIFS('QC listings'!$A$5:$A$200,$M42,'QC listings'!$C$5:$C$200,R$4,'QC listings'!$F$5:$F$200,"Listing page")+COUNTIFS('QC listings'!$A$5:$A$200,$M42,'QC listings'!$C$5:$C$200,R$4,'QC listings'!$F$5:$F$200,"Brand page")>0,"Y",IF(COUNTIFS('QC listings'!$A$5:$A$200,$M42,'QC listings'!$C$5:$C$200,R$4)>0,"?","–"))) | S42: =IF($M42="","",COUNTIF(O42:R42,"Y")) | T42: =IF($M42="","",SUMPRODUCT(MAX(('QC listings'!$A$5:$A$200=$M42)*'QC listings'!$E$5:$E$200))) | U42: =IF($M42="","",IF(T42>=Scoring!$B$11,3,IF(T42>=Scoring!$B$10,2,IF(T42>=Scoring!$B$9,1,0)))) | V42: =IFERROR(INDEX(Scoring!$B$27:$B$56,MATCH($E42,Scoring!$A$27:$A$56,0)),0) -> 0 | W42: =IF($G42="","",ROUND((Scoring!$B$5-$G42)/30.4375,1)) -> 12.7 | X42: =IF($F42="Expired",Scoring!$B$18,IF($G42="",Scoring!$B$17,IF(W42<=Scoring!$B$12,Scoring!$B$13,IF(W42<=Scoring!$B$14,Scoring!$B$15,Scoring!$B$16)))) -> 1 | Y42: =IF($M42="","",ROUND((S42*Scoring!$B$6+U42*Scoring!$B$7)*IFERROR(INDEX(Scoring!$B$22:$B$24,MATCH($N42,Scoring!$A$22:$A$24,0)),1)+V42*Scoring!$B$8+X42,2)) | Z42: =IF($M42="","",IF(SUMPRODUCT(($M$5:$M$249=$M42)*($G$5:$G$249>$G42))>0,0,IF(SUMPRODUCT(($M$5:$M$249=$M42)*($G$5:$G$249=$G42)*(ROW($M$5:$M$249)<ROW($M42)))>0,0,1))) | AA42: =IF($Z42=1,RANK($AE42,$AE$5:$AE$249,0),"") | AB42: Open | AC42: Link out; licence needed to display; run the PRD publication gate first (negative verdict) | AE42: =IF($Z42=1,$Y42+$T42/1000000000-ROW()/10000000,"")
A43: R039 | B43: Jivo | C43: Extra Virgin Olive Oil | D43: Everyday food | E43: Cooking oil | F43: Listed, rating not captured | I43: NABL labs (up to 3 per sample) | J43: Unbox Health | L43: https://www.unboxhealth.in/explore/product/799dab45-406f-48cf-9bde-2161b333057b | O43: =IF($M43="","",IF(COUNTIFS('QC listings'!$A$5:$A$200,$M43,'QC listings'!$C$5:$C$200,O$4,'QC listings'!$F$5:$F$200,"Listing page")+COUNTIFS('QC listings'!$A$5:$A$200,$M43,'QC listings'!$C$5:$C$200,O$4,'QC listings'!$F$5:$F$200,"Brand page")>0,"Y",IF(COUNTIFS('QC listings'!$A$5:$A$200,$M43,'QC listings'!$C$5:$C$200,O$4)>0,"?","–"))) | P43: =IF($M43="","",IF(COUNTIFS('QC listings'!$A$5:$A$200,$M43,'QC listings'!$C$5:$C$200,P$4,'QC listings'!$F$5:$F$200,"Listing page")+COUNTIFS('QC listings'!$A$5:$A$200,$M43,'QC listings'!$C$5:$C$200,P$4,'QC listings'!$F$5:$F$200,"Brand page")>0,"Y",IF(COUNTIFS('QC listings'!$A$5:$A$200,$M43,'QC listings'!$C$5:$C$200,P$4)>0,"?","–"))) | Q43: =IF($M43="","",IF(COUNTIFS('QC listings'!$A$5:$A$200,$M43,'QC listings'!$C$5:$C$200,Q$4,'QC listings'!$F$5:$F$200,"Listing page")+COUNTIFS('QC listings'!$A$5:$A$200,$M43,'QC listings'!$C$5:$C$200,Q$4,'QC listings'!$F$5:$F$200,"Brand page")>0,"Y",IF(COUNTIFS('QC listings'!$A$5:$A$200,$M43,'QC listings'!$C$5:$C$200,Q$4)>0,"?","–"))) | R43: =IF($M43="","",IF(COUNTIFS('QC listings'!$A$5:$A$200,$M43,'QC listings'!$C$5:$C$200,R$4,'QC listings'!$F$5:$F$200,"Listing page")+COUNTIFS('QC listings'!$A$5:$A$200,$M43,'QC listings'!$C$5:$C$200,R$4,'QC listings'!$F$5:$F$200,"Brand page")>0,"Y",IF(COUNTIFS('QC listings'!$A$5:$A$200,$M43,'QC listings'!$C$5:$C$200,R$4)>0,"?","–"))) | S43: =IF($M43="","",COUNTIF(O43:R43,"Y")) | T43: =IF($M43="","",SUMPRODUCT(MAX(('QC listings'!$A$5:$A$200=$M43)*'QC listings'!$E$5:$E$200))) | U43: =IF($M43="","",IF(T43>=Scoring!$B$11,3,IF(T43>=Scoring!$B$10,2,IF(T43>=Scoring!$B$9,1,0)))) | V43: =IFERROR(INDEX(Scoring!$B$27:$B$56,MATCH($E43,Scoring!$A$27:$A$56,0)),0) -> 0 | W43: =IF($G43="","",ROUND((Scoring!$B$5-$G43)/30.4375,1)) | X43: =IF($F43="Expired",Scoring!$B$18,IF($G43="",Scoring!$B$17,IF(W43<=Scoring!$B$12,Scoring!$B$13,IF(W43<=Scoring!$B$14,Scoring!$B$15,Scoring!$B$16)))) -> 1 | Y43: =IF($M43="","",ROUND((S43*Scoring!$B$6+U43*Scoring!$B$7)*IFERROR(INDEX(Scoring!$B$22:$B$24,MATCH($N43,Scoring!$A$22:$A$24,0)),1)+V43*Scoring!$B$8+X43,2)) | Z43: =IF($M43="","",IF(SUMPRODUCT(($M$5:$M$249=$M43)*($G$5:$G$249>$G43))>0,0,IF(SUMPRODUCT(($M$5:$M$249=$M43)*($G$5:$G$249=$G43)*(ROW($M$5:$M$249)<ROW($M43)))>0,0,1))) | AA43: =IF($Z43=1,RANK($AE43,$AE$5:$AE$249,0),"") | AB43: Free login for full report | AC43: Competitor rating: link out only; full report needs a free login | AE43: =IF($Z43=1,$Y43+$T43/1000000000-ROW()/10000000,"")
A44: R040 | B44: Fortune | C44: Soya Chunks | D44: Everyday food | E44: Soya & protein flour | F44: Passed | G44: 45695 | H44: (VA) CK56M12 | I44: Eurofins | J44: Trustified Pass/Fail | L44: https://www.trustified.in/passandfail/fortunesoyachunks | M44: FORTUNE-SOYA | N44: Exact | O44: =IF($M44="","",IF(COUNTIFS('QC listings'!$A$5:$A$200,$M44,'QC listings'!$C$5:$C$200,O$4,'QC listings'!$F$5:$F$200,"Listing page")+COUNTIFS('QC listings'!$A$5:$A$200,$M44,'QC listings'!$C$5:$C$200,O$4,'QC listings'!$F$5:$F$200,"Brand page")>0,"Y",IF(COUNTIFS('QC listings'!$A$5:$A$200,$M44,'QC listings'!$C$5:$C$200,O$4)>0,"?","–"))) -> Y | P44: =IF($M44="","",IF(COUNTIFS('QC listings'!$A$5:$A$200,$M44,'QC listings'!$C$5:$C$200,P$4,'QC listings'!$F$5:$F$200,"Listing page")+COUNTIFS('QC listings'!$A$5:$A$200,$M44,'QC listings'!$C$5:$C$200,P$4,'QC listings'!$F$5:$F$200,"Brand page")>0,"Y",IF(COUNTIFS('QC listings'!$A$5:$A$200,$M44,'QC listings'!$C$5:$C$200,P$4)>0,"?","–"))) -> Y | Q44: =IF($M44="","",IF(COUNTIFS('QC listings'!$A$5:$A$200,$M44,'QC listings'!$C$5:$C$200,Q$4,'QC listings'!$F$5:$F$200,"Listing page")+COUNTIFS('QC listings'!$A$5:$A$200,$M44,'QC listings'!$C$5:$C$200,Q$4,'QC listings'!$F$5:$F$200,"Brand page")>0,"Y",IF(COUNTIFS('QC listings'!$A$5:$A$200,$M44,'QC listings'!$C$5:$C$200,Q$4)>0,"?","–"))) -> – | R44: =IF($M44="","",IF(COUNTIFS('QC listings'!$A$5:$A$200,$M44,'QC listings'!$C$5:$C$200,R$4,'QC listings'!$F$5:$F$200,"Listing page")+COUNTIFS('QC listings'!$A$5:$A$200,$M44,'QC listings'!$C$5:$C$200,R$4,'QC listings'!$F$5:$F$200,"Brand page")>0,"Y",IF(COUNTIFS('QC listings'!$A$5:$A$200,$M44,'QC listings'!$C$5:$C$200,R$4)>0,"?","–"))) -> Y | S44: =IF($M44="","",COUNTIF(O44:R44,"Y")) -> 3 | T44: =IF($M44="","",SUMPRODUCT(MAX(('QC listings'!$A$5:$A$200=$M44)*'QC listings'!$E$5:$E$200))) -> 24414 | U44: =IF($M44="","",IF(T44>=Scoring!$B$11,3,IF(T44>=Scoring!$B$10,2,IF(T44>=Scoring!$B$9,1,0)))) -> 2 | V44: =IFERROR(INDEX(Scoring!$B$27:$B$56,MATCH($E44,Scoring!$A$27:$A$56,0)),0) -> 0 | W44: =IF($G44="","",ROUND((Scoring!$B$5-$G44)/30.4375,1)) -> 19.8 | X44: =IF($F44="Expired",Scoring!$B$18,IF($G44="",Scoring!$B$17,IF(W44<=Scoring!$B$12,Scoring!$B$13,IF(W44<=Scoring!$B$14,Scoring!$B$15,Scoring!$B$16)))) -> 1 | Y44: =IF($M44="","",ROUND((S44*Scoring!$B$6+U44*Scoring!$B$7)*IFERROR(INDEX(Scoring!$B$22:$B$24,MATCH($N44,Scoring!$A$22:$A$24,0)),1)+V44*Scoring!$B$8+X44,2)) -> 8 | Z44: =IF($M44="","",IF(SUMPRODUCT(($M$5:$M$249=$M44)*($G$5:$G$249>$G44))>0,0,IF(SUMPRODUCT(($M$5:$M$249=$M44)*($G$5:$G$249=$G44)*(ROW($M$5:$M$249)<ROW($M44)))>0,0,1))) -> 1 | AA44: =IF($Z44=1,RANK($AE44,$AE$5:$AE$249,0),"") -> 14 | AB44: Open | AC44: Link out; Trustified's written licence needed to display the report | AD44: QC: Blinkit 'mini chunks' card (38,641 ratings) is a different variant, not counted. Instamart not seen. | AE44: =IF($Z44=1,$Y44+$T44/1000000000-ROW()/10000000,"") -> 8.00002
A45: R041 | B45: Mill'd | C45: High Protein Flour | D45: Everyday food | E45: Soya & protein flour | F45: Passed | G45: 46121 | H45: IYI2AE | I45: Eurofins | J45: Trustified Pass/Fail | L45: https://www.trustified.in/passandfail/milldproteinflour | O45: =IF($M45="","",IF(COUNTIFS('QC listings'!$A$5:$A$200,$M45,'QC listings'!$C$5:$C$200,O$4,'QC listings'!$F$5:$F$200,"Listing page")+COUNTIFS('QC listings'!$A$5:$A$200,$M45,'QC listings'!$C$5:$C$200,O$4,'QC listings'!$F$5:$F$200,"Brand page")>0,"Y",IF(COUNTIFS('QC listings'!$A$5:$A$200,$M45,'QC listings'!$C$5:$C$200,O$4)>0,"?","–"))) | P45: =IF($M45="","",IF(COUNTIFS('QC listings'!$A$5:$A$200,$M45,'QC listings'!$C$5:$C$200,P$4,'QC listings'!$F$5:$F$200,"Listing page")+COUNTIFS('QC listings'!$A$5:$A$200,$M45,'QC listings'!$C$5:$C$200,P$4,'QC listings'!$F$5:$F$200,"Brand page")>0,"Y",IF(COUNTIFS('QC listings'!$A$5:$A$200,$M45,'QC listings'!$C$5:$C$200,P$4)>0,"?","–"))) | Q45: =IF($M45="","",IF(COUNTIFS('QC listings'!$A$5:$A$200,$M45,'QC listings'!$C$5:$C$200,Q$4,'QC listings'!$F$5:$F$200,"Listing page")+COUNTIFS('QC listings'!$A$5:$A$200,$M45,'QC listings'!$C$5:$C$200,Q$4,'QC listings'!$F$5:$F$200,"Brand page")>0,"Y",IF(COUNTIFS('QC listings'!$A$5:$A$200,$M45,'QC listings'!$C$5:$C$200,Q$4)>0,"?","–"))) | R45: =IF($M45="","",IF(COUNTIFS('QC listings'!$A$5:$A$200,$M45,'QC listings'!$C$5:$C$200,R$4,'QC listings'!$F$5:$F$200,"Listing page")+COUNTIFS('QC listings'!$A$5:$A$200,$M45,'QC listings'!$C$5:$C$200,R$4,'QC listings'!$F$5:$F$200,"Brand page")>0,"Y",IF(COUNTIFS('QC listings'!$A$5:$A$200,$M45,'QC listings'!$C$5:$C$200,R$4)>0,"?","–"))) | S45: =IF($M45="","",COUNTIF(O45:R45,"Y")) | T45: =IF($M45="","",SUMPRODUCT(MAX(('QC listings'!$A$5:$A$200=$M45)*'QC listings'!$E$5:$E$200))) | U45: =IF($M45="","",IF(T45>=Scoring!$B$11,3,IF(T45>=Scoring!$B$10,2,IF(T45>=Scoring!$B$9,1,0)))) | V45: =IFERROR(INDEX(Scoring!$B$27:$B$56,MATCH($E45,Scoring!$A$27:$A$56,0)),0) -> 0 | W45: =IF($G45="","",ROUND((Scoring!$B$5-$G45)/30.4375,1)) -> 5.8 | X45: =IF($F45="Expired",Scoring!$B$18,IF($G45="",Scoring!$B$17,IF(W45<=Scoring!$B$12,Scoring!$B$13,IF(W45<=Scoring!$B$14,Scoring!$B$15,Scoring!$B$16)))) -> 2 | Y45: =IF($M45="","",ROUND((S45*Scoring!$B$6+U45*Scoring!$B$7)*IFERROR(INDEX(Scoring!$B$22:$B$24,MATCH($N45,Scoring!$A$22:$A$24,0)),1)+V45*Scoring!$B$8+X45,2)) | Z45: =IF($M45="","",IF(SUMPRODUCT(($M$5:$M$249=$M45)*($G$5:$G$249>$G45))>0,0,IF(SUMPRODUCT(($M$5:$M$249=$M45)*($G$5:$G$249=$G45)*(ROW($M$5:$M$249)<ROW($M45)))>0,0,1))) | AA45: =IF($Z45=1,RANK($AE45,$AE$5:$AE$249,0),"") | AB45: Open | AC45: Link out; Trustified's written licence needed to display the report | AE45: =IF($Z45=1,$Y45+$T45/1000000000-ROW()/10000000,"")
A46: R042 | B46: Nutrela | C46: Soya Chunks | D46: Everyday food | E46: Soya & protein flour | F46: Failed | G46: 45655 | H46: TC04L01A | I46: Eurofins | J46: Trustified Pass/Fail | L46: https://www.trustified.in/passandfail/nutrelasoyachunks | O46: =IF($M46="","",IF(COUNTIFS('QC listings'!$A$5:$A$200,$M46,'QC listings'!$C$5:$C$200,O$4,'QC listings'!$F$5:$F$200,"Listing page")+COUNTIFS('QC listings'!$A$5:$A$200,$M46,'QC listings'!$C$5:$C$200,O$4,'QC listings'!$F$5:$F$200,"Brand page")>0,"Y",IF(COUNTIFS('QC listings'!$A$5:$A$200,$M46,'QC listings'!$C$5:$C$200,O$4)>0,"?","–"))) | P46: =IF($M46="","",IF(COUNTIFS('QC listings'!$A$5:$A$200,$M46,'QC listings'!$C$5:$C$200,P$4,'QC listings'!$F$5:$F$200,"Listing page")+COUNTIFS('QC listings'!$A$5:$A$200,$M46,'QC listings'!$C$5:$C$200,P$4,'QC listings'!$F$5:$F$200,"Brand page")>0,"Y",IF(COUNTIFS('QC listings'!$A$5:$A$200,$M46,'QC listings'!$C$5:$C$200,P$4)>0,"?","–"))) | Q46: =IF($M46="","",IF(COUNTIFS('QC listings'!$A$5:$A$200,$M46,'QC listings'!$C$5:$C$200,Q$4,'QC listings'!$F$5:$F$200,"Listing page")+COUNTIFS('QC listings'!$A$5:$A$200,$M46,'QC listings'!$C$5:$C$200,Q$4,'QC listings'!$F$5:$F$200,"Brand page")>0,"Y",IF(COUNTIFS('QC listings'!$A$5:$A$200,$M46,'QC listings'!$C$5:$C$200,Q$4)>0,"?","–"))) | R46: =IF($M46="","",IF(COUNTIFS('QC listings'!$A$5:$A$200,$M46,'QC listings'!$C$5:$C$200,R$4,'QC listings'!$F$5:$F$200,"Listing page")+COUNTIFS('QC listings'!$A$5:$A$200,$M46,'QC listings'!$C$5:$C$200,R$4,'QC listings'!$F$5:$F$200,"Brand page")>0,"Y",IF(COUNTIFS('QC listings'!$A$5:$A$200,$M46,'QC listings'!$C$5:$C$200,R$4)>0,"?","–"))) | S46: =IF($M46="","",COUNTIF(O46:R46,"Y")) | T46: =IF($M46="","",SUMPRODUCT(MAX(('QC listings'!$A$5:$A$200=$M46)*'QC listings'!$E$5:$E$200))) | U46: =IF($M46="","",IF(T46>=Scoring!$B$11,3,IF(T46>=Scoring!$B$10,2,IF(T46>=Scoring!$B$9,1,0)))) | V46: =IFERROR(INDEX(Scoring!$B$27:$B$56,MATCH($E46,Scoring!$A$27:$A$56,0)),0) -> 0 | W46: =IF($G46="","",ROUND((Scoring!$B$5-$G46)/30.4375,1)) -> 21.1 | X46: =IF($F46="Expired",Scoring!$B$18,IF($G46="",Scoring!$B$17,IF(W46<=Scoring!$B$12,Scoring!$B$13,IF(W46<=Scoring!$B$14,Scoring!$B$15,Scoring!$B$16)))) -> 1 | Y46: =IF($M46="","",ROUND((S46*Scoring!$B$6+U46*Scoring!$B$7)*IFERROR(INDEX(Scoring!$B$22:$B$24,MATCH($N46,Scoring!$A$22:$A$24,0)),1)+V46*Scoring!$B$8+X46,2)) | Z46: =IF($M46="","",IF(SUMPRODUCT(($M$5:$M$249=$M46)*($G$5:$G$249>$G46))>0,0,IF(SUMPRODUCT(($M$5:$M$249=$M46)*($G$5:$G$249=$G46)*(ROW($M$5:$M$249)<ROW($M46)))>0,0,1))) | AA46: =IF($Z46=1,RANK($AE46,$AE$5:$AE$249,0),"") | AB46: Open | AC46: Link out; licence needed to display; run the PRD publication gate first (negative verdict) | AE46: =IF($Z46=1,$Y46+$T46/1000000000-ROW()/10000000,"")
A47: R043 | B47: Britannia | C47: 100% Whole Wheat Bread | D47: Everyday food | E47: Bread | F47: Passed | G47: 45653 | H47: M3S28 | I47: Eurofins | J47: Trustified Pass/Fail | L47: https://www.trustified.in/passandfail/britanniawholebread | M47: BRITANNIA-WW | N47: Exact | O47: =IF($M47="","",IF(COUNTIFS('QC listings'!$A$5:$A$200,$M47,'QC listings'!$C$5:$C$200,O$4,'QC listings'!$F$5:$F$200,"Listing page")+COUNTIFS('QC listings'!$A$5:$A$200,$M47,'QC listings'!$C$5:$C$200,O$4,'QC listings'!$F$5:$F$200,"Brand page")>0,"Y",IF(COUNTIFS('QC listings'!$A$5:$A$200,$M47,'QC listings'!$C$5:$C$200,O$4)>0,"?","–"))) -> Y | P47: =IF($M47="","",IF(COUNTIFS('QC listings'!$A$5:$A$200,$M47,'QC listings'!$C$5:$C$200,P$4,'QC listings'!$F$5:$F$200,"Listing page")+COUNTIFS('QC listings'!$A$5:$A$200,$M47,'QC listings'!$C$5:$C$200,P$4,'QC listings'!$F$5:$F$200,"Brand page")>0,"Y",IF(COUNTIFS('QC listings'!$A$5:$A$200,$M47,'QC listings'!$C$5:$C$200,P$4)>0,"?","–"))) -> – | Q47: =IF($M47="","",IF(COUNTIFS('QC listings'!$A$5:$A$200,$M47,'QC listings'!$C$5:$C$200,Q$4,'QC listings'!$F$5:$F$200,"Listing page")+COUNTIFS('QC listings'!$A$5:$A$200,$M47,'QC listings'!$C$5:$C$200,Q$4,'QC listings'!$F$5:$F$200,"Brand page")>0,"Y",IF(COUNTIFS('QC listings'!$A$5:$A$200,$M47,'QC listings'!$C$5:$C$200,Q$4)>0,"?","–"))) -> Y | R47: =IF($M47="","",IF(COUNTIFS('QC listings'!$A$5:$A$200,$M47,'QC listings'!$C$5:$C$200,R$4,'QC listings'!$F$5:$F$200,"Listing page")+COUNTIFS('QC listings'!$A$5:$A$200,$M47,'QC listings'!$C$5:$C$200,R$4,'QC listings'!$F$5:$F$200,"Brand page")>0,"Y",IF(COUNTIFS('QC listings'!$A$5:$A$200,$M47,'QC listings'!$C$5:$C$200,R$4)>0,"?","–"))) -> Y | S47: =IF($M47="","",COUNTIF(O47:R47,"Y")) -> 3 | T47: =IF($M47="","",SUMPRODUCT(MAX(('QC listings'!$A$5:$A$200=$M47)*'QC listings'!$E$5:$E$200))) -> 0 | U47: =IF($M47="","",IF(T47>=Scoring!$B$11,3,IF(T47>=Scoring!$B$10,2,IF(T47>=Scoring!$B$9,1,0)))) -> 0 | V47: =IFERROR(INDEX(Scoring!$B$27:$B$56,MATCH($E47,Scoring!$A$27:$A$56,0)),0) -> 0 | W47: =IF($G47="","",ROUND((Scoring!$B$5-$G47)/30.4375,1)) -> 21.2 | X47: =IF($F47="Expired",Scoring!$B$18,IF($G47="",Scoring!$B$17,IF(W47<=Scoring!$B$12,Scoring!$B$13,IF(W47<=Scoring!$B$14,Scoring!$B$15,Scoring!$B$16)))) -> 1 | Y47: =IF($M47="","",ROUND((S47*Scoring!$B$6+U47*Scoring!$B$7)*IFERROR(INDEX(Scoring!$B$22:$B$24,MATCH($N47,Scoring!$A$22:$A$24,0)),1)+V47*Scoring!$B$8+X47,2)) -> 4 | Z47: =IF($M47="","",IF(SUMPRODUCT(($M$5:$M$249=$M47)*($G$5:$G$249>$G47))>0,0,IF(SUMPRODUCT(($M$5:$M$249=$M47)*($G$5:$G$249=$G47)*(ROW($M$5:$M$249)<ROW($M47)))>0,0,1))) -> 1 | AA47: =IF($Z47=1,RANK($AE47,$AE$5:$AE$249,0),"") -> 25 | AB47: Open | AC47: Link out; Trustified's written licence needed to display the report | AD47: QC: Listings now read 'Zero Maida' / 'rich in dietary fibre' (renamed). Zepto not seen. | AE47: =IF($Z47=1,$Y47+$T47/1000000000-ROW()/10000000,"") -> 3.9999953
A48: R044 | B48: DMart | C48: Haldi Powder | D48: Everyday food | E48: Spices & masala | F48: Failed | G48: 46110 | H48: BT09K50080 | I48: Eurofins | J48: Trustified Pass/Fail | L48: https://www.trustified.in/passandfail/Dmarthaldipowder | O48: =IF($M48="","",IF(COUNTIFS('QC listings'!$A$5:$A$200,$M48,'QC listings'!$C$5:$C$200,O$4,'QC listings'!$F$5:$F$200,"Listing page")+COUNTIFS('QC listings'!$A$5:$A$200,$M48,'QC listings'!$C$5:$C$200,O$4,'QC listings'!$F$5:$F$200,"Brand page")>0,"Y",IF(COUNTIFS('QC listings'!$A$5:$A$200,$M48,'QC listings'!$C$5:$C$200,O$4)>0,"?","–"))) | P48: =IF($M48="","",IF(COUNTIFS('QC listings'!$A$5:$A$200,$M48,'QC listings'!$C$5:$C$200,P$4,'QC listings'!$F$5:$F$200,"Listing page")+COUNTIFS('QC listings'!$A$5:$A$200,$M48,'QC listings'!$C$5:$C$200,P$4,'QC listings'!$F$5:$F$200,"Brand page")>0,"Y",IF(COUNTIFS('QC listings'!$A$5:$A$200,$M48,'QC listings'!$C$5:$C$200,P$4)>0,"?","–"))) | Q48: =IF($M48="","",IF(COUNTIFS('QC listings'!$A$5:$A$200,$M48,'QC listings'!$C$5:$C$200,Q$4,'QC listings'!$F$5:$F$200,"Listing page")+COUNTIFS('QC listings'!$A$5:$A$200,$M48,'QC listings'!$C$5:$C$200,Q$4,'QC listings'!$F$5:$F$200,"Brand page")>0,"Y",IF(COUNTIFS('QC listings'!$A$5:$A$200,$M48,'QC listings'!$C$5:$C$200,Q$4)>0,"?","–"))) | R48: =IF($M48="","",IF(COUNTIFS('QC listings'!$A$5:$A$200,$M48,'QC listings'!$C$5:$C$200,R$4,'QC listings'!$F$5:$F$200,"Listing page")+COUNTIFS('QC listings'!$A$5:$A$200,$M48,'QC listings'!$C$5:$C$200,R$4,'QC listings'!$F$5:$F$200,"Brand page")>0,"Y",IF(COUNTIFS('QC listings'!$A$5:$A$200,$M48,'QC listings'!$C$5:$C$200,R$4)>0,"?","–"))) | S48: =IF($M48="","",COUNTIF(O48:R48,"Y")) | T48: =IF($M48="","",SUMPRODUCT(MAX(('QC listings'!$A$5:$A$200=$M48)*'QC listings'!$E$5:$E$200))) | U48: =IF($M48="","",IF(T48>=Scoring!$B$11,3,IF(T48>=Scoring!$B$10,2,IF(T48>=Scoring!$B$9,1,0)))) | V48: =IFERROR(INDEX(Scoring!$B$27:$B$56,MATCH($E48,Scoring!$A$27:$A$56,0)),0) -> 0 | W48: =IF($G48="","",ROUND((Scoring!$B$5-$G48)/30.4375,1)) -> 6.1 | X48: =IF($F48="Expired",Scoring!$B$18,IF($G48="",Scoring!$B$17,IF(W48<=Scoring!$B$12,Scoring!$B$13,IF(W48<=Scoring!$B$14,Scoring!$B$15,Scoring!$B$16)))) -> 2 | Y48: =IF($M48="","",ROUND((S48*Scoring!$B$6+U48*Scoring!$B$7)*IFERROR(INDEX(Scoring!$B$22:$B$24,MATCH($N48,Scoring!$A$22:$A$24,0)),1)+V48*Scoring!$B$8+X48,2)) | Z48: =IF($M48="","",IF(SUMPRODUCT(($M$5:$M$249=$M48)*($G$5:$G$249>$G48))>0,0,IF(SUMPRODUCT(($M$5:$M$249=$M48)*($G$5:$G$249=$G48)*(ROW($M$5:$M$249)<ROW($M48)))>0,0,1))) | AA48: =IF($Z48=1,RANK($AE48,$AE$5:$AE$249,0),"") | AB48: Open | AC48: Link out; licence needed to display; run the PRD publication gate first (negative verdict) | AE48: =IF($Z48=1,$Y48+$T48/1000000000-ROW()/10000000,"")
A49: R045 | B49: DMart | C49: Red Chilli Powder | D49: Everyday food | E49: Spices & masala | F49: Failed | G49: 46110 | H49: OG19J50103 | I49: Eurofins | J49: Trustified Pass/Fail | L49: https://www.trustified.in/passandfail/dmartredchillipowder | O49: =IF($M49="","",IF(COUNTIFS('QC listings'!$A$5:$A$200,$M49,'QC listings'!$C$5:$C$200,O$4,'QC listings'!$F$5:$F$200,"Listing page")+COUNTIFS('QC listings'!$A$5:$A$200,$M49,'QC listings'!$C$5:$C$200,O$4,'QC listings'!$F$5:$F$200,"Brand page")>0,"Y",IF(COUNTIFS('QC listings'!$A$5:$A$200,$M49,'QC listings'!$C$5:$C$200,O$4)>0,"?","–"))) | P49: =IF($M49="","",IF(COUNTIFS('QC listings'!$A$5:$A$200,$M49,'QC listings'!$C$5:$C$200,P$4,'QC listings'!$F$5:$F$200,"Listing page")+COUNTIFS('QC listings'!$A$5:$A$200,$M49,'QC listings'!$C$5:$C$200,P$4,'QC listings'!$F$5:$F$200,"Brand page")>0,"Y",IF(COUNTIFS('QC listings'!$A$5:$A$200,$M49,'QC listings'!$C$5:$C$200,P$4)>0,"?","–"))) | Q49: =IF($M49="","",IF(COUNTIFS('QC listings'!$A$5:$A$200,$M49,'QC listings'!$C$5:$C$200,Q$4,'QC listings'!$F$5:$F$200,"Listing page")+COUNTIFS('QC listings'!$A$5:$A$200,$M49,'QC listings'!$C$5:$C$200,Q$4,'QC listings'!$F$5:$F$200,"Brand page")>0,"Y",IF(COUNTIFS('QC listings'!$A$5:$A$200,$M49,'QC listings'!$C$5:$C$200,Q$4)>0,"?","–"))) | R49: =IF($M49="","",IF(COUNTIFS('QC listings'!$A$5:$A$200,$M49,'QC listings'!$C$5:$C$200,R$4,'QC listings'!$F$5:$F$200,"Listing page")+COUNTIFS('QC listings'!$A$5:$A$200,$M49,'QC listings'!$C$5:$C$200,R$4,'QC listings'!$F$5:$F$200,"Brand page")>0,"Y",IF(COUNTIFS('QC listings'!$A$5:$A$200,$M49,'QC listings'!$C$5:$C$200,R$4)>0,"?","–"))) | S49: =IF($M49="","",COUNTIF(O49:R49,"Y")) | T49: =IF($M49="","",SUMPRODUCT(MAX(('QC listings'!$A$5:$A$200=$M49)*'QC listings'!$E$5:$E$200))) | U49: =IF($M49="","",IF(T49>=Scoring!$B$11,3,IF(T49>=Scoring!$B$10,2,IF(T49>=Scoring!$B$9,1,0)))) | V49: =IFERROR(INDEX(Scoring!$B$27:$B$56,MATCH($E49,Scoring!$A$27:$A$56,0)),0) -> 0 | W49: =IF($G49="","",ROUND((Scoring!$B$5-$G49)/30.4375,1)) -> 6.1 | X49: =IF($F49="Expired",Scoring!$B$18,IF($G49="",Scoring!$B$17,IF(W49<=Scoring!$B$12,Scoring!$B$13,IF(W49<=Scoring!$B$14,Scoring!$B$15,Scoring!$B$16)))) -> 2 | Y49: =IF($M49="","",ROUND((S49*Scoring!$B$6+U49*Scoring!$B$7)*IFERROR(INDEX(Scoring!$B$22:$B$24,MATCH($N49,Scoring!$A$22:$A$24,0)),1)+V49*Scoring!$B$8+X49,2)) | Z49: =IF($M49="","",IF(SUMPRODUCT(($M$5:$M$249=$M49)*($G$5:$G$249>$G49))>0,0,IF(SUMPRODUCT(($M$5:$M$249=$M49)*($G$5:$G$249=$G49)*(ROW($M$5:$M$249)<ROW($M49)))>0,0,1))) | AA49: =IF($Z49=1,RANK($AE49,$AE$5:$AE$249,0),"") | AB49: Open | AC49: Link out; licence needed to display; run the PRD publication gate first (negative verdict) | AE49: =IF($Z49=1,$Y49+$T49/1000000000-ROW()/10000000,"")
A50: R046 | B50: Everest | C50: Garam Masala | D50: Everyday food | E50: Spices & masala | F50: Failed | G50: 46082 | H50: E14N671157 | I50: Eurofins | J50: Trustified Pass/Fail | L50: https://www.trustified.in/passandfail/everestgarammasala | O50: =IF($M50="","",IF(COUNTIFS('QC listings'!$A$5:$A$200,$M50,'QC listings'!$C$5:$C$200,O$4,'QC listings'!$F$5:$F$200,"Listing page")+COUNTIFS('QC listings'!$A$5:$A$200,$M50,'QC listings'!$C$5:$C$200,O$4,'QC listings'!$F$5:$F$200,"Brand page")>0,"Y",IF(COUNTIFS('QC listings'!$A$5:$A$200,$M50,'QC listings'!$C$5:$C$200,O$4)>0,"?","–"))) | P50: =IF($M50="","",IF(COUNTIFS('QC listings'!$A$5:$A$200,$M50,'QC listings'!$C$5:$C$200,P$4,'QC listings'!$F$5:$F$200,"Listing page")+COUNTIFS('QC listings'!$A$5:$A$200,$M50,'QC listings'!$C$5:$C$200,P$4,'QC listings'!$F$5:$F$200,"Brand page")>0,"Y",IF(COUNTIFS('QC listings'!$A$5:$A$200,$M50,'QC listings'!$C$5:$C$200,P$4)>0,"?","–"))) | Q50: =IF($M50="","",IF(COUNTIFS('QC listings'!$A$5:$A$200,$M50,'QC listings'!$C$5:$C$200,Q$4,'QC listings'!$F$5:$F$200,"Listing page")+COUNTIFS('QC listings'!$A$5:$A$200,$M50,'QC listings'!$C$5:$C$200,Q$4,'QC listings'!$F$5:$F$200,"Brand page")>0,"Y",IF(COUNTIFS('QC listings'!$A$5:$A$200,$M50,'QC listings'!$C$5:$C$200,Q$4)>0,"?","–"))) | R50: =IF($M50="","",IF(COUNTIFS('QC listings'!$A$5:$A$200,$M50,'QC listings'!$C$5:$C$200,R$4,'QC listings'!$F$5:$F$200,"Listing page")+COUNTIFS('QC listings'!$A$5:$A$200,$M50,'QC listings'!$C$5:$C$200,R$4,'QC listings'!$F$5:$F$200,"Brand page")>0,"Y",IF(COUNTIFS('QC listings'!$A$5:$A$200,$M50,'QC listings'!$C$5:$C$200,R$4)>0,"?","–"))) | S50: =IF($M50="","",COUNTIF(O50:R50,"Y")) | T50: =IF($M50="","",SUMPRODUCT(MAX(('QC listings'!$A$5:$A$200=$M50)*'QC listings'!$E$5:$E$200))) | U50: =IF($M50="","",IF(T50>=Scoring!$B$11,3,IF(T50>=Scoring!$B$10,2,IF(T50>=Scoring!$B$9,1,0)))) | V50: =IFERROR(INDEX(Scoring!$B$27:$B$56,MATCH($E50,Scoring!$A$27:$A$56,0)),0) -> 0 | W50: =IF($G50="","",ROUND((Scoring!$B$5-$G50)/30.4375,1)) -> 7.1 | X50: =IF($F50="Expired",Scoring!$B$18,IF($G50="",Scoring!$B$17,IF(W50<=Scoring!$B$12,Scoring!$B$13,IF(W50<=Scoring!$B$14,Scoring!$B$15,Scoring!$B$16)))) -> 2 | Y50: =IF($M50="","",ROUND((S50*Scoring!$B$6+U50*Scoring!$B$7)*IFERROR(INDEX(Scoring!$B$22:$B$24,MATCH($N50,Scoring!$A$22:$A$24,0)),1)+V50*Scoring!$B$8+X50,2)) | Z50: =IF($M50="","",IF(SUMPRODUCT(($M$5:$M$249=$M50)*($G$5:$G$249>$G50))>0,0,IF(SUMPRODUCT(($M$5:$M$249=$M50)*($G$5:$G$249=$G50)*(ROW($M$5:$M$249)<ROW($M50)))>0,0,1))) | AA50: =IF($Z50=1,RANK($AE50,$AE$5:$AE$249,0),"") | AB50: Open | AC50: Link out; licence needed to display; run the PRD publication gate first (negative verdict) | AE50: =IF($Z50=1,$Y50+$T50/1000000000-ROW()/10000000,"")
A51: R047 | B51: Everest | C51: Kashmirilal Mirch | D51: Everyday food | E51: Spices & masala | F51: Failed | G51: 46082 | H51: E280674318 | I51: Eurofins | J51: Trustified Pass/Fail | L51: https://www.trustified.in/passandfail/everestkashmirilalmirch | M51: EVEREST-KMIRCH | N51: Exact | O51: =IF($M51="","",IF(COUNTIFS('QC listings'!$A$5:$A$200,$M51,'QC listings'!$C$5:$C$200,O$4,'QC listings'!$F$5:$F$200,"Listing page")+COUNTIFS('QC listings'!$A$5:$A$200,$M51,'QC listings'!$C$5:$C$200,O$4,'QC listings'!$F$5:$F$200,"Brand page")>0,"Y",IF(COUNTIFS('QC listings'!$A$5:$A$200,$M51,'QC listings'!$C$5:$C$200,O$4)>0,"?","–"))) -> – | P51: =IF($M51="","",IF(COUNTIFS('QC listings'!$A$5:$A$200,$M51,'QC listings'!$C$5:$C$200,P$4,'QC listings'!$F$5:$F$200,"Listing page")+COUNTIFS('QC listings'!$A$5:$A$200,$M51,'QC listings'!$C$5:$C$200,P$4,'QC listings'!$F$5:$F$200,"Brand page")>0,"Y",IF(COUNTIFS('QC listings'!$A$5:$A$200,$M51,'QC listings'!$C$5:$C$200,P$4)>0,"?","–"))) -> Y | Q51: =IF($M51="","",IF(COUNTIFS('QC listings'!$A$5:$A$200,$M51,'QC listings'!$C$5:$C$200,Q$4,'QC listings'!$F$5:$F$200,"Listing page")+COUNTIFS('QC listings'!$A$5:$A$200,$M51,'QC listings'!$C$5:$C$200,Q$4,'QC listings'!$F$5:$F$200,"Brand page")>0,"Y",IF(COUNTIFS('QC listings'!$A$5:$A$200,$M51,'QC listings'!$C$5:$C$200,Q$4)>0,"?","–"))) -> Y | R51: =IF($M51="","",IF(COUNTIFS('QC listings'!$A$5:$A$200,$M51,'QC listings'!$C$5:$C$200,R$4,'QC listings'!$F$5:$F$200,"Listing page")+COUNTIFS('QC listings'!$A$5:$A$200,$M51,'QC listings'!$C$5:$C$200,R$4,'QC listings'!$F$5:$F$200,"Brand page")>0,"Y",IF(COUNTIFS('QC listings'!$A$5:$A$200,$M51,'QC listings'!$C$5:$C$200,R$4)>0,"?","–"))) -> Y | S51: =IF($M51="","",COUNTIF(O51:R51,"Y")) -> 3 | T51: =IF($M51="","",SUMPRODUCT(MAX(('QC listings'!$A$5:$A$200=$M51)*'QC listings'!$E$5:$E$200))) -> 22802 | U51: =IF($M51="","",IF(T51>=Scoring!$B$11,3,IF(T51>=Scoring!$B$10,2,IF(T51>=Scoring!$B$9,1,0)))) -> 2 | V51: =IFERROR(INDEX(Scoring!$B$27:$B$56,MATCH($E51,Scoring!$A$27:$A$56,0)),0) -> 0 | W51: =IF($G51="","",ROUND((Scoring!$B$5-$G51)/30.4375,1)) -> 7.1 | X51: =IF($F51="Expired",Scoring!$B$18,IF($G51="",Scoring!$B$17,IF(W51<=Scoring!$B$12,Scoring!$B$13,IF(W51<=Scoring!$B$14,Scoring!$B$15,Scoring!$B$16)))) -> 2 | Y51: =IF($M51="","",ROUND((S51*Scoring!$B$6+U51*Scoring!$B$7)*IFERROR(INDEX(Scoring!$B$22:$B$24,MATCH($N51,Scoring!$A$22:$A$24,0)),1)+V51*Scoring!$B$8+X51,2)) -> 9 | Z51: =IF($M51="","",IF(SUMPRODUCT(($M$5:$M$249=$M51)*($G$5:$G$249>$G51))>0,0,IF(SUMPRODUCT(($M$5:$M$249=$M51)*($G$5:$G$249=$G51)*(ROW($M$5:$M$249)<ROW($M51)))>0,0,1))) -> 1 | AA51: =IF($Z51=1,RANK($AE51,$AE$5:$AE$249,0),"") -> 13 | AB51: Open | AC51: Link out; licence needed to display; run the PRD publication gate first (negative verdict) | AD51: QC: Blinkit listing not seen in my checks. | AE51: =IF($Z51=1,$Y51+$T51/1000000000-ROW()/10000000,"") -> 9.0000177
A52: R048 | B52: Everest | C52: Kitchen King Masala | D52: Everyday food | E52: Spices & masala | F52: Failed | G52: 46082 | H52: E09D669081 | I52: Eurofins | J52: Trustified Pass/Fail | L52: https://www.trustified.in/passandfail/everestkitchenkingmasala | O52: =IF($M52="","",IF(COUNTIFS('QC listings'!$A$5:$A$200,$M52,'QC listings'!$C$5:$C$200,O$4,'QC listings'!$F$5:$F$200,"Listing page")+COUNTIFS('QC listings'!$A$5:$A$200,$M52,'QC listings'!$C$5:$C$200,O$4,'QC listings'!$F$5:$F$200,"Brand page")>0,"Y",IF(COUNTIFS('QC listings'!$A$5:$A$200,$M52,'QC listings'!$C$5:$C$200,O$4)>0,"?","–"))) | P52: =IF($M52="","",IF(COUNTIFS('QC listings'!$A$5:$A$200,$M52,'QC listings'!$C$5:$C$200,P$4,'QC listings'!$F$5:$F$200,"Listing page")+COUNTIFS('QC listings'!$A$5:$A$200,$M52,'QC listings'!$C$5:$C$200,P$4,'QC listings'!$F$5:$F$200,"Brand page")>0,"Y",IF(COUNTIFS('QC listings'!$A$5:$A$200,$M52,'QC listings'!$C$5:$C$200,P$4)>0,"?","–"))) | Q52: =IF($M52="","",IF(COUNTIFS('QC listings'!$A$5:$A$200,$M52,'QC listings'!$C$5:$C$200,Q$4,'QC listings'!$F$5:$F$200,"Listing page")+COUNTIFS('QC listings'!$A$5:$A$200,$M52,'QC listings'!$C$5:$C$200,Q$4,'QC listings'!$F$5:$F$200,"Brand page")>0,"Y",IF(COUNTIFS('QC listings'!$A$5:$A$200,$M52,'QC listings'!$C$5:$C$200,Q$4)>0,"?","–"))) | R52: =IF($M52="","",IF(COUNTIFS('QC listings'!$A$5:$A$200,$M52,'QC listings'!$C$5:$C$200,R$4,'QC listings'!$F$5:$F$200,"Listing page")+COUNTIFS('QC listings'!$A$5:$A$200,$M52,'QC listings'!$C$5:$C$200,R$4,'QC listings'!$F$5:$F$200,"Brand page")>0,"Y",IF(COUNTIFS('QC listings'!$A$5:$A$200,$M52,'QC listings'!$C$5:$C$200,R$4)>0,"?","–"))) | S52: =IF($M52="","",COUNTIF(O52:R52,"Y")) | T52: =IF($M52="","",SUMPRODUCT(MAX(('QC listings'!$A$5:$A$200=$M52)*'QC listings'!$E$5:$E$200))) | U52: =IF($M52="","",IF(T52>=Scoring!$B$11,3,IF(T52>=Scoring!$B$10,2,IF(T52>=Scoring!$B$9,1,0)))) | V52: =IFERROR(INDEX(Scoring!$B$27:$B$56,MATCH($E52,Scoring!$A$27:$A$56,0)),0) -> 0 | W52: =IF($G52="","",ROUND((Scoring!$B$5-$G52)/30.4375,1)) -> 7.1 | X52: =IF($F52="Expired",Scoring!$B$18,IF($G52="",Scoring!$B$17,IF(W52<=Scoring!$B$12,Scoring!$B$13,IF(W52<=Scoring!$B$14,Scoring!$B$15,Scoring!$B$16)))) -> 2 | Y52: =IF($M52="","",ROUND((S52*Scoring!$B$6+U52*Scoring!$B$7)*IFERROR(INDEX(Scoring!$B$22:$B$24,MATCH($N52,Scoring!$A$22:$A$24,0)),1)+V52*Scoring!$B$8+X52,2)) | Z52: =IF($M52="","",IF(SUMPRODUCT(($M$5:$M$249=$M52)*($G$5:$G$249>$G52))>0,0,IF(SUMPRODUCT(($M$5:$M$249=$M52)*($G$5:$G$249=$G52)*(ROW($M$5:$M$249)<ROW($M52)))>0,0,1))) | AA52: =IF($Z52=1,RANK($AE52,$AE$5:$AE$249,0),"") | AB52: Open | AC52: Link out; licence needed to display; run the PRD publication gate first (negative verdict) | AE52: =IF($Z52=1,$Y52+$T52/1000000000-ROW()/10000000,"")
A53: R049 | B53: Everest | C53: Meat Masala | D53: Everyday food | E53: Spices & masala | F53: Failed | G53: 46082 | H53: E12D660803 | I53: Eurofins | J53: Trustified Pass/Fail | L53: https://www.trustified.in/passandfail/everestmeatmasala | O53: =IF($M53="","",IF(COUNTIFS('QC listings'!$A$5:$A$200,$M53,'QC listings'!$C$5:$C$200,O$4,'QC listings'!$F$5:$F$200,"Listing page")+COUNTIFS('QC listings'!$A$5:$A$200,$M53,'QC listings'!$C$5:$C$200,O$4,'QC listings'!$F$5:$F$200,"Brand page")>0,"Y",IF(COUNTIFS('QC listings'!$A$5:$A$200,$M53,'QC listings'!$C$5:$C$200,O$4)>0,"?","–"))) | P53: =IF($M53="","",IF(COUNTIFS('QC listings'!$A$5:$A$200,$M53,'QC listings'!$C$5:$C$200,P$4,'QC listings'!$F$5:$F$200,"Listing page")+COUNTIFS('QC listings'!$A$5:$A$200,$M53,'QC listings'!$C$5:$C$200,P$4,'QC listings'!$F$5:$F$200,"Brand page")>0,"Y",IF(COUNTIFS('QC listings'!$A$5:$A$200,$M53,'QC listings'!$C$5:$C$200,P$4)>0,"?","–"))) | Q53: =IF($M53="","",IF(COUNTIFS('QC listings'!$A$5:$A$200,$M53,'QC listings'!$C$5:$C$200,Q$4,'QC listings'!$F$5:$F$200,"Listing page")+COUNTIFS('QC listings'!$A$5:$A$200,$M53,'QC listings'!$C$5:$C$200,Q$4,'QC listings'!$F$5:$F$200,"Brand page")>0,"Y",IF(COUNTIFS('QC listings'!$A$5:$A$200,$M53,'QC listings'!$C$5:$C$200,Q$4)>0,"?","–"))) | R53: =IF($M53="","",IF(COUNTIFS('QC listings'!$A$5:$A$200,$M53,'QC listings'!$C$5:$C$200,R$4,'QC listings'!$F$5:$F$200,"Listing page")+COUNTIFS('QC listings'!$A$5:$A$200,$M53,'QC listings'!$C$5:$C$200,R$4,'QC listings'!$F$5:$F$200,"Brand page")>0,"Y",IF(COUNTIFS('QC listings'!$A$5:$A$200,$M53,'QC listings'!$C$5:$C$200,R$4)>0,"?","–"))) | S53: =IF($M53="","",COUNTIF(O53:R53,"Y")) | T53: =IF($M53="","",SUMPRODUCT(MAX(('QC listings'!$A$5:$A$200=$M53)*'QC listings'!$E$5:$E$200))) | U53: =IF($M53="","",IF(T53>=Scoring!$B$11,3,IF(T53>=Scoring!$B$10,2,IF(T53>=Scoring!$B$9,1,0)))) | V53: =IFERROR(INDEX(Scoring!$B$27:$B$56,MATCH($E53,Scoring!$A$27:$A$56,0)),0) -> 0 | W53: =IF($G53="","",ROUND((Scoring!$B$5-$G53)/30.4375,1)) -> 7.1 | X53: =IF($F53="Expired",Scoring!$B$18,IF($G53="",Scoring!$B$17,IF(W53<=Scoring!$B$12,Scoring!$B$13,IF(W53<=Scoring!$B$14,Scoring!$B$15,Scoring!$B$16)))) -> 2 | Y53: =IF($M53="","",ROUND((S53*Scoring!$B$6+U53*Scoring!$B$7)*IFERROR(INDEX(Scoring!$B$22:$B$24,MATCH($N53,Scoring!$A$22:$A$24,0)),1)+V53*Scoring!$B$8+X53,2)) | Z53: =IF($M53="","",IF(SUMPRODUCT(($M$5:$M$249=$M53)*($G$5:$G$249>$G53))>0,0,IF(SUMPRODUCT(($M$5:$M$249=$M53)*($G$5:$G$249=$G53)*(ROW($M$5:$M$249)<ROW($M53)))>0,0,1))) | AA53: =IF($Z53=1,RANK($AE53,$AE$5:$AE$249,0),"") | AB53: Open | AC53: Link out; licence needed to display; run the PRD publication gate first (negative verdict) | AE53: =IF($Z53=1,$Y53+$T53/1000000000-ROW()/10000000,"")
A54: R050 | B54: Maggi | C54: Masala-ae-Magic | D54: Everyday food | E54: Spices & masala | F54: Passed | G54: 46068 | H54: 50580455AA-M | I54: Eurofins | J54: Trustified Pass/Fail | L54: https://www.trustified.in/passandfail/magicamasala | M54: MAGGI-MAGIC | N54: Exact | O54: =IF($M54="","",IF(COUNTIFS('QC listings'!$A$5:$A$200,$M54,'QC listings'!$C$5:$C$200,O$4,'QC listings'!$F$5:$F$200,"Listing page")+COUNTIFS('QC listings'!$A$5:$A$200,$M54,'QC listings'!$C$5:$C$200,O$4,'QC listings'!$F$5:$F$200,"Brand page")>0,"Y",IF(COUNTIFS('QC listings'!$A$5:$A$200,$M54,'QC listings'!$C$5:$C$200,O$4)>0,"?","–"))) -> Y | P54: =IF($M54="","",IF(COUNTIFS('QC listings'!$A$5:$A$200,$M54,'QC listings'!$C$5:$C$200,P$4,'QC listings'!$F$5:$F$200,"Listing page")+COUNTIFS('QC listings'!$A$5:$A$200,$M54,'QC listings'!$C$5:$C$200,P$4,'QC listings'!$F$5:$F$200,"Brand page")>0,"Y",IF(COUNTIFS('QC listings'!$A$5:$A$200,$M54,'QC listings'!$C$5:$C$200,P$4)>0,"?","–"))) -> Y | Q54: =IF($M54="","",IF(COUNTIFS('QC listings'!$A$5:$A$200,$M54,'QC listings'!$C$5:$C$200,Q$4,'QC listings'!$F$5:$F$200,"Listing page")+COUNTIFS('QC listings'!$A$5:$A$200,$M54,'QC listings'!$C$5:$C$200,Q$4,'QC listings'!$F$5:$F$200,"Brand page")>0,"Y",IF(COUNTIFS('QC listings'!$A$5:$A$200,$M54,'QC listings'!$C$5:$C$200,Q$4)>0,"?","–"))) -> Y | R54: =IF($M54="","",IF(COUNTIFS('QC listings'!$A$5:$A$200,$M54,'QC listings'!$C$5:$C$200,R$4,'QC listings'!$F$5:$F$200,"Listing page")+COUNTIFS('QC listings'!$A$5:$A$200,$M54,'QC listings'!$C$5:$C$200,R$4,'QC listings'!$F$5:$F$200,"Brand page")>0,"Y",IF(COUNTIFS('QC listings'!$A$5:$A$200,$M54,'QC listings'!$C$5:$C$200,R$4)>0,"?","–"))) -> Y | S54: =IF($M54="","",COUNTIF(O54:R54,"Y")) -> 4 | T54: =IF($M54="","",SUMPRODUCT(MAX(('QC listings'!$A$5:$A$200=$M54)*'QC listings'!$E$5:$E$200))) -> 94808 | U54: =IF($M54="","",IF(T54>=Scoring!$B$11,3,IF(T54>=Scoring!$B$10,2,IF(T54>=Scoring!$B$9,1,0)))) -> 2 | V54: =IFERROR(INDEX(Scoring!$B$27:$B$56,MATCH($E54,Scoring!$A$27:$A$56,0)),0) -> 0 | W54: =IF($G54="","",ROUND((Scoring!$B$5-$G54)/30.4375,1)) -> 7.5 | X54: =IF($F54="Expired",Scoring!$B$18,IF($G54="",Scoring!$B$17,IF(W54<=Scoring!$B$12,Scoring!$B$13,IF(W54<=Scoring!$B$14,Scoring!$B$15,Scoring!$B$16)))) -> 2 | Y54: =IF($M54="","",ROUND((S54*Scoring!$B$6+U54*Scoring!$B$7)*IFERROR(INDEX(Scoring!$B$22:$B$24,MATCH($N54,Scoring!$A$22:$A$24,0)),1)+V54*Scoring!$B$8+X54,2)) -> 10 | Z54: =IF($M54="","",IF(SUMPRODUCT(($M$5:$M$249=$M54)*($G$5:$G$249>$G54))>0,0,IF(SUMPRODUCT(($M$5:$M$249=$M54)*($G$5:$G$249=$G54)*(ROW($M$5:$M$249)<ROW($M54)))>0,0,1))) -> 1 | AA54: =IF($Z54=1,RANK($AE54,$AE$5:$AE$249,0),"") -> 9 | AB54: Open | AC54: Link out; Trustified's written licence needed to display the report | AE54: =IF($Z54=1,$Y54+$T54/1000000000-ROW()/10000000,"") -> 10.000089
A55: R051 | B55: MDH | C55: Biryani Masala | D55: Everyday food | E55: Spices & masala | F55: Failed | G55: 46229 | H55: FA-006 | I55: Eurofins | J55: Trustified Pass/Fail | L55: https://www.trustified.in/passandfail/mdhbiryanimasala | O55: =IF($M55="","",IF(COUNTIFS('QC listings'!$A$5:$A$200,$M55,'QC listings'!$C$5:$C$200,O$4,'QC listings'!$F$5:$F$200,"Listing page")+COUNTIFS('QC listings'!$A$5:$A$200,$M55,'QC listings'!$C$5:$C$200,O$4,'QC listings'!$F$5:$F$200,"Brand page")>0,"Y",IF(COUNTIFS('QC listings'!$A$5:$A$200,$M55,'QC listings'!$C$5:$C$200,O$4)>0,"?","–"))) | P55: =IF($M55="","",IF(COUNTIFS('QC listings'!$A$5:$A$200,$M55,'QC listings'!$C$5:$C$200,P$4,'QC listings'!$F$5:$F$200,"Listing page")+COUNTIFS('QC listings'!$A$5:$A$200,$M55,'QC listings'!$C$5:$C$200,P$4,'QC listings'!$F$5:$F$200,"Brand page")>0,"Y",IF(COUNTIFS('QC listings'!$A$5:$A$200,$M55,'QC listings'!$C$5:$C$200,P$4)>0,"?","–"))) | Q55: =IF($M55="","",IF(COUNTIFS('QC listings'!$A$5:$A$200,$M55,'QC listings'!$C$5:$C$200,Q$4,'QC listings'!$F$5:$F$200,"Listing page")+COUNTIFS('QC listings'!$A$5:$A$200,$M55,'QC listings'!$C$5:$C$200,Q$4,'QC listings'!$F$5:$F$200,"Brand page")>0,"Y",IF(COUNTIFS('QC listings'!$A$5:$A$200,$M55,'QC listings'!$C$5:$C$200,Q$4)>0,"?","–"))) | R55: =IF($M55="","",IF(COUNTIFS('QC listings'!$A$5:$A$200,$M55,'QC listings'!$C$5:$C$200,R$4,'QC listings'!$F$5:$F$200,"Listing page")+COUNTIFS('QC listings'!$A$5:$A$200,$M55,'QC listings'!$C$5:$C$200,R$4,'QC listings'!$F$5:$F$200,"Brand page")>0,"Y",IF(COUNTIFS('QC listings'!$A$5:$A$200,$M55,'QC listings'!$C$5:$C$200,R$4)>0,"?","–"))) | S55: =IF($M55="","",COUNTIF(O55:R55,"Y")) | T55: =IF($M55="","",SUMPRODUCT(MAX(('QC listings'!$A$5:$A$200=$M55)*'QC listings'!$E$5:$E$200))) | U55: =IF($M55="","",IF(T55>=Scoring!$B$11,3,IF(T55>=Scoring!$B$10,2,IF(T55>=Scoring!$B$9,1,0)))) | V55: =IFERROR(INDEX(Scoring!$B$27:$B$56,MATCH($E55,Scoring!$A$27:$A$56,0)),0) -> 0 | W55: =IF($G55="","",ROUND((Scoring!$B$5-$G55)/30.4375,1)) -> 2.2 | X55: =IF($F55="Expired",Scoring!$B$18,IF($G55="",Scoring!$B$17,IF(W55<=Scoring!$B$12,Scoring!$B$13,IF(W55<=Scoring!$B$14,Scoring!$B$15,Scoring!$B$16)))) -> 2 | Y55: =IF($M55="","",ROUND((S55*Scoring!$B$6+U55*Scoring!$B$7)*IFERROR(INDEX(Scoring!$B$22:$B$24,MATCH($N55,Scoring!$A$22:$A$24,0)),1)+V55*Scoring!$B$8+X55,2)) | Z55: =IF($M55="","",IF(SUMPRODUCT(($M$5:$M$249=$M55)*($G$5:$G$249>$G55))>0,0,IF(SUMPRODUCT(($M$5:$M$249=$M55)*($G$5:$G$249=$G55)*(ROW($M$5:$M$249)<ROW($M55)))>0,0,1))) | AA55: =IF($Z55=1,RANK($AE55,$AE$5:$AE$249,0),"") | AB55: Open | AC55: Link out; licence needed to display; run the PRD publication gate first (negative verdict) | AE55: =IF($Z55=1,$Y55+$T55/1000000000-ROW()/10000000,"")
A56: R052 | B56: MDH | C56: Chunky Chat Masala | D56: Everyday food | E56: Spices & masala | F56: Failed | G56: 46229 | H56: RJ-098 | I56: Eurofins | J56: Trustified Pass/Fail | L56: https://www.trustified.in/passandfail/mdhchunkychatmasala | O56: =IF($M56="","",IF(COUNTIFS('QC listings'!$A$5:$A$200,$M56,'QC listings'!$C$5:$C$200,O$4,'QC listings'!$F$5:$F$200,"Listing page")+COUNTIFS('QC listings'!$A$5:$A$200,$M56,'QC listings'!$C$5:$C$200,O$4,'QC listings'!$F$5:$F$200,"Brand page")>0,"Y",IF(COUNTIFS('QC listings'!$A$5:$A$200,$M56,'QC listings'!$C$5:$C$200,O$4)>0,"?","–"))) | P56: =IF($M56="","",IF(COUNTIFS('QC listings'!$A$5:$A$200,$M56,'QC listings'!$C$5:$C$200,P$4,'QC listings'!$F$5:$F$200,"Listing page")+COUNTIFS('QC listings'!$A$5:$A$200,$M56,'QC listings'!$C$5:$C$200,P$4,'QC listings'!$F$5:$F$200,"Brand page")>0,"Y",IF(COUNTIFS('QC listings'!$A$5:$A$200,$M56,'QC listings'!$C$5:$C$200,P$4)>0,"?","–"))) | Q56: =IF($M56="","",IF(COUNTIFS('QC listings'!$A$5:$A$200,$M56,'QC listings'!$C$5:$C$200,Q$4,'QC listings'!$F$5:$F$200,"Listing page")+COUNTIFS('QC listings'!$A$5:$A$200,$M56,'QC listings'!$C$5:$C$200,Q$4,'QC listings'!$F$5:$F$200,"Brand page")>0,"Y",IF(COUNTIFS('QC listings'!$A$5:$A$200,$M56,'QC listings'!$C$5:$C$200,Q$4)>0,"?","–"))) | R56: =IF($M56="","",IF(COUNTIFS('QC listings'!$A$5:$A$200,$M56,'QC listings'!$C$5:$C$200,R$4,'QC listings'!$F$5:$F$200,"Listing page")+COUNTIFS('QC listings'!$A$5:$A$200,$M56,'QC listings'!$C$5:$C$200,R$4,'QC listings'!$F$5:$F$200,"Brand page")>0,"Y",IF(COUNTIFS('QC listings'!$A$5:$A$200,$M56,'QC listings'!$C$5:$C$200,R$4)>0,"?","–"))) | S56: =IF($M56="","",COUNTIF(O56:R56,"Y")) | T56: =IF($M56="","",SUMPRODUCT(MAX(('QC listings'!$A$5:$A$200=$M56)*'QC listings'!$E$5:$E$200))) | U56: =IF($M56="","",IF(T56>=Scoring!$B$11,3,IF(T56>=Scoring!$B$10,2,IF(T56>=Scoring!$B$9,1,0)))) | V56: =IFERROR(INDEX(Scoring!$B$27:$B$56,MATCH($E56,Scoring!$A$27:$A$56,0)),0) -> 0 | W56: =IF($G56="","",ROUND((Scoring!$B$5-$G56)/30.4375,1)) -> 2.2 | X56: =IF($F56="Expired",Scoring!$B$18,IF($G56="",Scoring!$B$17,IF(W56<=Scoring!$B$12,Scoring!$B$13,IF(W56<=Scoring!$B$14,Scoring!$B$15,Scoring!$B$16)))) -> 2 | Y56: =IF($M56="","",ROUND((S56*Scoring!$B$6+U56*Scoring!$B$7)*IFERROR(INDEX(Scoring!$B$22:$B$24,MATCH($N56,Scoring!$A$22:$A$24,0)),1)+V56*Scoring!$B$8+X56,2)) | Z56: =IF($M56="","",IF(SUMPRODUCT(($M$5:$M$249=$M56)*($G$5:$G$249>$G56))>0,0,IF(SUMPRODUCT(($M$5:$M$249=$M56)*($G$5:$G$249=$G56)*(ROW($M$5:$M$249)<ROW($M56)))>0,0,1))) | AA56: =IF($Z56=1,RANK($AE56,$AE$5:$AE$249,0),"") | AB56: Open | AC56: Link out; licence needed to display; run the PRD publication gate first (negative verdict) | AE56: =IF($Z56=1,$Y56+$T56/1000000000-ROW()/10000000,"")
A57: R053 | B57: MDH | C57: Deggi Mirch | D57: Everyday food | E57: Spices & masala | F57: Failed | G57: 46229 | H57: FA-359 | I57: Eurofins | J57: Trustified Pass/Fail | L57: https://www.trustified.in/passandfail/mdhdeggimirch | M57: MDH-DEGGI | N57: Exact | O57: =IF($M57="","",IF(COUNTIFS('QC listings'!$A$5:$A$200,$M57,'QC listings'!$C$5:$C$200,O$4,'QC listings'!$F$5:$F$200,"Listing page")+COUNTIFS('QC listings'!$A$5:$A$200,$M57,'QC listings'!$C$5:$C$200,O$4,'QC listings'!$F$5:$F$200,"Brand page")>0,"Y",IF(COUNTIFS('QC listings'!$A$5:$A$200,$M57,'QC listings'!$C$5:$C$200,O$4)>0,"?","–"))) -> Y | P57: =IF($M57="","",IF(COUNTIFS('QC listings'!$A$5:$A$200,$M57,'QC listings'!$C$5:$C$200,P$4,'QC listings'!$F$5:$F$200,"Listing page")+COUNTIFS('QC listings'!$A$5:$A$200,$M57,'QC listings'!$C$5:$C$200,P$4,'QC listings'!$F$5:$F$200,"Brand page")>0,"Y",IF(COUNTIFS('QC listings'!$A$5:$A$200,$M57,'QC listings'!$C$5:$C$200,P$4)>0,"?","–"))) -> Y | Q57: =IF($M57="","",IF(COUNTIFS('QC listings'!$A$5:$A$200,$M57,'QC listings'!$C$5:$C$200,Q$4,'QC listings'!$F$5:$F$200,"Listing page")+COUNTIFS('QC listings'!$A$5:$A$200,$M57,'QC listings'!$C$5:$C$200,Q$4,'QC listings'!$F$5:$F$200,"Brand page")>0,"Y",IF(COUNTIFS('QC listings'!$A$5:$A$200,$M57,'QC listings'!$C$5:$C$200,Q$4)>0,"?","–"))) -> – | R57: =IF($M57="","",IF(COUNTIFS('QC listings'!$A$5:$A$200,$M57,'QC listings'!$C$5:$C$200,R$4,'QC listings'!$F$5:$F$200,"Listing page")+COUNTIFS('QC listings'!$A$5:$A$200,$M57,'QC listings'!$C$5:$C$200,R$4,'QC listings'!$F$5:$F$200,"Brand page")>0,"Y",IF(COUNTIFS('QC listings'!$A$5:$A$200,$M57,'QC listings'!$C$5:$C$200,R$4)>0,"?","–"))) -> Y | S57: =IF($M57="","",COUNTIF(O57:R57,"Y")) -> 3 | T57: =IF($M57="","",SUMPRODUCT(MAX(('QC listings'!$A$5:$A$200=$M57)*'QC listings'!$E$5:$E$200))) -> 9428 | U57: =IF($M57="","",IF(T57>=Scoring!$B$11,3,IF(T57>=Scoring!$B$10,2,IF(T57>=Scoring!$B$9,1,0)))) -> 1 | V57: =IFERROR(INDEX(Scoring!$B$27:$B$56,MATCH($E57,Scoring!$A$27:$A$56,0)),0) -> 0 | W57: =IF($G57="","",ROUND((Scoring!$B$5-$G57)/30.4375,1)) -> 2.2 | X57: =IF($F57="Expired",Scoring!$B$18,IF($G57="",Scoring!$B$17,IF(W57<=Scoring!$B$12,Scoring!$B$13,IF(W57<=Scoring!$B$14,Scoring!$B$15,Scoring!$B$16)))) -> 2 | Y57: =IF($M57="","",ROUND((S57*Scoring!$B$6+U57*Scoring!$B$7)*IFERROR(INDEX(Scoring!$B$22:$B$24,MATCH($N57,Scoring!$A$22:$A$24,0)),1)+V57*Scoring!$B$8+X57,2)) -> 7 | Z57: =IF($M57="","",IF(SUMPRODUCT(($M$5:$M$249=$M57)*($G$5:$G$249>$G57))>0,0,IF(SUMPRODUCT(($M$5:$M$249=$M57)*($G$5:$G$249=$G57)*(ROW($M$5:$M$249)<ROW($M57)))>0,0,1))) -> 1 | AA57: =IF($Z57=1,RANK($AE57,$AE$5:$AE$249,0),"") -> 19 | AB57: Open | AC57: Link out; licence needed to display; run the PRD publication gate first (negative verdict) | AD57: QC: Instamart listing not seen in my checks. | AE57: =IF($Z57=1,$Y57+$T57/1000000000-ROW()/10000000,"") -> 7.0000037
A58: R054 | B58: MDH | C58: Garam Masala | D58: Everyday food | E58: Spices & masala | F58: Failed | G58: 46229 | H58: RJ-092 | I58: Eurofins | J58: Trustified Pass/Fail | L58: https://www.trustified.in/passandfail/mdhgarammasala | O58: =IF($M58="","",IF(COUNTIFS('QC listings'!$A$5:$A$200,$M58,'QC listings'!$C$5:$C$200,O$4,'QC listings'!$F$5:$F$200,"Listing page")+COUNTIFS('QC listings'!$A$5:$A$200,$M58,'QC listings'!$C$5:$C$200,O$4,'QC listings'!$F$5:$F$200,"Brand page")>0,"Y",IF(COUNTIFS('QC listings'!$A$5:$A$200,$M58,'QC listings'!$C$5:$C$200,O$4)>0,"?","–"))) | P58: =IF($M58="","",IF(COUNTIFS('QC listings'!$A$5:$A$200,$M58,'QC listings'!$C$5:$C$200,P$4,'QC listings'!$F$5:$F$200,"Listing page")+COUNTIFS('QC listings'!$A$5:$A$200,$M58,'QC listings'!$C$5:$C$200,P$4,'QC listings'!$F$5:$F$200,"Brand page")>0,"Y",IF(COUNTIFS('QC listings'!$A$5:$A$200,$M58,'QC listings'!$C$5:$C$200,P$4)>0,"?","–"))) | Q58: =IF($M58="","",IF(COUNTIFS('QC listings'!$A$5:$A$200,$M58,'QC listings'!$C$5:$C$200,Q$4,'QC listings'!$F$5:$F$200,"Listing page")+COUNTIFS('QC listings'!$A$5:$A$200,$M58,'QC listings'!$C$5:$C$200,Q$4,'QC listings'!$F$5:$F$200,"Brand page")>0,"Y",IF(COUNTIFS('QC listings'!$A$5:$A$200,$M58,'QC listings'!$C$5:$C$200,Q$4)>0,"?","–"))) | R58: =IF($M58="","",IF(COUNTIFS('QC listings'!$A$5:$A$200,$M58,'QC listings'!$C$5:$C$200,R$4,'QC listings'!$F$5:$F$200,"Listing page")+COUNTIFS('QC listings'!$A$5:$A$200,$M58,'QC listings'!$C$5:$C$200,R$4,'QC listings'!$F$5:$F$200,"Brand page")>0,"Y",IF(COUNTIFS('QC listings'!$A$5:$A$200,$M58,'QC listings'!$C$5:$C$200,R$4)>0,"?","–"))) | S58: =IF($M58="","",COUNTIF(O58:R58,"Y")) | T58: =IF($M58="","",SUMPRODUCT(MAX(('QC listings'!$A$5:$A$200=$M58)*'QC listings'!$E$5:$E$200))) | U58: =IF($M58="","",IF(T58>=Scoring!$B$11,3,IF(T58>=Scoring!$B$10,2,IF(T58>=Scoring!$B$9,1,0)))) | V58: =IFERROR(INDEX(Scoring!$B$27:$B$56,MATCH($E58,Scoring!$A$27:$A$56,0)),0) -> 0 | W58: =IF($G58="","",ROUND((Scoring!$B$5-$G58)/30.4375,1)) -> 2.2 | X58: =IF($F58="Expired",Scoring!$B$18,IF($G58="",Scoring!$B$17,IF(W58<=Scoring!$B$12,Scoring!$B$13,IF(W58<=Scoring!$B$14,Scoring!$B$15,Scoring!$B$16)))) -> 2 | Y58: =IF($M58="","",ROUND((S58*Scoring!$B$6+U58*Scoring!$B$7)*IFERROR(INDEX(Scoring!$B$22:$B$24,MATCH($N58,Scoring!$A$22:$A$24,0)),1)+V58*Scoring!$B$8+X58,2)) | Z58: =IF($M58="","",IF(SUMPRODUCT(($M$5:$M$249=$M58)*($G$5:$G$249>$G58))>0,0,IF(SUMPRODUCT(($M$5:$M$249=$M58)*($G$5:$G$249=$G58)*(ROW($M$5:$M$249)<ROW($M58)))>0,0,1))) | AA58: =IF($Z58=1,RANK($AE58,$AE$5:$AE$249,0),"") | AB58: Open | AC58: Link out; licence needed to display; run the PRD publication gate first (negative verdict) | AE58: =IF($Z58=1,$Y58+$T58/1000000000-ROW()/10000000,"")
A59: R055 | B59: MDH | C59: Kitchen King | D59: Everyday food | E59: Spices & masala | F59: Failed | G59: 46229 | H59: RJ-090 | I59: Eurofins | J59: Trustified Pass/Fail | L59: https://www.trustified.in/passandfail/mdhkitchenking | O59: =IF($M59="","",IF(COUNTIFS('QC listings'!$A$5:$A$200,$M59,'QC listings'!$C$5:$C$200,O$4,'QC listings'!$F$5:$F$200,"Listing page")+COUNTIFS('QC listings'!$A$5:$A$200,$M59,'QC listings'!$C$5:$C$200,O$4,'QC listings'!$F$5:$F$200,"Brand page")>0,"Y",IF(COUNTIFS('QC listings'!$A$5:$A$200,$M59,'QC listings'!$C$5:$C$200,O$4)>0,"?","–"))) | P59: =IF($M59="","",IF(COUNTIFS('QC listings'!$A$5:$A$200,$M59,'QC listings'!$C$5:$C$200,P$4,'QC listings'!$F$5:$F$200,"Listing page")+COUNTIFS('QC listings'!$A$5:$A$200,$M59,'QC listings'!$C$5:$C$200,P$4,'QC listings'!$F$5:$F$200,"Brand page")>0,"Y",IF(COUNTIFS('QC listings'!$A$5:$A$200,$M59,'QC listings'!$C$5:$C$200,P$4)>0,"?","–"))) | Q59: =IF($M59="","",IF(COUNTIFS('QC listings'!$A$5:$A$200,$M59,'QC listings'!$C$5:$C$200,Q$4,'QC listings'!$F$5:$F$200,"Listing page")+COUNTIFS('QC listings'!$A$5:$A$200,$M59,'QC listings'!$C$5:$C$200,Q$4,'QC listings'!$F$5:$F$200,"Brand page")>0,"Y",IF(COUNTIFS('QC listings'!$A$5:$A$200,$M59,'QC listings'!$C$5:$C$200,Q$4)>0,"?","–"))) | R59: =IF($M59="","",IF(COUNTIFS('QC listings'!$A$5:$A$200,$M59,'QC listings'!$C$5:$C$200,R$4,'QC listings'!$F$5:$F$200,"Listing page")+COUNTIFS('QC listings'!$A$5:$A$200,$M59,'QC listings'!$C$5:$C$200,R$4,'QC listings'!$F$5:$F$200,"Brand page")>0,"Y",IF(COUNTIFS('QC listings'!$A$5:$A$200,$M59,'QC listings'!$C$5:$C$200,R$4)>0,"?","–"))) | S59: =IF($M59="","",COUNTIF(O59:R59,"Y")) | T59: =IF($M59="","",SUMPRODUCT(MAX(('QC listings'!$A$5:$A$200=$M59)*'QC listings'!$E$5:$E$200))) | U59: =IF($M59="","",IF(T59>=Scoring!$B$11,3,IF(T59>=Scoring!$B$10,2,IF(T59>=Scoring!$B$9,1,0)))) | V59: =IFERROR(INDEX(Scoring!$B$27:$B$56,MATCH($E59,Scoring!$A$27:$A$56,0)),0) -> 0 | W59: =IF($G59="","",ROUND((Scoring!$B$5-$G59)/30.4375,1)) -> 2.2 | X59: =IF($F59="Expired",Scoring!$B$18,IF($G59="",Scoring!$B$17,IF(W59<=Scoring!$B$12,Scoring!$B$13,IF(W59<=Scoring!$B$14,Scoring!$B$15,Scoring!$B$16)))) -> 2 | Y59: =IF($M59="","",ROUND((S59*Scoring!$B$6+U59*Scoring!$B$7)*IFERROR(INDEX(Scoring!$B$22:$B$24,MATCH($N59,Scoring!$A$22:$A$24,0)),1)+V59*Scoring!$B$8+X59,2)) | Z59: =IF($M59="","",IF(SUMPRODUCT(($M$5:$M$249=$M59)*($G$5:$G$249>$G59))>0,0,IF(SUMPRODUCT(($M$5:$M$249=$M59)*($G$5:$G$249=$G59)*(ROW($M$5:$M$249)<ROW($M59)))>0,0,1))) | AA59: =IF($Z59=1,RANK($AE59,$AE$5:$AE$249,0),"") | AB59: Open | AC59: Link out; licence needed to display; run the PRD publication gate first (negative verdict) | AE59: =IF($Z59=1,$Y59+$T59/1000000000-ROW()/10000000,"")
A60: R056 | B60: Bevzilla | C60: Premium Classic Coffee | D60: Everyday food | E60: Tea & coffee | F60: Failed | G60: 45914 | H60: 2918F25 | I60: Eurofins | J60: Trustified Pass/Fail | L60: https://www.trustified.in/passandfail/Bevzillaclassiccoffee | O60: =IF($M60="","",IF(COUNTIFS('QC listings'!$A$5:$A$200,$M60,'QC listings'!$C$5:$C$200,O$4,'QC listings'!$F$5:$F$200,"Listing page")+COUNTIFS('QC listings'!$A$5:$A$200,$M60,'QC listings'!$C$5:$C$200,O$4,'QC listings'!$F$5:$F$200,"Brand page")>0,"Y",IF(COUNTIFS('QC listings'!$A$5:$A$200,$M60,'QC listings'!$C$5:$C$200,O$4)>0,"?","–"))) | P60: =IF($M60="","",IF(COUNTIFS('QC listings'!$A$5:$A$200,$M60,'QC listings'!$C$5:$C$200,P$4,'QC listings'!$F$5:$F$200,"Listing page")+COUNTIFS('QC listings'!$A$5:$A$200,$M60,'QC listings'!$C$5:$C$200,P$4,'QC listings'!$F$5:$F$200,"Brand page")>0,"Y",IF(COUNTIFS('QC listings'!$A$5:$A$200,$M60,'QC listings'!$C$5:$C$200,P$4)>0,"?","–"))) | Q60: =IF($M60="","",IF(COUNTIFS('QC listings'!$A$5:$A$200,$M60,'QC listings'!$C$5:$C$200,Q$4,'QC listings'!$F$5:$F$200,"Listing page")+COUNTIFS('QC listings'!$A$5:$A$200,$M60,'QC listings'!$C$5:$C$200,Q$4,'QC listings'!$F$5:$F$200,"Brand page")>0,"Y",IF(COUNTIFS('QC listings'!$A$5:$A$200,$M60,'QC listings'!$C$5:$C$200,Q$4)>0,"?","–"))) | R60: =IF($M60="","",IF(COUNTIFS('QC listings'!$A$5:$A$200,$M60,'QC listings'!$C$5:$C$200,R$4,'QC listings'!$F$5:$F$200,"Listing page")+COUNTIFS('QC listings'!$A$5:$A$200,$M60,'QC listings'!$C$5:$C$200,R$4,'QC listings'!$F$5:$F$200,"Brand page")>0,"Y",IF(COUNTIFS('QC listings'!$A$5:$A$200,$M60,'QC listings'!$C$5:$C$200,R$4)>0,"?","–"))) | S60: =IF($M60="","",COUNTIF(O60:R60,"Y")) | T60: =IF($M60="","",SUMPRODUCT(MAX(('QC listings'!$A$5:$A$200=$M60)*'QC listings'!$E$5:$E$200))) | U60: =IF($M60="","",IF(T60>=Scoring!$B$11,3,IF(T60>=Scoring!$B$10,2,IF(T60>=Scoring!$B$9,1,0)))) | V60: =IFERROR(INDEX(Scoring!$B$27:$B$56,MATCH($E60,Scoring!$A$27:$A$56,0)),0) -> 0 | W60: =IF($G60="","",ROUND((Scoring!$B$5-$G60)/30.4375,1)) -> 12.6 | X60: =IF($F60="Expired",Scoring!$B$18,IF($G60="",Scoring!$B$17,IF(W60<=Scoring!$B$12,Scoring!$B$13,IF(W60<=Scoring!$B$14,Scoring!$B$15,Scoring!$B$16)))) -> 1 | Y60: =IF($M60="","",ROUND((S60*Scoring!$B$6+U60*Scoring!$B$7)*IFERROR(INDEX(Scoring!$B$22:$B$24,MATCH($N60,Scoring!$A$22:$A$24,0)),1)+V60*Scoring!$B$8+X60,2)) | Z60: =IF($M60="","",IF(SUMPRODUCT(($M$5:$M$249=$M60)*($G$5:$G$249>$G60))>0,0,IF(SUMPRODUCT(($M$5:$M$249=$M60)*($G$5:$G$249=$G60)*(ROW($M$5:$M$249)<ROW($M60)))>0,0,1))) | AA60: =IF($Z60=1,RANK($AE60,$AE$5:$AE$249,0),"") | AB60: Open | AC60: Link out; licence needed to display; run the PRD publication gate first (negative verdict) | AE60: =IF($Z60=1,$Y60+$T60/1000000000-ROW()/10000000,"")
A61: R057 | B61: Bevzilla | C61: Premium Coffee | D61: Everyday food | E61: Tea & coffee | F61: Failed | G61: 45914 | H61: 27C25 | I61: Eurofins | J61: Trustified Pass/Fail | L61: https://www.trustified.in/passandfail/bevzillapremiumcoffee | O61: =IF($M61="","",IF(COUNTIFS('QC listings'!$A$5:$A$200,$M61,'QC listings'!$C$5:$C$200,O$4,'QC listings'!$F$5:$F$200,"Listing page")+COUNTIFS('QC listings'!$A$5:$A$200,$M61,'QC listings'!$C$5:$C$200,O$4,'QC listings'!$F$5:$F$200,"Brand page")>0,"Y",IF(COUNTIFS('QC listings'!$A$5:$A$200,$M61,'QC listings'!$C$5:$C$200,O$4)>0,"?","–"))) | P61: =IF($M61="","",IF(COUNTIFS('QC listings'!$A$5:$A$200,$M61,'QC listings'!$C$5:$C$200,P$4,'QC listings'!$F$5:$F$200,"Listing page")+COUNTIFS('QC listings'!$A$5:$A$200,$M61,'QC listings'!$C$5:$C$200,P$4,'QC listings'!$F$5:$F$200,"Brand page")>0,"Y",IF(COUNTIFS('QC listings'!$A$5:$A$200,$M61,'QC listings'!$C$5:$C$200,P$4)>0,"?","–"))) | Q61: =IF($M61="","",IF(COUNTIFS('QC listings'!$A$5:$A$200,$M61,'QC listings'!$C$5:$C$200,Q$4,'QC listings'!$F$5:$F$200,"Listing page")+COUNTIFS('QC listings'!$A$5:$A$200,$M61,'QC listings'!$C$5:$C$200,Q$4,'QC listings'!$F$5:$F$200,"Brand page")>0,"Y",IF(COUNTIFS('QC listings'!$A$5:$A$200,$M61,'QC listings'!$C$5:$C$200,Q$4)>0,"?","–"))) | R61: =IF($M61="","",IF(COUNTIFS('QC listings'!$A$5:$A$200,$M61,'QC listings'!$C$5:$C$200,R$4,'QC listings'!$F$5:$F$200,"Listing page")+COUNTIFS('QC listings'!$A$5:$A$200,$M61,'QC listings'!$C$5:$C$200,R$4,'QC listings'!$F$5:$F$200,"Brand page")>0,"Y",IF(COUNTIFS('QC listings'!$A$5:$A$200,$M61,'QC listings'!$C$5:$C$200,R$4)>0,"?","–"))) | S61: =IF($M61="","",COUNTIF(O61:R61,"Y")) | T61: =IF($M61="","",SUMPRODUCT(MAX(('QC listings'!$A$5:$A$200=$M61)*'QC listings'!$E$5:$E$200))) | U61: =IF($M61="","",IF(T61>=Scoring!$B$11,3,IF(T61>=Scoring!$B$10,2,IF(T61>=Scoring!$B$9,1,0)))) | V61: =IFERROR(INDEX(Scoring!$B$27:$B$56,MATCH($E61,Scoring!$A$27:$A$56,0)),0) -> 0 | W61: =IF($G61="","",ROUND((Scoring!$B$5-$G61)/30.4375,1)) -> 12.6 | X61: =IF($F61="Expired",Scoring!$B$18,IF($G61="",Scoring!$B$17,IF(W61<=Scoring!$B$12,Scoring!$B$13,IF(W61<=Scoring!$B$14,Scoring!$B$15,Scoring!$B$16)))) -> 1 | Y61: =IF($M61="","",ROUND((S61*Scoring!$B$6+U61*Scoring!$B$7)*IFERROR(INDEX(Scoring!$B$22:$B$24,MATCH($N61,Scoring!$A$22:$A$24,0)),1)+V61*Scoring!$B$8+X61,2)) | Z61: =IF($M61="","",IF(SUMPRODUCT(($M$5:$M$249=$M61)*($G$5:$G$249>$G61))>0,0,IF(SUMPRODUCT(($M$5:$M$249=$M61)*($G$5:$G$249=$G61)*(ROW($M$5:$M$249)<ROW($M61)))>0,0,1))) | AA61: =IF($Z61=1,RANK($AE61,$AE$5:$AE$249,0),"") | AB61: Open | AC61: Link out; licence needed to display; run the PRD publication gate first (negative verdict) | AE61: =IF($Z61=1,$Y61+$T61/1000000000-ROW()/10000000,"")
A62: R058 | B62: Brooke Bond | C62: Taaza Tea | D62: Everyday food | E62: Tea & coffee | F62: Failed | G62: 46215 | H62: E14B | I62: Eurofins | J62: Trustified Pass/Fail | L62: https://www.trustified.in/passandfail/taazatea | M62: BB-TAAZA | N62: Exact | O62: =IF($M62="","",IF(COUNTIFS('QC listings'!$A$5:$A$200,$M62,'QC listings'!$C$5:$C$200,O$4,'QC listings'!$F$5:$F$200,"Listing page")+COUNTIFS('QC listings'!$A$5:$A$200,$M62,'QC listings'!$C$5:$C$200,O$4,'QC listings'!$F$5:$F$200,"Brand page")>0,"Y",IF(COUNTIFS('QC listings'!$A$5:$A$200,$M62,'QC listings'!$C$5:$C$200,O$4)>0,"?","–"))) -> Y | P62: =IF($M62="","",IF(COUNTIFS('QC listings'!$A$5:$A$200,$M62,'QC listings'!$C$5:$C$200,P$4,'QC listings'!$F$5:$F$200,"Listing page")+COUNTIFS('QC listings'!$A$5:$A$200,$M62,'QC listings'!$C$5:$C$200,P$4,'QC listings'!$F$5:$F$200,"Brand page")>0,"Y",IF(COUNTIFS('QC listings'!$A$5:$A$200,$M62,'QC listings'!$C$5:$C$200,P$4)>0,"?","–"))) -> Y | Q62: =IF($M62="","",IF(COUNTIFS('QC listings'!$A$5:$A$200,$M62,'QC listings'!$C$5:$C$200,Q$4,'QC listings'!$F$5:$F$200,"Listing page")+COUNTIFS('QC listings'!$A$5:$A$200,$M62,'QC listings'!$C$5:$C$200,Q$4,'QC listings'!$F$5:$F$200,"Brand page")>0,"Y",IF(COUNTIFS('QC listings'!$A$5:$A$200,$M62,'QC listings'!$C$5:$C$200,Q$4)>0,"?","–"))) -> – | R62: =IF($M62="","",IF(COUNTIFS('QC listings'!$A$5:$A$200,$M62,'QC listings'!$C$5:$C$200,R$4,'QC listings'!$F$5:$F$200,"Listing page")+COUNTIFS('QC listings'!$A$5:$A$200,$M62,'QC listings'!$C$5:$C$200,R$4,'QC listings'!$F$5:$F$200,"Brand page")>0,"Y",IF(COUNTIFS('QC listings'!$A$5:$A$200,$M62,'QC listings'!$C$5:$C$200,R$4)>0,"?","–"))) -> Y | S62: =IF($M62="","",COUNTIF(O62:R62,"Y")) -> 3 | T62: =IF($M62="","",SUMPRODUCT(MAX(('QC listings'!$A$5:$A$200=$M62)*'QC listings'!$E$5:$E$200))) -> 6869 | U62: =IF($M62="","",IF(T62>=Scoring!$B$11,3,IF(T62>=Scoring!$B$10,2,IF(T62>=Scoring!$B$9,1,0)))) -> 1 | V62: =IFERROR(INDEX(Scoring!$B$27:$B$56,MATCH($E62,Scoring!$A$27:$A$56,0)),0) -> 0 | W62: =IF($G62="","",ROUND((Scoring!$B$5-$G62)/30.4375,1)) -> 2.7 | X62: =IF($F62="Expired",Scoring!$B$18,IF($G62="",Scoring!$B$17,IF(W62<=Scoring!$B$12,Scoring!$B$13,IF(W62<=Scoring!$B$14,Scoring!$B$15,Scoring!$B$16)))) -> 2 | Y62: =IF($M62="","",ROUND((S62*Scoring!$B$6+U62*Scoring!$B$7)*IFERROR(INDEX(Scoring!$B$22:$B$24,MATCH($N62,Scoring!$A$22:$A$24,0)),1)+V62*Scoring!$B$8+X62,2)) -> 7 | Z62: =IF($M62="","",IF(SUMPRODUCT(($M$5:$M$249=$M62)*($G$5:$G$249>$G62))>0,0,IF(SUMPRODUCT(($M$5:$M$249=$M62)*($G$5:$G$249=$G62)*(ROW($M$5:$M$249)<ROW($M62)))>0,0,1))) -> 1 | AA62: =IF($Z62=1,RANK($AE62,$AE$5:$AE$249,0),"") -> 20 | AB62: Open | AC62: Link out; licence needed to display; run the PRD publication gate first (negative verdict) | AD62: QC: Instamart not seen. | AE62: =IF($Z62=1,$Y62+$T62/1000000000-ROW()/10000000,"") -> 7.0000007
